Workbook
Name AÑO: [1]FILTROS!$A$1:$A$6
Name base: #REF!

Sheet VTA POR EMPLEADO
A3: Etiquetas de fila | B3: Suma de SUBTOT
A4: Arcos-C | B4: 154973.17
A5: ANGEL DANILO RODRIGUEZ LOPEZ | B5: 793.09
A6: GERMAN GUZMAN AGUIRRE | B6: 6775.85
A7: JESáS ULISES PEREZ VARGAS | B7: 1788.77
A8: NOE JONAS D CEL | B8: 145615.46
A9: Camino Real -C | B9: 161222.14
A10: ALFONSO M CARBALLAR | B10: 6689.64
A11: JESáS ULISES PEREZ VARGAS | B11: 689.65
A12: JESUS ALBERTO M GARCIA | B12: 153842.85
A13: Circunvalación CELESTERRA | B13: 126589.95
A14: ANGEL DANILO RODRIGUEZ LOPEZ | B14: 11926.74
A15: GERMAN GUZMAN AGUIRRE | B15: 6577.6
... A73: Total general | B73: 2192772.6

Sheet BASE GENERAL
H2: 2139 | I2: =I3/H2 -> 1.916316
I3: =SUM(I5:I3114) -> 4099 | J3: =SUM(J5:J3114) -> 2192772.6
B4: UBICACION | C4: FECHA | D4: VENDEDOR | E4: SKU | F4: ARTICULO | G4: FAMILIA COMERCIAL | H4: MARCA | I4: CANTIDAD | J4: SUBTOT
B5: Arcos-C | C5: 02/01/2026 | D5: NOE JONAS D CEL | E5: 7503013378652 | F5: Liquid Love Backdoor 100ml - DUSA | G5: CONSUMIBLE PROPIO | H5: DUSA | I5: 1 | J5: 1077.59
B6: Arcos-C | C6: 02/01/2026 | D6: NOE JONAS D CEL | E6: 7503013378690 | F6: Shumatsu 3 pzas - DUSA | G6: CONSUMIBLE PROPIO | H6: DUSA | I6: 1 | J6: 577.59
B7: Arcos-C | C7: 03/01/2026 | D7: NOE JONAS D CEL | E7: 7503014914002 | F7: CAPSULAS MULTIORGASMICO AMO O-GEN | G7: CONSUMIBLE | H7: POWER MAN | I7: 1 | J7: 431.04
B8: Arcos-C | C8: 03/01/2026 | D8: NOE JONAS D CEL | E8: 8699415912859 | F8: Miel Vigorizante para Hombre Miracle Honey VIP 15g- SECRET MIRACLE HONEY | G8: CONSUMIBLE | H8: SECRET MIRACLE HONEY | I8: 1 | J8: 215.52
B9: Arcos-C | C9: 03/01/2026 | D9: NOE JONAS D CEL | E9: 7503023462891 | F9: ORAL SEX Exotic Nut 30ml - DIAMANTE | G9: CONSUMIBLE | H9: DIAMANTE | I9: 1 | J9: 310.35
B10: Arcos-C | C10: 03/01/2026 | D10: NOE JONAS D CEL | E10: 7503032300443 | F10: Zoe bala vibradora RETAIL - CXO | G10: JUGUETE PROPIO | H10: CXO | I10: 2 | J10: 310.34
B11: Arcos-C | C11: 04/01/2026 | D11: ANGEL DANILO RODRIGUEZ LOPEZ | E11: 7502214982477 | F11: Condon Fresa 3pzs - PRUDENCE | G11: CONSUMIBLE | H11: PRUDENCE | I11: 1 | J11: 60.34
B12: Arcos-C | C12: 04/01/2026 | D12: ANGEL DANILO RODRIGUEZ LOPEZ | E12: 7503032300993 | F12: Liquid Love Pleasure 30ml - DUSA | G12: CONSUMIBLE PROPIO | H12: DUSA | I12: 1 | J12: 301.72
B13: Arcos-C | C13: 04/01/2026 | D13: ANGEL DANILO RODRIGUEZ LOPEZ | E13: 7503050524241 | F13: Orgasmik 30ml - DUSA | G13: CONSUMIBLE PROPIO | H13: DUSA | I13: 1 | J13: 431.03
B14: Arcos-C | C14: 05/01/2026 | D14: NOE JONAS D CEL | E14: 7503030211021 | F14: Anillo desechable para pene Donut - CXO | G14: JUGUETE PROPIO | H14: CXO | I14: 1 | J14: 34.48
B15: Arcos-C | C15: 05/01/2026 | D15: NOE JONAS D CEL | E15: 7503043917081 | F15: Blade rosa anillo vibrador - CXO | G15: JUGUETE PROPIO | H15: CXO | I15: 1 | J15: 81.9
B16: Arcos-C | C16: 05/01/2026 | D16: NOE JONAS D CEL | E16: 7503013378492 | F16: Clean Whisper 120ml - DUSA | G16: CONSUMIBLE PROPIO | H16: DUSA | I16: 1 | J16: 301.72
... B52: Arcos-C | C52: 09/01/2026 | D52: NOE JONAS D CEL | E52: 7503013378980 | F52: Lubricante Body Surf Termico Chicle DUSA 60ml | G52: CONSUMIBLE PROPIO | H52: DUSA | I52: 1 | J52: 387.93
B53: Arcos-C | C53: 09/01/2026 | D53: NOE JONAS D CEL | E53: 695963319882 | F53: Masturbador Recargable Hannes NEO - SVAKOM | H53: SVAKOM | I53: 1 | J53: 2586.21
B54: Arcos-C | C54: 09/01/2026 | D54: NOE JONAS D CEL | E54: 716770096036 | F54: Sheology set intercambiable kegel - CALEX | G54: JUGUETE | H54: CALEXOTICS | I54: 1 | J54: 1637.93
B55: Arcos-C | C55: 09/01/2026 | D55: NOE JONAS D CEL | E55: CBD | F55: SUNNY SIDE UP CBD HIPOALERGENICO 10ml | G55: CONSUMIBLE | H55: SUNNY SIDE UP | I55: 1 | J55: 301.72
B56: Arcos-C | C56: 09/01/2026 | D56: NOE JONAS D CEL | E56: 716770065742 | F56: The Accommodator dildo de latex - CALEX | G56: JUGUETE | H56: CALEXOTICS | I56: 1 | J56: 775.86
B57: Arcos-C | C57: 09/01/2026 | D57: NOE JONAS D CEL | E57: 7503020104075 | F57: Vibrador multiorgásmico texturizado con succionador de clítoris Yeni - CXO | G57: JUGUETE PROPIO | H57: CXO | I57: 1 | J57: 2465.52
B58: Arcos-C | C58: 10/01/2026 | D58: NOE JONAS D CEL | E58: 7503043917081 | F58: Blade rosa anillo vibrador - CXO | G58: JUGUETE PROPIO | H58: CXO | I58: 4 | J58: 327.6
B59: Arcos-C | C59: 10/01/2026 | D59: NOE JONAS D CEL | E59: 7508304288412 | F59: FEROMONAS EN GEL 20ML HOMBRE HOMBRE | G59: CONSUMIBLE | H59: DIAMANTE | I59: 1 | J59: 379.31
B60: Arcos-C | C60: 10/01/2026 | D60: NOE JONAS D CEL | E60: 7503043917012 | F60: Liquid Love Backdoor 30ml - DUSA | G60: CONSUMIBLE PROPIO | H60: DUSA | I60: 1 | J60: 301.72
B61: Arcos-C | C61: 10/01/2026 | D61: NOE JONAS D CEL | E61: 7503013378645 | F61: Liquid Love Pleasure 100ml - DUSA | G61: CONSUMIBLE PROPIO | H61: DUSA | I61: 1 | J61: 775.86
B62: Arcos-C | C62: 10/01/2026 | D62: NOE JONAS D CEL | E62: 7503024256154 | F62: Lubricante Body Surf Termico Cereza DUSA 60ml | G62: CONSUMIBLE PROPIO | H62: DUSA | I62: 1 | J62: 387.93
B63: Arcos-C | C63: 10/01/2026 | D63: NOE JONAS D CEL | E63: 8699415912859 | F63: Miel Vigorizante para Hombre Miracle Honey VIP 15g- SECRET MIRACLE HONEY | G63: CONSUMIBLE | H63: SECRET MIRACLE HONEY | I63: 2 | J63: 431.03
B64: Arcos-C | C64: 10/01/2026 | D64: NOE JONAS D CEL | E64: 7503013378010 | F64: Rigidex 2 pzas - DUSA | G64: CONSUMIBLE PROPIO | H64: DUSA | I64: 3 | J64: 1293.1
B65: Arcos-C | C65: 10/01/2026 | D65: NOE JONAS D CEL | E65: 7503020596049 | F65: Sensicool - DUSA | G65: CONSUMIBLE PROPIO | H65: DUSA | I65: 1 | J65: 431.03
... B93: Arcos-C | C93: 15/01/2026 | D93: NOE JONAS D CEL | E93: 7503023462259 | F93: Lubricante Masaje Térmico Comestible Frutas Prohibidas FEEL LOVE 4 en 1 - 60ml | G93: LUBRICANTE | H93: FEEL LOVE | I93: 1 | J93: 344.83
B94: Arcos-C | C94: 15/01/2026 | D94: NOE JONAS D CEL | E94: 695963319882 | F94: Masturbador Recargable Hannes NEO - SVAKOM | H94: SVAKOM | I94: 1 | J94: 2586.21
B95: Arcos-C | C95: 15/01/2026 | D95: NOE JONAS D CEL | E95: 75079413 | F95: Mini Kit Hombre 3 piezas - SXO | G95: CONSUMIBLE | H95: SXO | I95: 1 | J95: 284.48
B96: Arcos-C | C96: 15/01/2026 | D96: NOE JONAS D CEL | E96: 75079390 | F96: Mini Kit Mujer 3 piezas- SXO | G96: CONSUMIBLE | H96: SXO | I96: 2 | J96: 568.97
B97: Arcos-C | C97: 15/01/2026 | D97: NOE JONAS D CEL | E97: USK-V11 | F97: Multiorgasmico con Lenguita Ceci - CXO | G97: JUGUETE PROPIO | H97: CXO | I97: 1 | J97: 2474.14
B98: Arcos-C | C98: 15/01/2026 | D98: NOE JONAS D CEL | E98: 7503050524241 | F98: Orgasmik 30ml - DUSA | G98: CONSUMIBLE PROPIO | H98: DUSA | I98: 3 | J98: 1293.09
B99: Arcos-C | C99: 15/01/2026 | D99: NOE JONAS D CEL | E99: 7503013378010 | F99: Rigidex 2 pzas - DUSA | G99: CONSUMIBLE PROPIO | H99: DUSA | I99: 1 | J99: 431.03
B100: Arcos-C | C100: 15/01/2026 | D100: NOE JONAS D CEL | E100: 6959633156094 | F100: Robin - SVAKOM | G100: JUGUETE | H100: SVAKOM | I100: 1 | J100: 1318.97
B101: Arcos-C | C101: 15/01/2026 | D101: NOE JONAS D CEL | E101: 7503020596049 | F101: Sensicool - DUSA | G101: CONSUMIBLE PROPIO | H101: DUSA | I101: 1 | J101: 431.03
B102: Arcos-C | C102: 15/01/2026 | D102: NOE JONAS D CEL | E102: 7503050524258 | F102: Sensicool 30ml - DUSA | G102: CONSUMIBLE PROPIO | H102: DUSA | I102: 2 | J102: 862.07
B103: Arcos-C | C103: 15/01/2026 | D103: NOE JONAS D CEL | E103: 7503032300443 | F103: Zoe bala vibradora RETAIL - CXO | G103: JUGUETE PROPIO | H103: CXO | I103: 1 | J103: 155.17
B104: Arcos-C | C104: 16/01/2026 | D104: NOE JONAS D CEL | E104: 7503013378690 | F104: Shumatsu 3 pzas - DUSA | G104: CONSUMIBLE PROPIO | H104: DUSA | I104: 1 | J104: 577.59
B105: Arcos-C | C105: 17/01/2026 | D105: NOE JONAS D CEL | E105: 7503030211021 | F105: Anillo desechable para pene Donut - CXO | G105: JUGUETE PROPIO | H105: CXO | I105: 1 | J105: 34.48
B106: Arcos-C | C106: 17/01/2026 | D106: NOE JONAS D CEL | E106: 7503020111072 | F106: Anillo vibrador recargable con textura negra Hank - CXO | G106: JUGUETE PROPIO | H106: CXO | I106: 1 | J106: 1267.24
... B1765: Plaza Alamo CELESTERRA | C1765: 11/01/2026 | D1765: DELIA AGUIRRE CERVANTES | E1765: 7503032300993 | F1765: Liquid Love Pleasure 30ml - DUSA | G1765: CONSUMIBLE PROPIO | H1765: DUSA | I1765: 1 | J1765: 301.72
B1766: Plaza Alamo CELESTERRA | C1766: 11/01/2026 | D1766: DELIA AGUIRRE CERVANTES | E1766: 695963319882 | F1766: Masturbador Recargable Hannes NEO - SVAKOM | H1766: SVAKOM | I1766: 1 | J1766: 2586.21
B1767: Plaza Alamo CELESTERRA | C1767: 11/01/2026 | D1767: DELIA AGUIRRE CERVANTES | E1767: 714718001654 | F1767: MEDIAS DE NYLON EN ENCAJE NUDE 1011 | G1767: LENCERIA | H1767: LEG AVENUE | I1767: 1 | J1767: 172.41
B1768: Plaza Alamo CELESTERRA | C1768: 11/01/2026 | D1768: DELIA AGUIRRE CERVANTES | E1768: 7503032300856 | F1768: Sachet vibrador liquido 2 ml - BANANA SHAKE | G1768: CONSUMIBLE | H1768: BANANA SHAKE | I1768: 1 | J1768: 17.24
B1769: Plaza Alamo CELESTERRA | C1769: 11/01/2026 | D1769: DELIA AGUIRRE CERVANTES | E1769: 7503020596957 | F1769: Shot Shumatsu Fun Hombre - DUSA | G1769: CONSUMIBLE PROPIO | H1769: DUSA | I1769: 1 | J1769: 172.41
B1770: Plaza Alamo CELESTERRA | C1770: 11/01/2026 | D1770: DELIA AGUIRRE CERVANTES | E1770: 7503024256192 | F1770: Shot Shumatsu Fun Mujer - DUSA | G1770: CONSUMIBLE PROPIO | H1770: DUSA | I1770: 1 | J1770: 172.41
B1771: Plaza Alamo CELESTERRA | C1771: 11/01/2026 | D1771: DELIA AGUIRRE CERVANTES | E1771: 7501513758042 | F1771: TANGA MASCULINA GSTRING AZUL MARINO UNITALLA | G1771: LENCERIA | H1771: ADRENALINE | I1771: 1 | J1771: 258.62
B1772: Plaza Alamo CELESTERRA | C1772: 12/01/2026 | D1772: DELIA AGUIRRE CERVANTES | E1772: 7503043917036 | F1772: Arnes universal de argolla negro - CXO | G1772: JUGUETE PROPIO | H1772: CXO | I1772: 1 | J1772: 474.14
B1773: Plaza Alamo CELESTERRA | C1773: 12/01/2026 | D1773: DELIA AGUIRRE CERVANTES | E1773: 7502214982514 | F1773: Condon Chocolate 3 pzs - PRUDENCE | G1773: CONSUMIBLE | H1773: PRUDENCE | I1773: 1 | J1773: 60.34
B1774: Plaza Alamo CELESTERRA | C1774: 12/01/2026 | D1774: DELIA AGUIRRE CERVANTES | E1774: 7503043917005 | F1774: Liquid Love Clear 30ml - DUSA | G1774: CONSUMIBLE PROPIO | H1774: DUSA | I1774: 1 | J1774: 301.72
B1775: Plaza Alamo CELESTERRA | C1775: 12/01/2026 | D1775: DELIA AGUIRRE CERVANTES | E1775: 7503032300993 | F1775: Liquid Love Pleasure 30ml - DUSA | G1775: CONSUMIBLE PROPIO | H1775: DUSA | I1775: 1 | J1775: 301.72
B1776: Plaza Alamo CELESTERRA | C1776: 12/01/2026 | D1776: DELIA AGUIRRE CERVANTES | E1776: 7503023462235 | F1776: Lubricante Masaje Térmico Comestible Piña Colada FEEL LOVE 4 en 1 - 60ml | G1776: LUBRICANTE | H1776: FEEL LOVE | I1776: 1 | J1776: 344.83
B1777: Plaza Alamo CELESTERRA | C1777: 12/01/2026 | D1777: DELIA AGUIRRE CERVANTES | E1777: 7503026484845 | F1777: Oral Sex Erotic Nut 5g - Feel Love | G1777: CONSUMIBLE | H1777: DIAMANTE | I1777: 1 | J1777: 51.72
B1778: Plaza Alamo CELESTERRA | C1778: 12/01/2026 | D1778: DELIA AGUIRRE CERVANTES | E1778: 4061504007496 | F1778: Succionado con App Curvy 1+ - Satisfayer | G1778: JUGUETE | H1778: SATISFAYER | I1778: 1 | J1778: 1810.34
... B3114: Provenza-Cel | C3114: 31/01/2026 | D3114: ANGEL DANILO RODRIGUEZ LOPEZ | E3114: 7503032300443 | F3114: Zoe bala vibradora RETAIL - CXO | G3114: JUGUETE PROPIO | H3114: CXO | I3114: 1 | J3114: 155.17

Sheet semana 4
B4: UBICACION | C4: FECHA | D4: VENDEDOR | E4: SKU | F4: ARTICULO | G4: FAMILIA COMERCIAL | H4: MARCA | I4: CANTIDAD | J4: SUBTOT
B5: Arcos-C | C5: 26/01/2026 | D5: NOE JONAS D CEL | E5: 7503013378645 | F5: Liquid Love Pleasure 100ml - DUSA | G5: CONSUMIBLE PROPIO | H5: DUSA | I5: 1 | J5: 775.86 | P5: dias de cuota
B6: Arcos-C | C6: 27/01/2026 | D6: NOE JONAS D CEL | E6: 7503043917081 | F6: Blade rosa anillo vibrador - CXO | G6: JUGUETE PROPIO | H6: CXO | I6: 1 | J6: 81.9 | L6: Etiquetas de fila | M6: Suma de SUBTOT | N6: 0.01 | O6: ppto | P6: 6
B7: Arcos-C | C7: 27/01/2026 | D7: NOE JONAS D CEL | E7: 68100P | F7: Conjunto bordado Paty 2 piezas M | G7: LENCERIA | H7: OLA MOU | I7: 1 | J7: 260.34 | L7: Arcos-C | M7: 28271.56 | O7: 200000 | P7: =O7/31*$P$6 -> 38709.677
B8: Arcos-C | C8: 27/01/2026 | D8: NOE JONAS D CEL | E8: 7503043917005 | F8: Liquid Love Clear 30ml - DUSA | G8: CONSUMIBLE PROPIO | H8: DUSA | I8: 1 | J8: 301.72 | L8: Camino Real -C | M8: 29676.7 | O8: 175000 | P8: =O8/31*$P$6 -> 33870.968
B9: Arcos-C | C9: 27/01/2026 | D9: NOE JONAS D CEL | E9: 7503013378799 | F9: Lubricante Body Surf Termico Citricos DUSA 60ml | G9: CONSUMIBLE PROPIO | H9: DUSA | I9: 1 | J9: 387.93 | L9: Circunvalación CELESTERRA | M9: 36557.21 | N9: =GETPIVOTDATA("SUBTOT",$L$6,"UBICACION","Circunvalación CELESTERRA")*N6 -> 365.5721 | O9: 110000 | P9: =O9/31*$P$6 -> 21290.323
B10: Arcos-C | C10: 27/01/2026 | D10: NOE JONAS D CEL | E10: 6959633127964 | F10: Sam Neo - SVAKOM | G10: JUGUETE | H10: SVAKOM | I10: 1 | J10: 3017.24 | L10: Conchitas CEL | M10: 27022.09 | O10: 210000 | P10: =O10/31*$P$6 -> 40645.161
B11: Arcos-C | C11: 28/01/2026 | D11: NOE JONAS D CEL | E11: 68213T | F11: Conjunto rosa con estampado de flores Tania 2 piezas M | G11: LENCERIA | H11: OLA MOU | I11: 1 | J11: 260.34 | L11: Federalismo CEL | M11: 11499.97 | O11: 100000 | P11: =O11/31*$P$6 -> 19354.839
B12: Arcos-C | C12: 28/01/2026 | D12: NOE JONAS D CEL | E12: 6959633166963 | F12: Ella Neo rojo- SVAKOM | G12: JUGUETE | H12: SVAKOM | I12: 1 | J12: 3017.24 | L12: Hidalgo CEL | M12: 17064.6 | O12: 120000 | P12: =O12/31*$P$6 -> 23225.806
B13: Arcos-C | C13: 28/01/2026 | D13: NOE JONAS D CEL | E13: 7503043917012 | F13: Liquid Love Backdoor 30ml - DUSA | G13: CONSUMIBLE PROPIO | H13: DUSA | I13: 1 | J13: 301.72 | L13: Hotel los Reyes CEL | M13: 10698.24 | O13: 100000 | P13: =O13/31*$P$6 -> 19354.839
B14: Arcos-C | C14: 28/01/2026 | D14: NOE JONAS D CEL | E14: GWPS_BANANASHAKE_001 | F14: Lub de Regalo - Banana Shake | G14: ACTIVACION | H14: BANANA SHAKE | I14: 1 | J14: 0.01 | L14: León 1 CEL | M14: 12025.79 | O14: 100000 | P14: =O14/31*$P$6 -> 19354.839
B15: Arcos-C | C15: 28/01/2026 | D15: NOE JONAS D CEL | E15: 7503032300825 | F15: Lubricante Sachet natural 2 ml - BANANA SHAKE | G15: CONSUMIBLE | H15: BANANA SHAKE | I15: 1 | J15: 17.24 | L15: Naciones Unidas CEL | M15: 28208.38 | N15: =GETPIVOTDATA("SUBTOT",$L$6,"UBICACION","Naciones Unidas CEL")*N6 -> 282.0838 | O15: 100000 | P15: =O15/31*$P$6 -> 19354.839
B16: Arcos-C | C16: 28/01/2026 | D16: NOE JONAS D CEL | E16: 7503032300443 | F16: Zoe bala vibradora RETAIL - CXO | G16: JUGUETE PROPIO | H16: CXO | I16: 2 | J16: 310.34 | L16: Patria -CEL | M16: 35288.77 | O16: 185000 | P16: =O16/31*$P$6 -> 35806.452
B17: Arcos-C | C17: 29/01/2026 | D17: NOE JONAS D CEL | E17: 7503020202214 | F17: Dildo realista con ventosa y testiculos Eddy - CXO | G17: JUGUETE PROPIO | H17: CXO | I17: 1 | J17: 948.28 | L17: Plaza Alamo CELESTERRA | M17: 13939.63 | O17: 100000 | P17: =O17/31*$P$6 -> 19354.839
B18: Arcos-C | C18: 29/01/2026 | D18: NOE JONAS D CEL | E18: 7503013378652 | F18: Liquid Love Backdoor 100ml - DUSA | G18: CONSUMIBLE PROPIO | H18: DUSA | I18: 1 | J18: 1077.59 | L18: Plaza Conchitas CEL | M18: 37271.43 | N18: =GETPIVOTDATA("SUBTOT",$L$6,"UBICACION","Plaza Conchitas CEL")*N6 -> 372.7143 | O18: 150000 | P18: =O18/31*$P$6 -> 29032.258
B19: Arcos-C | C19: 29/01/2026 | D19: NOE JONAS D CEL | E19: 7503013378645 | F19: Liquid Love Pleasure 100ml - DUSA | G19: CONSUMIBLE PROPIO | H19: DUSA | I19: 1 | J19: 775.86 | L19: Plaza las Torres CELESTERRA | M19: 21185.31 | O19: 180000 | P19: =O19/31*$P$6 -> 34838.71
B20: Arcos-C | C20: 29/01/2026 | D20: NOE JONAS D CEL | E20: 7503024256154 | F20: Lubricante Body Surf Termico Cereza DUSA 60ml | G20: CONSUMIBLE PROPIO | H20: DUSA | I20: 1 | J20: 387.93 | L20: Plaza Madison -CEL | M20: 13560.3 | O20: 115000 | P20: =O20/31*$P$6 -> 22258.065
B21: Arcos-C | C21: 29/01/2026 | D21: NOE JONAS D CEL | E21: 7503020596957 | F21: Shot Shumatsu Fun Hombre - DUSA | G21: CONSUMIBLE PROPIO | H21: DUSA | I21: 2 | J21: 344.82 | L21: Plaza Sauces CEL | M21: 21732.8 | O21: 155000 | P21: =O21/31*$P$6 -> 30000
B22: Arcos-C | C22: 29/01/2026 | D22: NOE JONAS D CEL | E22: 7503032300443 | F22: Zoe bala vibradora RETAIL - CXO | G22: JUGUETE PROPIO | H22: CXO | I22: 1 | J22: 155.17 | L22: Plaza Zenter CEL | M22: 43306.03 | O22: 435000 | P22: =O22/31*$P$6 -> 84193.548
B23: Arcos-C | C23: 30/01/2026 | D23: NOE JONAS D CEL | E23: 7503013378119 | F23: Anastasia gema de colores S - CXO | G23: JUGUETE PROPIO | H23: CXO | I23: 1 | J23: 396.55 | L23: Provenza-Cel | M23: 39336.69 | N23: =GETPIVOTDATA("SUBTOT",$L$6,"UBICACION","Provenza-Cel")*N6 -> 393.3669 | O23: 145000 | P23: =O23/31*$P$6 -> 28064.516
B24: Arcos-C | C24: 30/01/2026 | D24: NOE JONAS D CEL | E24: 7503043917081 | F24: Blade rosa anillo vibrador - CXO | G24: JUGUETE PROPIO | H24: CXO | I24: 3 | J24: 245.7 | L24: Total general | M24: 426645.5 | N24: =SUM(N7:N23) -> 1413.7371 | O24: =SUM(O7:O23) -> 2680000 | P24: =SUM(P7:P23) -> 518709.68
B25: Arcos-C | C25: 30/01/2026 | D25: NOE JONAS D CEL | E25: 66096A | F25: Conjunto Andrea negro de encaje 3 piezas M | G25: LENCERIA | H25: OLA MOU | I25: 1 | J25: 371.55
B26: Arcos-C | C26: 30/01/2026 | D26: NOE JONAS D CEL | E26: 75037628 | F26: Dulces Garganta Profunda 2 piezas Sabor Fresa - SXO | G26: CONSUMIBLE | H26: SXO | I26: 1 | J26: 120.69
B27: Arcos-C | C27: 30/01/2026 | D27: NOE JONAS D CEL | E27: 7503043917012 | F27: Liquid Love Backdoor 30ml - DUSA | G27: CONSUMIBLE PROPIO | H27: DUSA | I27: 1 | J27: 301.72
B28: Arcos-C | C28: 30/01/2026 | D28: NOE JONAS D CEL | E28: GWPS_BANANASHAKE_001 | F28: Lub de Regalo - Banana Shake | G28: ACTIVACION | H28: BANANA SHAKE | I28: 1 | J28: 0.01
B29: Arcos-C | C29: 30/01/2026 | D29: NOE JONAS D CEL | E29: 7503023462204 | F29: Lubricante Masaje Térmico Comestible Manzana del Edén FEEL LOVE 4 en 1 - 60ml | G29: LUBRICANTE | H29: FEEL LOVE | I29: 1 | J29: 344.83
B30: Arcos-C | C30: 30/01/2026 | D30: NOE JONAS D CEL | E30: 782421007607 | F30: Reverse Tightening gel 0.25oz - DOC JOHNSON | G30: CONSUMIBLE | H30: DOC JOHNSON | I30: 2 | J30: 137.94
B31: Arcos-C | C31: 30/01/2026 | D31: NOE JONAS D CEL | E31: 7503013378690 | F31: Shumatsu 3 pzas - DUSA | G31: CONSUMIBLE PROPIO | H31: DUSA | I31: 1 | J31: 577.59
B32: Arcos-C | C32: 30/01/2026 | D32: NOE JONAS D CEL | E32: 7503020104073 | F32: Vibrador multiorgásmico con textura y estimulación doble Lidia - CXO | G32: JUGUETE PROPIO | H32: CXO | I32: 1 | J32: 2008.62
B33: Arcos-C | C33: 31/01/2026 | D33: NOE JONAS D CEL | E33: 7503020111072 | F33: Anillo vibrador recargable con textura negra Hank - CXO | G33: JUGUETE PROPIO | H33: CXO | I33: 1 | J33: 1267.24
B34: Arcos-C | C34: 31/01/2026 | D34: NOE JONAS D CEL | E34: 7503043917081 | F34: Blade rosa anillo vibrador - CXO | G34: JUGUETE PROPIO | H34: CXO | I34: 4 | J34: 327.6
B35: Arcos-C | C35: 31/01/2026 | D35: NOE JONAS D CEL | E35: 7503013378904 | F35: Dildo Mr. Hernandez - CXO | G35: JUGUETE PROPIO | H35: CXO | I35: 1 | J35: 517.24
B36: Arcos-C | C36: 31/01/2026 | D36: NOE JONAS D CEL | E36: LL-A2216 | F36: Huevito con 10 modos de Vibración Gina - CXO | G36: JUGUETE PROPIO | H36: CXO | I36: 1 | J36: 1500
... B617: Provenza-Cel | C617: 31/01/2026 | D617: ANGEL DANILO RODRIGUEZ LOPEZ | E617: 7503032300443 | F617: Zoe bala vibradora RETAIL - CXO | G617: JUGUETE PROPIO | H617: CXO | I617: 1 | J617: 155.17

Sheet Semana 3
B4: UBICACION | C4: FECHA | D4: VENDEDOR | E4: SKU | F4: ARTICULO | G4: FAMILIA COMERCIAL | H4: MARCA | I4: CANTIDAD | J4: SUBTOT | P4: dias de cuota
B5: Arcos-C | C5: 21/01/2026 | D5: NOE JONAS D CEL | E5: 7503030211021 | F5: Anillo desechable para pene Donut - CXO | G5: JUGUETE PROPIO | H5: CXO | I5: 1 | J5: 34.48 | L5: Etiquetas de fila | M5: Suma de SUBTOT | N5: 0.01 | O5: ppto | P5: 7
B6: Arcos-C | C6: 21/01/2026 | D6: NOE JONAS D CEL | E6: 7503024256741 | F6: Cola de Zorro 45cm café S - CXO | G6: JUGUETE PROPIO | H6: CXO | I6: 1 | J6: 258.62 | L6: Arcos-C | M6: 32439.58 | O6: 200000 | P6: =O6/31*$P$5 -> 45161.29
B7: Arcos-C | C7: 21/01/2026 | D7: NOE JONAS D CEL | E7: 7503020202213 | F7: Dildo realista con ventosa Nick - CXO | G7: JUGUETE PROPIO | H7: CXO | I7: 1 | J7: 818.97 | L7: Camino Real -C | M7: 39413.73 | O7: 175000 | P7: =O7/31*$P$5 -> 39516.129
B8: Arcos-C | C8: 21/01/2026 | D8: NOE JONAS D CEL | E8: 7503043917012 | F8: Liquid Love Backdoor 30ml - DUSA | G8: CONSUMIBLE PROPIO | H8: DUSA | I8: 1 | J8: 301.72 | L8: Circunvalación CELESTERRA | M8: 24676.72 | O8: 110000 | P8: =O8/31*$P$5 -> 24838.71
B9: Arcos-C | C9: 21/01/2026 | D9: NOE JONAS D CEL | E9: 6959633134559 | F9: Phoenix Neo 2 rojo - SVAKOM | G9: JUGUETE | H9: SVAKOM | I9: 1 | J9: 3534.48 | L9: Conchitas CEL | M9: 57836.02 | N9: =GETPIVOTDATA("SUBTOT",$L$5,"UBICACION","Conchitas CEL")*N5 -> 578.3602 | O9: 210000 | P9: =O9/31*$P$5 -> 47419.355
B10: Arcos-C | C10: 21/01/2026 | D10: NOE JONAS D CEL | E10: 7503020596957 | F10: Shot Shumatsu Fun Hombre - DUSA | G10: CONSUMIBLE PROPIO | H10: DUSA | I10: 5 | J10: 862.05 | L10: Federalismo CEL | M10: 4366.33 | O10: 100000 | P10: =O10/31*$P$5 -> 22580.645
B11: Arcos-C | C11: 21/01/2026 | D11: NOE JONAS D CEL | E11: 7503024256192 | F11: Shot Shumatsu Fun Mujer - DUSA | G11: CONSUMIBLE PROPIO | H11: DUSA | I11: 5 | J11: 862.05 | L11: Hidalgo CEL | M11: 13581.83 | O11: 120000 | P11: =O11/31*$P$5 -> 27096.774
B12: Arcos-C | C12: 21/01/2026 | D12: NOE JONAS D CEL | E12: 7503020596063 | F12: Stallion Regenerador - DUSA | G12: CONSUMIBLE PROPIO | H12: DUSA | I12: 1 | J12: 1293.1 | L12: Hotel los Reyes CEL | M12: 15280.13 | O12: 100000 | P12: =O12/31*$P$5 -> 22580.645
B13: Arcos-C | C13: 21/01/2026 | D13: NOE JONAS D CEL | E13: 7503020104076 | F13: Vibrador multiorgásmico con succión y estimulación de punto G Lulu - CXO | G13: JUGUETE PROPIO | H13: CXO | I13: 1 | J13: 2120.69 | L13: León 1 CEL | M13: 14844.8 | O13: 100000 | P13: =O13/31*$P$5 -> 22580.645
B14: Arcos-C | C14: 21/01/2026 | D14: NOE JONAS D CEL | E14: 7503032300443 | F14: Zoe bala vibradora RETAIL - CXO | G14: JUGUETE PROPIO | H14: CXO | I14: 2 | J14: 310.34 | L14: Naciones Unidas CEL | M14: 22077.54 | O14: 100000 | P14: =O14/31*$P$5 -> 22580.645
B15: Arcos-C | C15: 22/01/2026 | D15: NOE JONAS D CEL | E15: 4630017970018 | F15: Alargador de Pene Titan Gel 50 ml | G15: CONSUMIBLE | H15: TITAN | I15: 1 | J15: 594.83 | L15: Patria -CEL | M15: 26732.72 | O15: 185000 | P15: =O15/31*$P$5 -> 41774.194
B16: Arcos-C | C16: 22/01/2026 | D16: NOE JONAS D CEL | E16: 7503043917081 | F16: Blade rosa anillo vibrador - CXO | G16: JUGUETE PROPIO | H16: CXO | I16: 1 | J16: 81.9 | L16: Plaza Alamo CELESTERRA | M16: 31493.49 | N16: =GETPIVOTDATA("SUBTOT",$L$5,"UBICACION","Plaza Alamo CELESTERRA")*N5 -> 314.9349 | O16: 100000 | P16: =O16/31*$P$5 -> 22580.645
B17: Arcos-C | C17: 22/01/2026 | D17: NOE JONAS D CEL | E17: 6959633103500 | F17: Chika multiorgasmico turqueza - SVAKOM | G17: JUGUETE | H17: SVAKOM | I17: 1 | J17: 2155.17 | L17: Plaza Conchitas CEL | M17: 23969.79 | O17: 150000 | P17: =O17/31*$P$5 -> 33870.968
B18: Arcos-C | C18: 22/01/2026 | D18: NOE JONAS D CEL | E18: 7503020202214 | F18: Dildo realista con ventosa y testiculos Eddy - CXO | G18: JUGUETE PROPIO | H18: CXO | I18: 1 | J18: 948.28 | L18: Plaza las Torres CELESTERRA | M18: 23469.76 | O18: 180000 | P18: =O18/31*$P$5 -> 40645.161
B19: Arcos-C | C19: 22/01/2026 | D19: NOE JONAS D CEL | E19: 603912120042 | F19: Happy Top Tickler funda - PIPEDREAM | G19: JUGUETE | H19: PIPEDREAM | I19: 1 | J19: 344.83 | L19: Plaza Madison -CEL | M19: 28754.23 | O19: 115000 | P19: =O19/31*$P$5 -> 25967.742
B20: Arcos-C | C20: 22/01/2026 | D20: NOE JONAS D CEL | E20: 7503013378645 | F20: Liquid Love Pleasure 100ml - DUSA | G20: CONSUMIBLE PROPIO | H20: DUSA | I20: 2 | J20: 1551.72 | L20: Plaza Sauces CEL | M20: 27587.67 | O20: 155000 | P20: =O20/31*$P$5 -> 35000
B21: Arcos-C | C21: 22/01/2026 | D21: NOE JONAS D CEL | E21: 7503032300443 | F21: Zoe bala vibradora RETAIL - CXO | G21: JUGUETE PROPIO | H21: CXO | I21: 2 | J21: 310.34 | L21: Plaza Zenter CEL | M21: 47810.32 | O21: 435000 | P21: =O21/31*$P$5 -> 98225.806
B22: Arcos-C | C22: 23/01/2026 | D22: NOE JONAS D CEL | E22: 716222287524 | F22: ACEITE AROMATHERAPY MASSAGE OIL 4 SENSUALITY | G22: CONSUMIBLE | H22: WET | I22: 1 | J22: 926.72 | L22: Provenza-Cel | M22: 16590.42 | O22: 145000 | P22: =O22/31*$P$5 -> 32741.935
B23: Arcos-C | C23: 23/01/2026 | D23: NOE JONAS D CEL | E23: 7503043917081 | F23: Blade rosa anillo vibrador - CXO | G23: JUGUETE PROPIO | H23: CXO | I23: 2 | J23: 163.8 | L23: Total general | M23: 450925.08 | N23: =SUM(N6:N22) -> 893.2951 | O23: =SUM(O6:O22) -> 2680000 | P23: =SUM(P6:P22) -> 605161.29
B24: Arcos-C | C24: 23/01/2026 | D24: NOE JONAS D CEL | E24: 7503032300511 | F24: Cola de Zorro 45cm rosa M - CXO | G24: JUGUETE PROPIO | H24: CXO | I24: 1 | J24: 301.72
B25: Arcos-C | C25: 23/01/2026 | D25: NOE JONAS D CEL | E25: 7502214982811 | F25: Condones Mix Sabor y Aroma 5 pzs - PRUDENCE | G25: CONSUMIBLE | H25: PRUDENCE | I25: 1 | J25: 77.59
B26: Arcos-C | C26: 23/01/2026 | D26: NOE JONAS D CEL | E26: 7503043917005 | F26: Liquid Love Clear 30ml - DUSA | G26: CONSUMIBLE PROPIO | H26: DUSA | I26: 1 | J26: 301.72
B27: Arcos-C | C27: 23/01/2026 | D27: NOE JONAS D CEL | E27: 7503032300993 | F27: Liquid Love Pleasure 30ml - DUSA | G27: CONSUMIBLE PROPIO | H27: DUSA | I27: 2 | J27: 603.44
B28: Arcos-C | C28: 23/01/2026 | D28: NOE JONAS D CEL | E28: 7503013378645 | F28: Liquid Love Pleasure 100ml - DUSA | G28: CONSUMIBLE PROPIO | H28: DUSA | I28: 1 | J28: 775.86
B29: Arcos-C | C29: 23/01/2026 | D29: NOE JONAS D CEL | E29: 7503032300825 | F29: Lubricante Sachet natural 2 ml - BANANA SHAKE | G29: CONSUMIBLE | H29: BANANA SHAKE | I29: 1 | J29: 17.24
B30: Arcos-C | C30: 23/01/2026 | D30: NOE JONAS D CEL | E30: 7503013378690 | F30: Shumatsu 3 pzas - DUSA | G30: CONSUMIBLE PROPIO | H30: DUSA | I30: 5 | J30: 2887.95
B31: Arcos-C | C31: 23/01/2026 | D31: NOE JONAS D CEL | E31: 7350075028564 | F31: Sila Cruise pink - LELO | G31: JUGUETE | H31: LELO | I31: 1 | J31: 4396.55
B32: Arcos-C | C32: 23/01/2026 | D32: NOE JONAS D CEL | E32: 7503032300443 | F32: Zoe bala vibradora RETAIL - CXO | G32: JUGUETE PROPIO | H32: CXO | I32: 4 | J32: 620.68
B33: Arcos-C | C33: 24/01/2026 | D33: NOE JONAS D CEL | E33: 7503043917081 | F33: Blade rosa anillo vibrador - CXO | G33: JUGUETE PROPIO | H33: CXO | I33: 1 | J33: 81.9
B34: Arcos-C | C34: 24/01/2026 | D34: NOE JONAS D CEL | E34: 7503050524265 | F34: He Plus 30ml - DUSA | G34: CONSUMIBLE PROPIO | H34: DUSA | I34: 1 | J34: 431.03
B35: Arcos-C | C35: 24/01/2026 | D35: NOE JONAS D CEL | E35: 6959633103494 | F35: Mora Neo multiorgasmico rosa - SVAKOM | G35: JUGUETE | H35: SVAKOM | I35: 1 | J35: 1637.93
... B652: Provenza-Cel | C652: 25/01/2026 | D652: BRYAN ALEJANDRO V BERNAL | E652: 7503032300443 | F652: Zoe bala vibradora RETAIL - CXO | G652: JUGUETE PROPIO | H652: CXO | I652: 2 | J652: 310.34

Sheet Semana 2
B5: UBICACION | C5: FECHA | D5: VENDEDOR | E5: SKU | F5: ARTICULO | G5: FAMILIA COMERCIAL | H5: MARCA | I5: CANTIDAD | J5: SUBTOT
B6: Arcos-C | C6: 12/01/2026 | D6: NOE JONAS D CEL | E6: 6959633156094 | F6: Robin - SVAKOM | G6: JUGUETE | H6: SVAKOM | I6: 1 | J6: 1318.97
B7: Arcos-C | C7: 12/01/2026 | D7: NOE JONAS D CEL | E7: 7503032300443 | F7: Zoe bala vibradora RETAIL - CXO | G7: JUGUETE PROPIO | H7: CXO | I7: 1 | J7: 155.17
B8: Arcos-C | C8: 13/01/2026 | D8: NOE JONAS D CEL | E8: 7503043917081 | F8: Blade rosa anillo vibrador - CXO | G8: JUGUETE PROPIO | H8: CXO | I8: 3 | J8: 245.7 | P8: dias de cuota
B9: Arcos-C | C9: 13/01/2026 | D9: NOE JONAS D CEL | E9: 68892L | F9: Conjunto Leonor con pedreria negro 2 piezas M | G9: LENCERIA | H9: OLA MOU | I9: 1 | J9: 260.34 | L9: Etiquetas de fila | M9: Suma de SUBTOT | N9: 0.01 | O9: ppto | P9: 7
B10: Arcos-C | C10: 13/01/2026 | D10: NOE JONAS D CEL | E10: 75080471 | F10: Dulces Garganta Profunda 2 piezas Sabor Uva - SXO | G10: CONSUMIBLE | H10: SXO | I10: 1 | J10: 120.69 | L10: Arcos-C | M10: 40029.3 | O10: 200000 | P10: =O10/31*$P$9 -> 45161.29
B11: Arcos-C | C11: 13/01/2026 | D11: NOE JONAS D CEL | E11: 7503013378645 | F11: Liquid Love Pleasure 100ml - DUSA | G11: CONSUMIBLE PROPIO | H11: DUSA | I11: 2 | J11: 1551.72 | L11: Camino Real -C | M11: 32448.23 | O11: 175000 | P11: =O11/31*$P$9 -> 39516.129
B12: Arcos-C | C12: 13/01/2026 | D12: NOE JONAS D CEL | E12: GWPS_BANANASHAKE_001 | F12: Lub de Regalo - Banana Shake | G12: ACTIVACION | H12: BANANA SHAKE | I12: 1 | J12: 0.01 | L12: Circunvalación CELESTERRA | M12: 38179.28 | N12: =GETPIVOTDATA("SUBTOT",$L$9,"UBICACION","Circunvalación CELESTERRA")*N9 -> 381.7928 | O12: 110000 | P12: =O12/31*$P$9 -> 24838.71
B13: Arcos-C | C13: 13/01/2026 | D13: NOE JONAS D CEL | E13: 7503013378010 | F13: Rigidex 2 pzas - DUSA | G13: CONSUMIBLE PROPIO | H13: DUSA | I13: 3 | J13: 1293.1 | L13: Conchitas CEL | M13: 31581.81 | O13: 210000 | P13: =O13/31*$P$9 -> 47419.355
B14: Arcos-C | C14: 13/01/2026 | D14: NOE JONAS D CEL | E14: 7503032300443 | F14: Zoe bala vibradora RETAIL - CXO | G14: JUGUETE PROPIO | H14: CXO | I14: 1 | J14: 155.17 | L14: Federalismo CEL | M14: 20866.39 | O14: 100000 | P14: =O14/31*$P$9 -> 22580.645
B15: Arcos-C | C15: 14/01/2026 | D15: NOE JONAS D CEL | E15: 6959633103500 | F15: Chika multiorgasmico turqueza - SVAKOM | G15: JUGUETE | H15: SVAKOM | I15: 1 | J15: 2155.17 | L15: Hidalgo CEL | M15: 18706.83 | O15: 120000 | P15: =O15/31*$P$9 -> 27096.774
B16: Arcos-C | C16: 14/01/2026 | D16: NOE JONAS D CEL | E16: 7503013378645 | F16: Liquid Love Pleasure 100ml - DUSA | G16: CONSUMIBLE PROPIO | H16: DUSA | I16: 1 | J16: 775.86 | L16: Hotel los Reyes CEL | M16: 5543.07 | O16: 100000 | P16: =O16/31*$P$9 -> 22580.645
B17: Arcos-C | C17: 14/01/2026 | D17: NOE JONAS D CEL | E17: 7503013378010 | F17: Rigidex 2 pzas - DUSA | G17: CONSUMIBLE PROPIO | H17: DUSA | I17: 1 | J17: 431.03 | L17: León 1 CEL | M17: 23327.55 | N17: =GETPIVOTDATA("SUBTOT",$L$9,"UBICACION","León 1 CEL")*N9 -> 233.2755 | O17: 100000 | P17: =O17/31*$P$9 -> 22580.645
B18: Arcos-C | C18: 14/01/2026 | D18: NOE JONAS D CEL | E18: 7503020596957 | F18: Shot Shumatsu Fun Hombre - DUSA | G18: CONSUMIBLE PROPIO | H18: DUSA | I18: 3 | J18: 517.23 | L18: Naciones Unidas CEL | M18: 7655.14 | O18: 100000 | P18: =O18/31*$P$9 -> 22580.645
B19: Arcos-C | C19: 14/01/2026 | D19: NOE JONAS D CEL | E19: 7503024256192 | F19: Shot Shumatsu Fun Mujer - DUSA | G19: CONSUMIBLE PROPIO | H19: DUSA | I19: 2 | J19: 344.82 | L19: Patria -CEL | M19: 39172.4 | O19: 185000 | P19: =O19/31*$P$9 -> 41774.194
B20: Arcos-C | C20: 14/01/2026 | D20: NOE JONAS D CEL | E20: 7503032300443 | F20: Zoe bala vibradora RETAIL - CXO | G20: JUGUETE PROPIO | H20: CXO | I20: 1 | J20: 155.17 | L20: Plaza Alamo CELESTERRA | M20: 32689.59 | N20: =GETPIVOTDATA("SUBTOT",$L$9,"UBICACION","Plaza Alamo CELESTERRA")*N9 -> 326.8959 | O20: 100000 | P20: =O20/31*$P$9 -> 22580.645
B21: Arcos-C | C21: 15/01/2026 | D21: NOE JONAS D CEL | E21: 7503043917081 | F21: Blade rosa anillo vibrador - CXO | G21: JUGUETE PROPIO | H21: CXO | I21: 2 | J21: 163.8 | L21: Plaza Conchitas CEL | M21: 23262.87 | O21: 150000 | P21: =O21/31*$P$9 -> 33870.968
B22: Arcos-C | C22: 15/01/2026 | D22: NOE JONAS D CEL | E22: 7503013378492 | F22: Clean Whisper 120ml - DUSA | G22: CONSUMIBLE PROPIO | H22: DUSA | I22: 2 | J22: 603.44 | L22: Plaza las Torres CELESTERRA | M22: 23271.45 | O22: 180000 | P22: =O22/31*$P$9 -> 40645.161
B23: Arcos-C | C23: 15/01/2026 | D23: NOE JONAS D CEL | E23: 68877F | F23: Conjunto cafe tipo red Fernanda 2 piezas M | G23: LENCERIA | H23: OLA MOU | I23: 1 | J23: 312.07 | L23: Plaza Madison -CEL | M23: 35254.26 | N23: =GETPIVOTDATA("SUBTOT",$L$9,"UBICACION","Plaza Madison -CEL")*N9 -> 352.5426 | O23: 115000 | P23: =O23/31*$P$9 -> 25967.742
B24: Arcos-C | C24: 15/01/2026 | D24: NOE JONAS D CEL | E24: 68862J | F24: Conjunto leopardo Jennifer 3 piezas G | G24: LENCERIA | H24: OLA MOU | I24: 1 | J24: 646.55 | L24: Plaza Sauces CEL | M24: 21668.1 | O24: 155000 | P24: =O24/31*$P$9 -> 35000
B25: Arcos-C | C25: 15/01/2026 | D25: NOE JONAS D CEL | E25: 6959633166963 | F25: Ella Neo rojo- SVAKOM | G25: JUGUETE | H25: SVAKOM | I25: 1 | J25: 3017.24 | L25: Plaza Zenter CEL | M25: 68534.42 | O25: 435000 | P25: =O25/31*$P$9 -> 98225.806
B26: Arcos-C | C26: 15/01/2026 | D26: NOE JONAS D CEL | E26: 7508304288429 | F26: Feromonas en gel 20ml unisex - DIAMANTE | G26: CONSUMIBLE | H26: DIAMANTE | I26: 1 | J26: 379.31 | L26: Provenza-Cel | M26: 29810.32 | O26: 145000 | P26: =O26/31*$P$9 -> 32741.935
B27: Arcos-C | C27: 15/01/2026 | D27: NOE JONAS D CEL | E27: GWPS_BANANASHAKE_001 | F27: Lub de Regalo - Banana Shake | G27: ACTIVACION | H27: BANANA SHAKE | I27: 1 | J27: 0.01 | L27: Total general | M27: 492001.01 | N27: =SUM(N10:N25) -> 1294.5068 | O27: =SUM(O10:O26) -> 2680000 | P27: =SUM(P10:P26) -> 605161.29
B28: Arcos-C | C28: 15/01/2026 | D28: NOE JONAS D CEL | E28: 7503013378799 | F28: Lubricante Body Surf Termico Citricos DUSA 60ml | G28: CONSUMIBLE PROPIO | H28: DUSA | I28: 1 | J28: 387.93
B29: Arcos-C | C29: 15/01/2026 | D29: NOE JONAS D CEL | E29: 7503023462259 | F29: Lubricante Masaje Térmico Comestible Frutas Prohibidas FEEL LOVE 4 en 1 - 60ml | G29: LUBRICANTE | H29: FEEL LOVE | I29: 1 | J29: 344.83
B30: Arcos-C | C30: 15/01/2026 | D30: NOE JONAS D CEL | E30: 695963319882 | F30: Masturbador Recargable Hannes NEO - SVAKOM | H30: SVAKOM | I30: 1 | J30: 2586.21
B31: Arcos-C | C31: 15/01/2026 | D31: NOE JONAS D CEL | E31: 75079413 | F31: Mini Kit Hombre 3 piezas - SXO | G31: CONSUMIBLE | H31: SXO | I31: 1 | J31: 284.48
B32: Arcos-C | C32: 15/01/2026 | D32: NOE JONAS D CEL | E32: 75079390 | F32: Mini Kit Mujer 3 piezas- SXO | G32: CONSUMIBLE | H32: SXO | I32: 2 | J32: 568.97
B33: Arcos-C | C33: 15/01/2026 | D33: NOE JONAS D CEL | E33: USK-V11 | F33: Multiorgasmico con Lenguita Ceci - CXO | G33: JUGUETE PROPIO | H33: CXO | I33: 1 | J33: 2474.14
B34: Arcos-C | C34: 15/01/2026 | D34: NOE JONAS D CEL | E34: 7503050524241 | F34: Orgasmik 30ml - DUSA | G34: CONSUMIBLE PROPIO | H34: DUSA | I34: 3 | J34: 1293.09
B35: Arcos-C | C35: 15/01/2026 | D35: NOE JONAS D CEL | E35: 7503013378010 | F35: Rigidex 2 pzas - DUSA | G35: CONSUMIBLE PROPIO | H35: DUSA | I35: 1 | J35: 431.03
B36: Arcos-C | C36: 15/01/2026 | D36: NOE JONAS D CEL | E36: 6959633156094 | F36: Robin - SVAKOM | G36: JUGUETE | H36: SVAKOM | I36: 1 | J36: 1318.97
B37: Arcos-C | C37: 15/01/2026 | D37: NOE JONAS D CEL | E37: 7503020596049 | F37: Sensicool - DUSA | G37: CONSUMIBLE PROPIO | H37: DUSA | I37: 1 | J37: 431.03
B38: Arcos-C | C38: 15/01/2026 | D38: NOE JONAS D CEL | E38: 7503050524258 | F38: Sensicool 30ml - DUSA | G38: CONSUMIBLE PROPIO | H38: DUSA | I38: 2 | J38: 862.07
B39: Arcos-C | C39: 15/01/2026 | D39: NOE JONAS D CEL | E39: 7503032300443 | F39: Zoe bala vibradora RETAIL - CXO | G39: JUGUETE PROPIO | H39: CXO | I39: 1 | J39: 155.17
B40: Arcos-C | C40: 16/01/2026 | D40: NOE JONAS D CEL | E40: 7503013378690 | F40: Shumatsu 3 pzas - DUSA | G40: CONSUMIBLE PROPIO | H40: DUSA | I40: 1 | J40: 577.59
B41: Arcos-C | C41: 17/01/2026 | D41: NOE JONAS D CEL | E41: 7503030211021 | F41: Anillo desechable para pene Donut - CXO | G41: JUGUETE PROPIO | H41: CXO | I41: 1 | J41: 34.48
B42: Arcos-C | C42: 17/01/2026 | D42: NOE JONAS D CEL | E42: 7503020111072 | F42: Anillo vibrador recargable con textura negra Hank - CXO | G42: JUGUETE PROPIO | H42: CXO | I42: 1 | J42: 1267.24
... B693: Provenza-Cel | C693: 18/01/2026 | D693: BRYAN ALEJANDRO V BERNAL | E693: 7350075026157 | F693: Sona cerise - LELO | G693: JUGUETE | H693: LELO | I693: 1 | J693: 2068.97

Sheet Semana 1
B4: UBICACION | C4: FECHA | D4: VENDEDOR | E4: SKU | F4: ARTICULO | G4: FAMILIA COMERCIAL | H4: MARCA | I4: CANTIDAD | J4: SUBTOT | P4: dias de cuota
B5: Arcos-C | C5: 02/01/2026 | D5: NOE JONAS D CEL | E5: 7503013378652 | F5: Liquid Love Backdoor 100ml - DUSA | G5: CONSUMIBLE PROPIO | H5: DUSA | I5: 1 | J5: 1077.59 | L5: Etiquetas de fila | M5: Suma de SUBTOT | N5: 0.01 | O5: ppto | P5: 11
B6: Arcos-C | C6: 02/01/2026 | D6: NOE JONAS D CEL | E6: 7503013378690 | F6: Shumatsu 3 pzas - DUSA | G6: CONSUMIBLE PROPIO | H6: DUSA | I6: 1 | J6: 577.59 | L6: Arcos-C | M6: 54232.73 | O6: =ERECTUS!C13 -> 200000 | P6: =O6/31*$P$5 -> 70967.742
B7: Arcos-C | C7: 03/01/2026 | D7: NOE JONAS D CEL | E7: 7503014914002 | F7: CAPSULAS MULTIORGASMICO AMO O-GEN | G7: CONSUMIBLE | H7: POWER MAN | I7: 1 | J7: 431.04 | L7: Camino Real -C | M7: 59683.48 | O7: =ERECTUS!C19 -> 175000 | P7: =O7/31*$P$5 -> 62096.774
B8: Arcos-C | C8: 03/01/2026 | D8: NOE JONAS D CEL | E8: 8699415912859 | F8: Miel Vigorizante para Hombre Miracle Honey VIP 15g- SECRET MIRACLE HONEY | G8: CONSUMIBLE | H8: SECRET MIRACLE HONEY | I8: 1 | J8: 215.52 | L8: Circunvalación CELESTERRA | M8: 27176.74 | O8: =ERECTUS!C23 -> 110000 | P8: =O8/31*$P$5 -> 39032.258
B9: Arcos-C | C9: 03/01/2026 | D9: NOE JONAS D CEL | E9: 7503023462891 | F9: ORAL SEX Exotic Nut 30ml - DIAMANTE | G9: CONSUMIBLE | H9: DIAMANTE | I9: 1 | J9: 310.35 | L9: Conchitas CEL | M9: 78961.05 | N9: =GETPIVOTDATA("SUBTOT",$L$5,"UBICACION","Conchitas CEL")*N5 -> 789.6105 | O9: =ERECTUS!C29 -> 210000 | P9: =O9/31*$P$5 -> 74516.129
B10: Arcos-C | C10: 03/01/2026 | D10: NOE JONAS D CEL | E10: 7503032300443 | F10: Zoe bala vibradora RETAIL - CXO | G10: JUGUETE PROPIO | H10: CXO | I10: 2 | J10: 310.34 | L10: Federalismo CEL | M10: 31900.8 | O10: =ERECTUS!C34 -> 100000 | P10: =O10/31*$P$5 -> 35483.871
B11: Arcos-C | C11: 04/01/2026 | D11: ANGEL DANILO RODRIGUEZ LOPEZ | E11: 7502214982477 | F11: Condon Fresa 3pzs - PRUDENCE | G11: CONSUMIBLE | H11: PRUDENCE | I11: 1 | J11: 60.34 | L11: Hidalgo CEL | M11: 19392.19 | O11: =ERECTUS!C39 -> 120000 | P11: =O11/31*$P$5 -> 42580.645
B12: Arcos-C | C12: 04/01/2026 | D12: ANGEL DANILO RODRIGUEZ LOPEZ | E12: 7503032300993 | F12: Liquid Love Pleasure 30ml - DUSA | G12: CONSUMIBLE PROPIO | H12: DUSA | I12: 1 | J12: 301.72 | L12: Hotel los Reyes CEL | M12: 25268.08 | O12: =ERECTUS!C44 -> 100000 | P12: =O12/31*$P$5 -> 35483.871
B13: Arcos-C | C13: 04/01/2026 | D13: ANGEL DANILO RODRIGUEZ LOPEZ | E13: 7503050524241 | F13: Orgasmik 30ml - DUSA | G13: CONSUMIBLE PROPIO | H13: DUSA | I13: 1 | J13: 431.03 | L13: León 1 CEL | M13: 32758.61 | O13: =ERECTUS!C48 -> 100000 | P13: =O13/31*$P$5 -> 35483.871
B14: Arcos-C | C14: 05/01/2026 | D14: NOE JONAS D CEL | E14: 7503030211021 | F14: Anillo desechable para pene Donut - CXO | G14: JUGUETE PROPIO | H14: CXO | I14: 1 | J14: 34.48 | L14: Naciones Unidas CEL | M14: 60780.63 | N14: =GETPIVOTDATA("SUBTOT",$L$5,"UBICACION","Naciones Unidas CEL")*N5 -> 607.8063 | O14: =ERECTUS!C50 -> 100000 | P14: =O14/31*$P$5 -> 35483.871
B15: Arcos-C | C15: 05/01/2026 | D15: NOE JONAS D CEL | E15: 7503043917081 | F15: Blade rosa anillo vibrador - CXO | G15: JUGUETE PROPIO | H15: CXO | I15: 1 | J15: 81.9 | L15: Patria -CEL | M15: 54111.93 | O15: =ERECTUS!C53 -> 185000 | P15: =O15/31*$P$5 -> 65645.161
B16: Arcos-C | C16: 05/01/2026 | D16: NOE JONAS D CEL | E16: 7503013378492 | F16: Clean Whisper 120ml - DUSA | G16: CONSUMIBLE PROPIO | H16: DUSA | I16: 1 | J16: 301.72 | L16: Plaza Alamo CELESTERRA | M16: 42659.41 | N16: =GETPIVOTDATA("SUBTOT",$L$5,"UBICACION","Plaza Alamo CELESTERRA")*N5 -> 426.5941 | O16: =ERECTUS!C59 -> 100000 | P16: =O16/31*$P$5 -> 35483.871
B17: Arcos-C | C17: 05/01/2026 | D17: NOE JONAS D CEL | E17: 8699415912859 | F17: Miel Vigorizante para Hombre Miracle Honey VIP 15g- SECRET MIRACLE HONEY | G17: CONSUMIBLE | H17: SECRET MIRACLE HONEY | I17: 2 | J17: 431.04 | L17: Plaza Conchitas CEL | M17: 37099 | O17: =ERECTUS!C63 -> 150000 | P17: =O17/31*$P$5 -> 53225.806
B18: Arcos-C | C18: 05/01/2026 | D18: NOE JONAS D CEL | E18: 6959633156094 | F18: Robin - SVAKOM | G18: JUGUETE | H18: SVAKOM | I18: 1 | J18: 1318.97 | L18: Plaza las Torres CELESTERRA | M18: 45193.8 | O18: =ERECTUS!C71 -> 180000 | P18: =O18/31*$P$5 -> 63870.968
B19: Arcos-C | C19: 05/01/2026 | D19: NOE JONAS D CEL | E19: 7503032300443 | F19: Zoe bala vibradora RETAIL - CXO | G19: JUGUETE PROPIO | H19: CXO | I19: 2 | J19: 310.34 | L19: Plaza Madison -CEL | M19: 40094.84 | O19: =ERECTUS!C67 -> 115000 | P19: =O19/31*$P$5 -> 40806.452
B20: Arcos-C | C20: 06/01/2026 | D20: NOE JONAS D CEL | E20: 7503032300993 | F20: Liquid Love Pleasure 30ml - DUSA | G20: CONSUMIBLE PROPIO | H20: DUSA | I20: 1 | J20: 301.72 | L20: Plaza Sauces CEL | M20: 66478.43 | O20: =ERECTUS!C76 -> 155000 | P20: =O20/31*$P$5 -> 55000
B21: Arcos-C | C21: 06/01/2026 | D21: NOE JONAS D CEL | E21: 8699415912859 | F21: Miel Vigorizante para Hombre Miracle Honey VIP 15g- SECRET MIRACLE HONEY | G21: CONSUMIBLE | H21: SECRET MIRACLE HONEY | I21: 1 | J21: 215.52 | L21: Plaza Zenter CEL | M21: 104853.28 | O21: =ERECTUS!C81 -> 435000 | P21: =O21/31*$P$5 -> 154354.84
B22: Arcos-C | C22: 06/01/2026 | D22: NOE JONAS D CEL | E22: 819835024781 | F22: Pom Adjustable Nipple Clamps - NOIR | G22: LENCERIA | H22: BLUSH | I22: 1 | J22: 543.1 | L22: Provenza-Cel | M22: 42555.97 | O22: =ERECTUS!C85 -> 145000 | P22: =O22/31*$P$5 -> 51451.613
B23: Arcos-C | C23: 06/01/2026 | D23: NOE JONAS D CEL | E23: 7503013378010 | F23: Rigidex 2 pzas - DUSA | G23: CONSUMIBLE PROPIO | H23: DUSA | I23: 1 | J23: 431.03 | L23: Total general | M23: 823200.97 | N23: =SUM(N7:N22) -> 1824.0109 | O23: =SUM(O6:O22) -> 2680000 | P23: =SUM(P6:P22) -> 950967.74
B24: Arcos-C | C24: 06/01/2026 | D24: NOE JONAS D CEL | E24: 7503026484050 | F24: SENSIBILIZADOR PARA PEZONES 15ML | G24: CONSUMIBLE | H24: FEEL LOVE | I24: 1 | J24: 172.41
B25: Arcos-C | C25: 06/01/2026 | D25: NOE JONAS D CEL | E25: 7503020596957 | F25: Shot Shumatsu Fun Hombre - DUSA | G25: CONSUMIBLE PROPIO | H25: DUSA | I25: 1 | J25: 172.41
B26: Arcos-C | C26: 06/01/2026 | D26: NOE JONAS D CEL | E26: 7503024256192 | F26: Shot Shumatsu Fun Mujer - DUSA | G26: CONSUMIBLE PROPIO | H26: DUSA | I26: 1 | J26: 172.41
B27: Arcos-C | C27: 07/01/2026 | D27: NOE JONAS D CEL | E27: 7503030111031 | F27: Anillo vibrador de aro doble con estimulador y dildo Javier - CXO | G27: JUGUETE PROPIO | H27: CXO | I27: 1 | J27: 1681.03
B28: Arcos-C | C28: 07/01/2026 | D28: NOE JONAS D CEL | E28: 7503043917081 | F28: Blade rosa anillo vibrador - CXO | G28: JUGUETE PROPIO | H28: CXO | I28: 3 | J28: 245.7
B29: Arcos-C | C29: 07/01/2026 | D29: NOE JONAS D CEL | E29: 7503014914002 | F29: CAPSULAS MULTIORGASMICO AMO O-GEN | G29: CONSUMIBLE | H29: POWER MAN | I29: 1 | J29: 431.04
B30: Arcos-C | C30: 07/01/2026 | D30: NOE JONAS D CEL | E30: M-22056 | F30: Dildo L 21cm - CXO | G30: JUGUETE PROPIO | H30: CXO | I30: 1 | J30: 689.66
B31: Arcos-C | C31: 07/01/2026 | D31: NOE JONAS D CEL | E31: 7503030102034 | F31: Dildo vibrador con control Anthony - CXO | G31: JUGUETE PROPIO | H31: CXO | I31: 1 | J31: 2112.07
B32: Arcos-C | C32: 07/01/2026 | D32: NOE JONAS D CEL | E32: 7503013378645 | F32: Liquid Love Pleasure 100ml - DUSA | G32: CONSUMIBLE PROPIO | H32: DUSA | I32: 2 | J32: 1551.72
B33: Arcos-C | C33: 07/01/2026 | D33: NOE JONAS D CEL | E33: 7503023462235 | F33: Lubricante Masaje Térmico Comestible Piña Colada FEEL LOVE 4 en 1 - 60ml | G33: LUBRICANTE | H33: FEEL LOVE | I33: 1 | J33: 344.83
B34: Arcos-C | C34: 07/01/2026 | D34: NOE JONAS D CEL | E34: 8699415912859 | F34: Miel Vigorizante para Hombre Miracle Honey VIP 15g- SECRET MIRACLE HONEY | G34: CONSUMIBLE | H34: SECRET MIRACLE HONEY | I34: 2 | J34: 431.03
B35: Arcos-C | C35: 07/01/2026 | D35: NOE JONAS D CEL | E35: 7503026484845 | F35: Oral Sex Erotic Nut 5g - Feel Love | G35: CONSUMIBLE | H35: DIAMANTE | I35: 1 | J35: 51.72
... B52: Arcos-C | C52: 09/01/2026 | D52: NOE JONAS D CEL | E52: 7503013378980 | F52: Lubricante Body Surf Termico Chicle DUSA 60ml | G52: CONSUMIBLE PROPIO | H52: DUSA | I52: 1 | J52: 387.93
B53: Arcos-C | C53: 09/01/2026 | D53: NOE JONAS D CEL | E53: 695963319882 | F53: Masturbador Recargable Hannes NEO - SVAKOM | H53: SVAKOM | I53: 1 | J53: 2586.21
B54: Arcos-C | C54: 09/01/2026 | D54: NOE JONAS D CEL | E54: 716770096036 | F54: Sheology set intercambiable kegel - CALEX | G54: JUGUETE | H54: CALEXOTICS | I54: 1 | J54: 1637.93
B55: Arcos-C | C55: 09/01/2026 | D55: NOE JONAS D CEL | E55: CBD | F55: SUNNY SIDE UP CBD HIPOALERGENICO 10ml | G55: CONSUMIBLE | H55: SUNNY SIDE UP | I55: 1 | J55: 301.72
B56: Arcos-C | C56: 09/01/2026 | D56: NOE JONAS D CEL | E56: 716770065742 | F56: The Accommodator dildo de latex - CALEX | G56: JUGUETE | H56: CALEXOTICS | I56: 1 | J56: 775.86
B57: Arcos-C | C57: 09/01/2026 | D57: NOE JONAS D CEL | E57: 7503020104075 | F57: Vibrador multiorgásmico texturizado con succionador de clítoris Yeni - CXO | G57: JUGUETE PROPIO | H57: CXO | I57: 1 | J57: 2465.52
B58: Arcos-C | C58: 10/01/2026 | D58: NOE JONAS D CEL | E58: 7503043917081 | F58: Blade rosa anillo vibrador - CXO | G58: JUGUETE PROPIO | H58: CXO | I58: 4 | J58: 327.6
B59: Arcos-C | C59: 10/01/2026 | D59: NOE JONAS D CEL | E59: 7508304288412 | F59: FEROMONAS EN GEL 20ML HOMBRE HOMBRE | G59: CONSUMIBLE | H59: DIAMANTE | I59: 1 | J59: 379.31
B60: Arcos-C | C60: 10/01/2026 | D60: NOE JONAS D CEL | E60: 7503043917012 | F60: Liquid Love Backdoor 30ml - DUSA | G60: CONSUMIBLE PROPIO | H60: DUSA | I60: 1 | J60: 301.72
B61: Arcos-C | C61: 10/01/2026 | D61: NOE JONAS D CEL | E61: 7503013378645 | F61: Liquid Love Pleasure 100ml - DUSA | G61: CONSUMIBLE PROPIO | H61: DUSA | I61: 1 | J61: 775.86
B62: Arcos-C | C62: 10/01/2026 | D62: NOE JONAS D CEL | E62: 7503024256154 | F62: Lubricante Body Surf Termico Cereza DUSA 60ml | G62: CONSUMIBLE PROPIO | H62: DUSA | I62: 1 | J62: 387.93
B63: Arcos-C | C63: 10/01/2026 | D63: NOE JONAS D CEL | E63: 8699415912859 | F63: Miel Vigorizante para Hombre Miracle Honey VIP 15g- SECRET MIRACLE HONEY | G63: CONSUMIBLE | H63: SECRET MIRACLE HONEY | I63: 2 | J63: 431.03
B64: Arcos-C | C64: 10/01/2026 | D64: NOE JONAS D CEL | E64: 7503013378010 | F64: Rigidex 2 pzas - DUSA | G64: CONSUMIBLE PROPIO | H64: DUSA | I64: 3 | J64: 1293.1
B65: Arcos-C | C65: 10/01/2026 | D65: NOE JONAS D CEL | E65: 7503020596049 | F65: Sensicool - DUSA | G65: CONSUMIBLE PROPIO | H65: DUSA | I65: 1 | J65: 431.03
... B710: Plaza Alamo CELESTERRA | C710: 11/01/2026 | D710: DELIA AGUIRRE CERVANTES | E710: 7503032300993 | F710: Liquid Love Pleasure 30ml - DUSA | G710: CONSUMIBLE PROPIO | H710: DUSA | I710: 1 | J710: 301.72
B711: Plaza Alamo CELESTERRA | C711: 11/01/2026 | D711: DELIA AGUIRRE CERVANTES | E711: 695963319882 | F711: Masturbador Recargable Hannes NEO - SVAKOM | H711: SVAKOM | I711: 1 | J711: 2586.21
B712: Plaza Alamo CELESTERRA | C712: 11/01/2026 | D712: DELIA AGUIRRE CERVANTES | E712: 714718001654 | F712: MEDIAS DE NYLON EN ENCAJE NUDE 1011 | G712: LENCERIA | H712: LEG AVENUE | I712: 1 | J712: 172.41
B713: Plaza Alamo CELESTERRA | C713: 11/01/2026 | D713: DELIA AGUIRRE CERVANTES | E713: 7503032300856 | F713: Sachet vibrador liquido 2 ml - BANANA SHAKE | G713: CONSUMIBLE | H713: BANANA SHAKE | I713: 1 | J713: 17.24
B714: Plaza Alamo CELESTERRA | C714: 11/01/2026 | D714: DELIA AGUIRRE CERVANTES | E714: 7503020596957 | F714: Shot Shumatsu Fun Hombre - DUSA | G714: CONSUMIBLE PROPIO | H714: DUSA | I714: 1 | J714: 172.41
B715: Plaza Alamo CELESTERRA | C715: 11/01/2026 | D715: DELIA AGUIRRE CERVANTES | E715: 7503024256192 | F715: Shot Shumatsu Fun Mujer - DUSA | G715: CONSUMIBLE PROPIO | H715: DUSA | I715: 1 | J715: 172.41
B716: Plaza Alamo CELESTERRA | C716: 11/01/2026 | D716: DELIA AGUIRRE CERVANTES | E716: 7501513758042 | F716: TANGA MASCULINA GSTRING AZUL MARINO UNITALLA | G716: LENCERIA | H716: ADRENALINE | I716: 1 | J716: 258.62
B717: Plaza Conchitas CEL | C717: 02/01/2026 | D717: OSCAR ANTONIO L CEL | E717: 7503032300887 | F717: Anahi L - CXO | G717: JUGUETE PROPIO | H717: CXO | I717: 1 | J717: 521.55
B718: Plaza Conchitas CEL | C718: 02/01/2026 | D718: OSCAR ANTONIO L CEL | E718: 7503014914002 | F718: CAPSULAS MULTIORGASMICO AMO O-GEN | G718: CONSUMIBLE | H718: POWER MAN | I718: 1 | J718: 431.04
B719: Plaza Conchitas CEL | C719: 02/01/2026 | D719: OSCAR ANTONIO L CEL | E719: 7503013378492 | F719: Clean Whisper 120ml - DUSA | G719: CONSUMIBLE PROPIO | H719: DUSA | I719: 1 | J719: 301.72
B720: Plaza Conchitas CEL | C720: 02/01/2026 | D720: OSCAR ANTONIO L CEL | E720: 7502214982491 | F720: CONDON PRUDENCE EXTRA TIME UVA | G720: CONSUMIBLE | H720: PRUDENCE | I720: 1 | J720: 60.34
B721: Plaza Conchitas CEL | C721: 02/01/2026 | D721: OSCAR ANTONIO L CEL | E721: 7503032300252 | F721: Dildo Nebulosa - CXO | G721: JUGUETE PROPIO | H721: CXO | I721: 1 | J721: 474.14
B722: Plaza Conchitas CEL | C722: 02/01/2026 | D722: OSCAR ANTONIO L CEL | E722: 855215007654 | F722: Dildo Realista 8" Cocolate - Blush | G722: JUGUETE | H722: BLUSH | I722: 1 | J722: 1896.55
B723: Plaza Conchitas CEL | C723: 02/01/2026 | D723: OSCAR ANTONIO L CEL | E723: 7503020310205 | F723: Dildo Vibrador Termico Realista 3 en 1 con movimiento Hades-CXO | G723: JUGUETE PROPIO | H723: CXO | I723: 1 | J723: 2500
... B1165: Provenza-Cel | C1165: 11/01/2026 | D1165: BRYAN ALEJANDRO V BERNAL | E1165: 7503043917012 | F1165: Liquid Love Backdoor 30ml - DUSA | G1165: CONSUMIBLE PROPIO | H1165: DUSA | I1165: 1 | J1165: 301.72

Sheet ERECTUS
I1: x
H2: CUMPLIMIENTO | I2: Cumplimiento Cuota | J2: JUGUETES ARRIBA DE 1500 ANTES DE IVA | K2: CXO / LUA | L2: DUSA | M2: PASTILLA DUSA
H3: MENOR AL 69% | I3: 0 | J3: 0 | K3: 0 | L3: 0 | M3: 0
B4: TIENDAS / BLOQUES DE CUMPLIMIENTO PPTO MENSUAL | H4: 70% AL 75% | I4: 0.005 | J4: 0.005 | K4: 0.03 | L4: 0.01 | M4: 0.03
C5: Bloque 1 | D5: Bloque 2 | E5: Bloque 3 | F5: Bloque 4 | H5: 76 % AL 80% | I5: 0.01 | J5: 0.0075 | K5: 0.045 | L5: 0.015 | M5: 0.045
B6: PORCENTAJES | C6: 75 A 79 % | D6: 80% a 89% | E6: 90 A 109% | F6: 110% en adelante | H6: 81% AL 100% | I6: 0.02 | J6: 0.01 | K6: 0.06 | L6: 0.02 | M6: 0.06
B7: Venta Total | C7: 0.0075 | D7: 0.0125 | E7: 0.02 | F7: 0.025 | H7: 110% en Adelante | I7: 0.025 | J7: 0.01 | K7: 0.06 | L7: 0.02 | M7: 0.06
C11: PRESUPUESTO | D11: VENTA | E11: % ALCANCE | F11: CUMPLIMIENTO | I11: PAGO DE COMISIONES | O11: PAGO
B12: Sucursal | C12: Presupuesto | D12: Venta | E12: Venta | F12: EMPLEADO | G12: Venta por vendedor | H12: VTA ECOMMERCE | I12: CUOTA MENSUAL | J12: Juguetes en General $ 1,500 | K12: CXO | L12: DUSA | M12: PASTILLA SHUMA | N12: SEMANAL | O12: SUBTOTAL | P12: % ALCANCE VS LA VENTA | Q12: % DE ALCANCE VS LA VTA GLOBAL
B13: Arcos-C | C13: 200000 | D13: =SUMIF('BASE GENERAL'!B4:B3114,ERECTUS!B13,'BASE GENERAL'!J4:J3114) -> 154973.17 | E13: =D13/C13 -> 0.77486585 | F13: ='VTA POR EMPLEADO'!A5 -> ANGEL DANILO RODRIGUEZ LOPEZ | G13: =SUMIF('VTA POR EMPLEADO'!A5:A8,ERECTUS!F13,'VTA POR EMPLEADO'!B5:B8) -> 793.09 | O13: =SUM(I13:N13) -> 0
F14: ='VTA POR EMPLEADO'!A6 -> GERMAN GUZMAN AGUIRRE | G14: =SUMIF('VTA POR EMPLEADO'!A6:A9,ERECTUS!F14,'VTA POR EMPLEADO'!B6:B9) -> 6775.85 | O14: =SUM(I14:N14) -> 0
F15: ='VTA POR EMPLEADO'!A7 -> JESáS ULISES PEREZ VARGAS | G15: =SUMIF('VTA POR EMPLEADO'!A7:A10,ERECTUS!F15,'VTA POR EMPLEADO'!B7:B10) -> 1788.77 | O15: =SUM(I15:N15) -> 0
F16: ='VTA POR EMPLEADO'!A8 -> NOE JONAS D CEL | G16: =SUMIF('VTA POR EMPLEADO'!A8:A11,ERECTUS!F16,'VTA POR EMPLEADO'!B8:B11) -> 145615.46 | I16: =G16*C7 -> 1092.1159 | J16: =Juguetes!O26 -> 333.6205 | K16: =CXO!O27 -> 2583.1056 | L16: =DUSA!O25 -> 675.8578 | M16: =Pastilla!O27 -> 415.8648 | O16: =SUM(I16:N16) -> 5100.5646 | P16: =O16/D13 -> 0.032912566 | Q16: =O16/$D$92 -> 0.002326103
O17: =SUM(I17:N17) -> 0
O18: =SUM(I18:N18) -> 0
B19: Camino Real -C | C19: 175000 | D19: =SUMIF('BASE GENERAL'!B4:B3114,ERECTUS!B19,'BASE GENERAL'!J4:J3114) -> 161222.14 | E19: =D19/C19 -> 0.92126937 | F19: ='VTA POR EMPLEADO'!A10 -> ALFONSO M CARBALLAR | G19: =SUMIF('VTA POR EMPLEADO'!A10:A12,ERECTUS!F19,'VTA POR EMPLEADO'!B10:B12) -> 6689.64 | O19: =SUM(I19:N19) -> 0
F20: ='VTA POR EMPLEADO'!A11 -> JESáS ULISES PEREZ VARGAS | G20: =SUMIF('VTA POR EMPLEADO'!A11:A13,ERECTUS!F20,'VTA POR EMPLEADO'!B11:B13) -> 689.65 | O20: =SUM(I20:N20) -> 0
F21: ='VTA POR EMPLEADO'!A12 -> JESUS ALBERTO M GARCIA | G21: =SUMIF('VTA POR EMPLEADO'!A12:A14,ERECTUS!F21,'VTA POR EMPLEADO'!B12:B14) -> 153842.85 | I21: =G21*E7 -> 3076.857 | J21: =Juguetes!O22 -> 311.3362 | K21: =CXO!O23 -> 3412.5 | L21: =DUSA!O21 -> 803.0956 | M21: =Pastilla!O23 -> 797.0742 | O21: =SUM(I21:N21) -> 8400.863 | P21: =O21/D19 -> 0.052107378 | Q21: =O21/$D$92 -> 0.0038311979
F22: ='VTA POR EMPLEADO'!A13 -> Circunvalación CELESTERRA | O22: =SUM(I22:N22) -> 0
B23: Circunvalación CELESTERRA | C23: 110000 | D23: =SUMIF('BASE GENERAL'!B14:B3124,ERECTUS!B23,'BASE GENERAL'!J14:J3124) -> 126589.95 | E23: =D23/C23 -> 1.1508177 | F23: ='VTA POR EMPLEADO'!A14 -> ANGEL DANILO RODRIGUEZ LOPEZ | G23: =SUMIF('VTA POR EMPLEADO'!A14:A16,ERECTUS!F23,'VTA POR EMPLEADO'!B14:B16) -> 11926.74 | O23: =SUM(I23:N23) -> 0
F24: ='VTA POR EMPLEADO'!A15 -> GERMAN GUZMAN AGUIRRE | G24: =SUMIF('VTA POR EMPLEADO'!A15:A17,ERECTUS!F24,'VTA POR EMPLEADO'!B15:B17) -> 6577.6 | O24: =SUM(I24:N24) -> 0
F25: ='VTA POR EMPLEADO'!A16 -> IRIS CRISTINA RIVERA PEREZ CELESTERRA | G25: =SUMIF('VTA POR EMPLEADO'!A16:A18,ERECTUS!F25,'VTA POR EMPLEADO'!B16:B18) -> 104594.24 | I25: =G25*F7 -> 2614.856 | J25: =Juguetes!O20 -> 164.2241 | K25: =CXO!O21 -> 2639.5536 | L25: =DUSA!O19 -> 495.687 | M25: =Pastilla!O21 -> 415.8648 | N25: ='Semana 2'!N12+'semana 4'!N9 -> 747.3649 | O25: =SUM(I25:N25) -> 7077.5504 | P25: =O25/D23 -> 0.05590926 | Q25: =O25/$D$92 -> 0.0032277036
F26: ='VTA POR EMPLEADO'!A17 -> JESáS ULISES PEREZ VARGAS | G26: =SUMIF('VTA POR EMPLEADO'!A17:A19,ERECTUS!F26,'VTA POR EMPLEADO'!B17:B19) -> 3491.37 | O26: =SUM(I26:N26) -> 0
O27: =SUM(I27:N27) -> 0
O28: =SUM(I28:N28) -> 0
B29: Conchitas CEL | C29: 210000 | D29: =SUMIF('BASE GENERAL'!B4:B3114,ERECTUS!B29,'BASE GENERAL'!J4:J3114) -> 195400.97 | E29: =D29/C29 -> 0.93048081 | F29: ='VTA POR EMPLEADO'!A19 -> ALFONSO M CARBALLAR | G29: =SUMIF('VTA POR EMPLEADO'!A19:A21,ERECTUS!F29,'VTA POR EMPLEADO'!B19:B21) -> 20668.07 | O29: =SUM(I29:N29) -> 0
F30: ='VTA POR EMPLEADO'!A20 -> GERMAN GUZMAN AGUIRRE | G30: =SUMIF('VTA POR EMPLEADO'!A20:A22,ERECTUS!F30,'VTA POR EMPLEADO'!B20:B22) -> 14607.69 | O30: =SUM(I30:N30) -> 0
F31: ='VTA POR EMPLEADO'!A21 -> HECTOR MANUEL P CELEST | G31: =SUMIF('VTA POR EMPLEADO'!A21:A23,ERECTUS!F31,'VTA POR EMPLEADO'!B21:B23) -> 160125.21 | I31: =G31*E7 -> 3202.5042 | J31: =Juguetes!O19 -> 368.491 | K31: =CXO!O20 -> 3786.2418 | L31: =DUSA!O18 -> 834.9926 | M31: =Pastilla!O20 -> 762.4188 | N31: ='Semana 1'!N9+'Semana 3'!N9 -> 1367.9707 | O31: =SUM(I31:N31) -> 10322.619 | P31: =O31/D29 -> 0.052827881 | Q31: =O31/$D$92 -> 0.0047076111
O32: =SUM(I32:N32) -> 0
O33: =SUM(I33:N33) -> 0
B34: Federalismo CEL | C34: 100000 | D34: =SUMIF('BASE GENERAL'!B4:B3114,ERECTUS!B34,'BASE GENERAL'!J4:J3114) -> 68633.49 | E34: =D34/C34 -> 0.6863349 | F34: ='VTA POR EMPLEADO'!A23 -> ANGEL DANILO RODRIGUEZ LOPEZ | G34: =SUMIF('VTA POR EMPLEADO'!A23:A25,ERECTUS!F34,'VTA POR EMPLEADO'!B23:B25) -> 2413.8 | O34: =SUM(I34:N34) -> 0
F35: ='VTA POR EMPLEADO'!A24 -> GERMAN GUZMAN AGUIRRE | G35: =SUMIF('VTA POR EMPLEADO'!A24:A26,ERECTUS!F35,'VTA POR EMPLEADO'!B24:B26) -> 150.86 | O35: =SUM(I35:N35) -> 0
F36: ='VTA POR EMPLEADO'!A25 -> MARIA EDUWIGES DEL TORO ORTEGA | G36: =SUMIF('VTA POR EMPLEADO'!A25:A27,ERECTUS!F36,'VTA POR EMPLEADO'!B25:B27) -> 66068.83 | J36: =Juguetes!O23 -> 0 | K36: =CXO!O24 -> 0 | L36: =DUSA!O22 -> 0 | M36: =Pastilla!O24 -> 0 | O36: =SUM(I36:N36) -> 0 | P36: =O36/D34 -> 0 | Q36: =O36/$D$92 -> 0
O37: =SUM(I37:N37) -> 0
O38: =SUM(I38:N38) -> 0
B39: Hidalgo CEL | C39: 120000 | D39: =SUMIF('BASE GENERAL'!B9:B3119,ERECTUS!B39,'BASE GENERAL'!J9:J3119) -> 68745.45 | E39: =D39/C39 -> 0.57287875 | F39: ='VTA POR EMPLEADO'!A27 -> CELINA HERMILA M GUILLEN | G39: =SUMIF('VTA POR EMPLEADO'!A27:A29,ERECTUS!F39,'VTA POR EMPLEADO'!B27:B29) -> 54879.1 | J39: =Juguetes!O14 -> 42.7586 | K39: =CXO!O15 -> 1204.3968 | L39: 326.0316 | M39: =Pastilla!O15 -> 381.2094 | O39: =SUM(I39:N39) -> 1954.3964 | P39: =O39/D39 -> 0.028429466 | Q39: =O39/$D$92 -> 0.00089129883
F40: ='VTA POR EMPLEADO'!A28 -> GERMAN GUZMAN AGUIRRE | G40: =SUMIF('VTA POR EMPLEADO'!A28:A30,ERECTUS!F40,'VTA POR EMPLEADO'!B28:B30) -> 12051.71 | O40: =SUM(I40:N40) -> 0
F41: ='VTA POR EMPLEADO'!A29 -> JESáS ULISES PEREZ VARGAS | G41: =SUMIF('VTA POR EMPLEADO'!A29:A31,ERECTUS!F41,'VTA POR EMPLEADO'!B29:B31) -> 1814.64 | O41: =SUM(I41:N41) -> 0
O42: =SUM(I42:N42) -> 0
O43: =SUM(I43:N43) -> 0
B44: Hotel los Reyes CEL | C44: 100000 | D44: =SUMIF('BASE GENERAL'!B4:B3114,ERECTUS!B44,'BASE GENERAL'!J4:J3114) -> 56789.52 | E44: =D44/C44 -> 0.5678952 | F44: ='VTA POR EMPLEADO'!A31 -> ALFONSO M CARBALLAR | G44: =SUMIF('VTA POR EMPLEADO'!A31:A34,ERECTUS!F44,'VTA POR EMPLEADO'!B31:B34) -> 301.72 | O44: =SUM(I44:N44) -> 0
F45: ='VTA POR EMPLEADO'!A32 -> ANGEL DANILO RODRIGUEZ LOPEZ | G45: =SUMIF('VTA POR EMPLEADO'!A32:A35,ERECTUS!F45,'VTA POR EMPLEADO'!B32:B35) -> 1538.79 | O45: =SUM(I45:N45) -> 0
F46: ='VTA POR EMPLEADO'!A33 -> GERMAN GUZMAN AGUIRRE | G46: =SUMIF('VTA POR EMPLEADO'!A33:A36,ERECTUS!F46,'VTA POR EMPLEADO'!B33:B36) -> 4737.07 | O46: =SUM(I46:N46) -> 0
F47: ='VTA POR EMPLEADO'!A34 -> NINOSCHKA VILLAREAL GONZALEZ | G47: =SUMIF('VTA POR EMPLEADO'!A34:A37,ERECTUS!F47,'VTA POR EMPLEADO'!B34:B37) -> 50211.94 | J47: =Juguetes!O25 -> 0 | K47: =CXO!O26 -> 0 | L47: =DUSA!O24 -> 0 | M47: =Pastilla!O26 -> 0 | O47: =SUM(I47:N47) -> 0 | P47: =O47/D44 -> 0 | Q47: =O47/$D$92 -> 0
B48: León 1 CEL | C48: 100000 | D48: =SUMIF('BASE GENERAL'!B4:B3114,ERECTUS!B48,'BASE GENERAL'!J3:J4) -> 82935.2 | E48: =D48/C48 -> 0.829352 | F48: ='VTA POR EMPLEADO'!A36 -> Rodolfo Serrano Amezcua | G48: =SUMIF('VTA POR EMPLEADO'!A35:A38,ERECTUS!F48,'VTA POR EMPLEADO'!B35:B38) -> 82956.75 | I48: =G48*D7 -> 1036.9594 | J48: =Juguetes!O28 -> 34.4827 | K48: =CXO!O29 -> 2793.1044 | L48: =DUSA!O27 -> 358.2728 | M48: =Pastilla!O29 -> 415.8648 | N48: ='Semana 2'!N17 -> 233.2755 | O48: =SUM(I48:N48) -> 4871.9596 | P48: =O48/D48 -> 0.058744171 | Q48: =O48/$D$92 -> 0.0022218481
O49: =SUM(I49:N49) -> 0
B50: Naciones Unidas CEL | C50: 100000 | D50: =SUMIF('BASE GENERAL'!B4:B3114,ERECTUS!B50,'BASE GENERAL'!J4:J3114) -> 118721.69 | E50: =D50/C50 -> 1.1872169 | F50: ='VTA POR EMPLEADO'!A38 -> EDGAR MOISES A NAVARRO | G50: =SUMIF('VTA POR EMPLEADO'!A37:A40,ERECTUS!F50,'VTA POR EMPLEADO'!B37:B40) -> 118721.69 | I50: =G50*F7 -> 2968.0422 | J50: =Juguetes!O16 -> 247.4136 | K50: =CXO!O17 -> 1822.332 | L50: =DUSA!O15 -> 704.3056 | M50: =Pastilla!O17 -> 589.1418 | N50: ='Semana 1'!N14+'semana 4'!N15 -> 889.8901 | O50: =SUM(I50:N50) -> 7221.1253 | P50: =O50/D50 -> 0.060823977 | Q50: =O50/$D$92 -> 0.0032931807
O51: =SUM(I51:N51) -> 0
O52: =SUM(I52:N52) -> 0
B53: Patria -CEL | C53: 185000 | D53: =SUMIF('BASE GENERAL'!B4:B3114,ERECTUS!B53,'BASE GENERAL'!J4:J3114) -> 155305.82 | E53: =D53/C53 -> 0.83949092 | F53: ='VTA POR EMPLEADO'!A40 -> ANGEL DANILO RODRIGUEZ LOPEZ | G53: =SUMIF('VTA POR EMPLEADO'!A40:A42,ERECTUS!F53,'VTA POR EMPLEADO'!B40:B42) -> 8310.35 | O53: =SUM(I53:N53) -> 0
F54: ='VTA POR EMPLEADO'!A41 -> ANTONIO EDMUNDO E CAMBEROS | G54: =SUMIF('VTA POR EMPLEADO'!A41:A43,ERECTUS!F54,'VTA POR EMPLEADO'!B41:B43) -> 132762.74 | I54: =G54*D7 -> 1659.5343 | J54: 136.2068 | K54: =CXO!O12 -> 3113.0172 | L54: =DUSA!O10 -> 667.4074 | M54: =Pastilla!O12 -> 1005.0066 | O54: =SUM(I54:N54) -> 6581.1723 | P54: =O54/D53 -> 0.042375567 | Q54: =O54/$D$92 -> 0.0030013313
F55: ='VTA POR EMPLEADO'!A42 -> GERMAN GUZMAN AGUIRRE | G55: =SUMIF('VTA POR EMPLEADO'!A42:A44,ERECTUS!F55,'VTA POR EMPLEADO'!B42:B44) -> 14232.73 | O55: =SUM(I55:N55) -> 0
O56: =SUM(I56:N56) -> 0
O57: =SUM(I57:N57) -> 0
O58: =SUM(I58:N58) -> 0
B59: Plaza Alamo CELESTERRA | C59: 100000 | D59: =SUMIF('BASE GENERAL'!B4:B3114,ERECTUS!B59,'BASE GENERAL'!J4:J3114) -> 120782.12 | E59: =D59/C59 -> 1.2078212 | F59: ='VTA POR EMPLEADO'!A44 -> ALFONSO M CARBALLAR | G59: =SUMIF('VTA POR EMPLEADO'!A44:A47,ERECTUS!F59,'VTA POR EMPLEADO'!B44:B47) -> 3163.78 | O59: =SUM(I59:N59) -> 0
F60: ='VTA POR EMPLEADO'!A45 -> ANGEL DANILO RODRIGUEZ LOPEZ | G60: =SUMIF('VTA POR EMPLEADO'!A45:A48,ERECTUS!F60,'VTA POR EMPLEADO'!B45:B48) -> 2387.93 | O60: =SUM(I60:N60) -> 0
F61: ='VTA POR EMPLEADO'!A46 -> DELIA AGUIRRE CERVANTES | G61: =SUMIF('VTA POR EMPLEADO'!A46:A49,ERECTUS!F61,'VTA POR EMPLEADO'!B46:B49) -> 112626.96 | I61: =G61*F7 -> 2815.674 | J61: =Juguetes!O15 -> 162.9309 | K61: =CXO!O16 -> 2947.5042 | L61: 437.0642 | M61: =Pastilla!O16 -> 485.1756 | N61: ='Semana 1'!N16+'Semana 2'!N20+'Semana 3'!N16 -> 1068.4249 | O61: =SUM(I61:N61) -> 7916.7738 | P61: =O61/D59 -> 0.065545909 | Q61: =O60/$D$92 -> 0
F62: ='VTA POR EMPLEADO'!A47 -> JESáS ULISES PEREZ VARGAS | G62: =SUMIF('VTA POR EMPLEADO'!A47:A50,ERECTUS!F62,'VTA POR EMPLEADO'!B47:B50) -> 2603.45 | O62: =SUM(I62:N62) -> 0
B63: Plaza Conchitas CEL | C63: 150000 | D63: =SUMIF('BASE GENERAL'!B8:B3118,ERECTUS!B63,'BASE GENERAL'!J8:J3118) -> 121603.09 | E63: =D63/C63 -> 0.81068727 | F63: ='VTA POR EMPLEADO'!A49 -> ALFONSO M CARBALLAR | G63: =SUMIF('VTA POR EMPLEADO'!A48:A51,ERECTUS!F63,'VTA POR EMPLEADO'!B48:B51) -> 17913.77 | O63: =SUM(I63:N63) -> 0
F64: ='VTA POR EMPLEADO'!A50 -> OSCAR ANTONIO L CEL | G64: =SUMIF('VTA POR EMPLEADO'!A49:A52,ERECTUS!F64,'VTA POR EMPLEADO'!B49:B52) -> 103689.32 | I64: =G64*D7 -> 1296.1165 | J64: =Juguetes!O27 -> 154.3103 | K64: =CXO!O28 -> 1598.2776 | L64: =DUSA!O26 -> 780.8564 | M64: =Pastilla!O28 -> 277.2432 | N64: ='semana 4'!N18 -> 372.7143 | O64: =SUM(I64:N64) -> 4479.5183 | P64: =O64/D63 -> 0.036837208 | Q64: =O65/$D$92 -> 0
O65: =SUM(I65:N65) -> 0
O66: =SUM(I66:N66) -> 0
B67: Plaza Madison -CEL | C67: 115000 | D67: =SUMIF('BASE GENERAL'!B12:B3122,ERECTUS!B67,'BASE GENERAL'!J12:J3122) -> 117663.63 | E67: =D67/C67 -> 1.023162 | F67: ='VTA POR EMPLEADO'!A57 -> ALFONSO M CARBALLAR | G67: =SUMIF('VTA POR EMPLEADO'!A57:A59,ERECTUS!F67,'VTA POR EMPLEADO'!B57:B59) -> 387.93 | O67: =SUM(I67:N67) -> 0
F68: ='VTA POR EMPLEADO'!A58 -> BERTHA SOFIA O BERMEJO | G68: =SUMIF('VTA POR EMPLEADO'!A58:A60,ERECTUS!F68,'VTA POR EMPLEADO'!B58:B60) -> 96146.43 | I68: =G68*E7 -> 1922.9286 | J68: =Juguetes!O12 -> 154.3967 | K68: =CXO!O13 -> 2950.3428 | L68: =DUSA!O11 -> 363.7892 | M68: =Pastilla!O13 -> 277.2432 | N68: ='Semana 2'!N23 -> 352.5426 | O68: =SUM(I68:N68) -> 6021.2431 | P68: =O68/D67 -> 0.051173358 | Q68: =O68/$D$92 -> 0.0027459767
F69: ='VTA POR EMPLEADO'!A59 -> GERMAN GUZMAN AGUIRRE | G69: =SUMIF('VTA POR EMPLEADO'!A59:A61,ERECTUS!F69,'VTA POR EMPLEADO'!B59:B61) -> 21129.27 | O69: =SUM(I69:N69) -> 0
O70: =SUM(I70:N70) -> 0
B71: Plaza las Torres CELESTERRA | C71: 180000 | D71: =SUMIF('BASE GENERAL'!B16:B3126,ERECTUS!B71,'BASE GENERAL'!J16:J3126) -> 113120.32 | E71: =D71/C71 -> 0.62844622 | F71: ='VTA POR EMPLEADO'!A52 -> ALFONSO M CARBALLAR | G71: =SUMIF('VTA POR EMPLEADO'!A52:A55,ERECTUS!F71,'VTA POR EMPLEADO'!B52:B55) -> 9271.51 | O71: =SUM(I71:N71) -> 0
F72: ='VTA POR EMPLEADO'!A53 -> ANGEL DANILO RODRIGUEZ LOPEZ | G72: =SUMIF('VTA POR EMPLEADO'!A53:A56,ERECTUS!F72,'VTA POR EMPLEADO'!B53:B56) -> 38357.63 | O72: =SUM(I72:N72) -> 0
F73: ='VTA POR EMPLEADO'!A54 -> GERMAN GUZMAN AGUIRRE | G73: =SUMIF('VTA POR EMPLEADO'!A54:A57,ERECTUS!F73,'VTA POR EMPLEADO'!B54:B57) -> 3758.6
F74: ='VTA POR EMPLEADO'!A55 -> JESáS ULISES PEREZ VARGAS | G74: =SUMIF('VTA POR EMPLEADO'!A55:A58,ERECTUS!F74,'VTA POR EMPLEADO'!B55:B58)+G15+G20+G26+G41+G62+G78 -> 78685.1 | J74: =Juguetes!O21 -> 100.862 | K74: =CXO!O22 -> 1530.2592 | L74: =DUSA!O20 -> 509.4778 | M74: =Pastilla!O22 -> 346.554 | O74: =SUM(I74:N74) -> 2487.153 | P74: =O74/D71 -> 0.021986792 | Q74: =O74/$D$92 -> 0.0011342615
O75: =SUM(I75:N75) -> 0
B76: Plaza Sauces CEL | C76: 155000 | D76: =SUMIF('BASE GENERAL'!B4:B3114,ERECTUS!B76,'BASE GENERAL'!J4:J3114) -> 137467 | E76: =D76/C76 -> 0.88688387 | F76: ='VTA POR EMPLEADO'!A61 -> ALFONSO M CARBALLAR | G76: =SUMIF('VTA POR EMPLEADO'!A61:A63,ERECTUS!F76,'VTA POR EMPLEADO'!B61:B63) -> 15737.02 | O76: =SUM(I76:N76) -> 0
F77: ='VTA POR EMPLEADO'!A62 -> FATIMA CAROLINA VALENCIA ENRIQUEZ | G77: =SUMIF('VTA POR EMPLEADO'!A62:A64,ERECTUS!F77,'VTA POR EMPLEADO'!B62:B64) -> 115165.34 | I77: =G77*D7 -> 1439.5667 | J77: =Juguetes!O17 -> 275.8619 | K77: =CXO!O18 -> 1792.0746 | L77: =DUSA!O16 -> 654.3048 | M77: =Pastilla!O18 -> 693.108 | O77: =SUM(I77:N77) -> 4854.9161 | P77: =O77/D76 -> 0.035316956 | Q77: =O77/$D$92 -> 0.0022140754
F78: ='VTA POR EMPLEADO'!A63 -> JESáS ULISES PEREZ VARGAS | G78: =SUMIF('VTA POR EMPLEADO'!A63:A65,ERECTUS!F78,'VTA POR EMPLEADO'!B63:B65) -> 6564.64 | O78: =SUM(I78:N78) -> 0
O79: =SUM(I79:N79) -> 0
O80: =SUM(I80:N80) -> 0
B81: Plaza Zenter CEL | C81: 435000 | D81: =SUMIF('BASE GENERAL'!B4:B3114,ERECTUS!B81,'BASE GENERAL'!J4:J3114) -> 264504.05 | E81: =D81/C81 -> 0.60805529 | F81: ='VTA POR EMPLEADO'!A65 -> ALFONSO M CARBALLAR | G81: =SUMIF('VTA POR EMPLEADO'!A65:A68,ERECTUS!F81,'VTA POR EMPLEADO'!B65:B68) -> 32150.83 | O81: =SUM(I81:N81) -> 0
F82: ='VTA POR EMPLEADO'!A66 -> ANGEL DANILO RODRIGUEZ LOPEZ | G82: =SUMIF('VTA POR EMPLEADO'!A66:A69,ERECTUS!F82,'VTA POR EMPLEADO'!B66:B69) -> 23543.06 | O82: =SUM(I82:N82) -> 0
F83: ='VTA POR EMPLEADO'!A67 -> GERMAN GUZMAN AGUIRRE | G83: =SUMIF('VTA POR EMPLEADO'!A67:A70,ERECTUS!F83,'VTA POR EMPLEADO'!B67:B70) -> 2456.9 | O83: =SUM(I83:N83) -> 0
F84: ='VTA POR EMPLEADO'!A68 -> NICOLAS H ACEVES | G84: =SUMIF('VTA POR EMPLEADO'!A68:A71,ERECTUS!F84,'VTA POR EMPLEADO'!B68:B71) -> 206353.26 | I84: =SUPERVISOR!E15+SUPERVISOR!G15+SUPERVISOR!I15+SUPERVISOR!N15 -> 11497.406 | J84: =SUPERVISOR!K15 -> 2033.5551 | K84: =SUPERVISOR!J15 -> 11758.856 | L84: =SUPERVISOR!L15 -> 8594.6706 | M84: =SUPERVISOR!M15 -> 2460.5334 | O84: =SUM(I84:N84) -> 36345.021 | P84: =O84/D81 -> 0.13740818 | Q84: =O84/$D$92 -> 0.016575079
B85: Provenza-Cel | C85: 145000 | D85: =SUMIF('BASE GENERAL'!B4:B3114,ERECTUS!B85,'BASE GENERAL'!J4:J3114) -> 128293.4 | E85: =D85/C85 -> 0.88478207 | F85: ='VTA POR EMPLEADO'!A70 -> ALFONSO M CARBALLAR | G85: =SUMIF('VTA POR EMPLEADO'!A70:A72,ERECTUS!F85,'VTA POR EMPLEADO'!B70:B72) -> 2866.36 | O85: =SUM(I85:N85) -> 0
F86: ='VTA POR EMPLEADO'!A71 -> ANGEL DANILO RODRIGUEZ LOPEZ | G86: =SUMIF('VTA POR EMPLEADO'!A71:A73,ERECTUS!F86,'VTA POR EMPLEADO'!B71:B73) -> 18952.57 | O86: =SUM(I86:N86) -> 0
F87: ='VTA POR EMPLEADO'!A72 -> BRYAN ALEJANDRO V BERNAL | G87: =SUMIF('VTA POR EMPLEADO'!A72:A74,ERECTUS!F87,'VTA POR EMPLEADO'!B72:B74) -> 106474.47 | I87: =G87*D7 -> 1330.9309 | J87: =Juguetes!O13 -> 149.1379 | K87: =CXO!O14 -> 2585.7252 | L87: =DUSA!O12 -> 637.925 | M87: =Pastilla!O14 -> 381.2094 | N87: ='semana 4'!N23 -> 393.3669 | O87: =SUM(I87:N87) -> 5478.2953 | P87: =O87/D85 -> 0.042701302 | Q87: =O87/$D$92 -> 0.0024983663
O88: =SUM(I88:N88) -> 0
B89: ALFONSO M CARBALLAR | C89: 150000 | D89: =G89 -> 109150.63 | E89: =D89/C89 -> 0.72767087 | F89: ALFONSO M CARBALLAR | G89: =SUMIF('BASE GENERAL'!D4:D3114,ERECTUS!F89,'BASE GENERAL'!J4:J3114) -> 109150.63 | J89: =Juguetes!O9 -> 54.8706 | K89: =CXO!O10 -> 2963.535 | L89: =DUSA!O8 -> 752.236 | M89: =Pastilla!O10 -> 415.8648 | O89: =SUM(I89:N89) -> 4186.5064 | P89: =O89/D89 -> 0.038355311 | Q89: =O89/D92 -> 0.0019092484
B90: ANGEL DANILO RODRIGUEZ LOPEZ | C90: 110000 | D90: =G90 -> 108223.96 | E90: =D90/C90 -> 0.98385418 | F90: ANGEL DANILO RODRIGUEZ LOPEZ | G90: =SUMIF('BASE GENERAL'!D5:D3115,ERECTUS!F90,'BASE GENERAL'!J5:J3115) -> 108223.96 | I90: =G90*I6 -> 2164.4792 | J90: =Juguetes!O10 -> 243.1032 | K90: =CXO!O11 -> 1867.7604 | L90: =DUSA!O9 -> 478.099 | M90: =Pastilla!O11 -> 589.1418 | O90: =SUM(I90:N90) -> 5342.5836 | P90: =O90/D90 -> 0.049365996 | Q90: =O90/$D$92 -> 0.0024364753
B91: GERMAN GUZMAN AGUIRRE | C91: 125000 | D91: =G91 -> 86478.28 | E91: =D91/C91 -> 0.69182624 | F91: GERMAN GUZMAN AGUIRRE | G91: =SUMIF('BASE GENERAL'!D6:D3116,ERECTUS!F91,'BASE GENERAL'!J6:J3116) -> 86478.28 | J91: =Juguetes!O18 -> 0 | K91: =CXO!O19 -> 0 | L91: =DUSA!O17 -> 0 | M91: =Pastilla!O19 -> 0 | O91: =SUM(I91:N91) -> 0 | P91: =O91/D91 -> 0 | Q91: =O91/D92 -> 0
C92: =SUM(C13:C88) -> 2680000 | D92: =SUM(D13:D88) -> 2192751 | E92: =D92/C92 -> 0.81819068 | G92: =SUM(G3:G88) -> 2209725.1 | H92: =SUM(H13:H91) -> 0 | I92: =SUM(I13:I91) -> 38117.971 | J92: =SUM(J13:J91) -> 4967.5621 | K92: =SUM(K13:K91) -> 51348.586 | L92: =SUM(L13:L91) -> 18074.073 | M92: =SUM(M13:M91) -> 10708.519 | N92: =SUM(N13:N91) -> 5425.5499 | O92: =SUM(O13:O91) -> 128642.26 | Q92: =O92/D92 -> 0.058667063
H94: % de participación | I94: =I92/D92 -> 0.017383629 | J94: =J92/D92 -> 0.0022654474 | K94: =K92/D92 -> 0.023417427 | L94: =L92/D92 -> 0.0082426474 | M94: =M92/D92 -> 0.0048835999 | N94: =N92/D92 -> 0.0024743119 | O94: =O92/D92 -> 0.058667063

Sheet Hoja1
F2: Venta por vendedor | G2: % ALCANCE | H2: CUOTA MENSUAL | I2: Juguetes en General $ 1,500 | J2: CXO | K2: DUSA | L2: PASTILLA SHUMA | M2: SEMANAL | N2: PAGO
E3: NOE JONAS D CEL | F3: 145615.46 | G3: 77 | H3: 1092.1159 | I3: 333.6205 | J3: 2583.1056 | K3: 675.8578 | L3: 415.8648 | N3: 5100.5646
E4: JESUS ALBERTO M GARCIA | F4: 153842.85 | G4: 92 | H4: 3076.857 | I4: 311.3362 | J4: 3412.5 | K4: 803.0956 | L4: 797.0742 | N4: 8400.863
E5: IRIS CRISTINA RIVERA PEREZ CELESTERRA | F5: 104594.24 | G5: 115 | H5: 2614.856 | I5: 164.2241 | J5: 2639.5536 | K5: 495.687 | L5: 415.8648 | M5: 747.3649 | N5: 7077.5504
E6: HECTOR MANUEL P CELEST | F6: 160125.21 | G6: 93 | H6: 3202.5042 | I6: 368.491 | J6: 3786.2418 | K6: 834.9926 | L6: 762.4188 | M6: 1367.9707 | N6: 10322.619
E7: CELINA HERMILA M GUILLEN | F7: 54879.1 | G7: 57 | I7: 42.7586 | J7: 1204.3968 | K7: 326.0316 | L7: 381.2094 | N7: 1954.3964
E8: Rodolfo Serrano Amezcua | F8: 82956.75 | G8: 83 | H8: 1036.9594 | I8: 34.4827 | J8: 2793.1044 | K8: 358.2728 | L8: 415.8648 | M8: 233.2755 | N8: 4871.9596
E9: EDGAR MOISES A NAVARRO | F9: 118721.69 | G9: 119 | H9: 2968.0422 | I9: 247.4136 | J9: 1822.332 | K9: 704.3056 | L9: 589.1418 | M9: 889.8901 | N9: 7221.1253
E10: ANTONIO EDMUNDO E CAMBEROS | F10: 132762.74 | G10: 84 | H10: 1659.5343 | I10: 136.2068 | J10: 3113.0172 | K10: 667.4074 | L10: 1005.0066 | N10: 6581.1723
E11: DELIA AGUIRRE CERVANTES | F11: 112626.96 | G11: 121 | H11: 2815.674 | I11: 162.9309 | J11: 2947.5042 | K11: 437.0642 | L11: 485.1756 | M11: 1068.4249 | N11: 7916.7738
E12: OSCAR ANTONIO L CEL | F12: 103689.32 | G12: 81 | H12: 1296.1165 | I12: 154.3103 | J12: 1598.2776 | K12: 780.8564 | L12: 277.2432 | M12: 372.7143 | N12: 4479.5183
E13: BERTHA SOFIA O BERMEJO | F13: 96146.43 | G13: 102 | H13: 1922.9286 | I13: 154.3967 | J13: 2950.3428 | K13: 363.7892 | L13: 277.2432 | M13: 352.5426 | N13: 6021.2431
E14: JESáS ULISES PEREZ VARGAS | F14: 78685.1 | G14: 63 | I14: 100.862 | J14: 1530.2592 | K14: 509.4778 | L14: 346.554 | N14: 2487.153
E15: FATIMA CAROLINA VALENCIA ENRIQUEZ | F15: 115165.34 | G15: 89 | H15: 1439.5667 | I15: 275.8619 | J15: 1792.0746 | K15: 654.3048 | L15: 693.108 | N15: 4854.9161
E16: NICOLAS H ACEVES | F16: 206353.26 | G16: 61 | H16: 11497.406 | I16: 2033.5551 | J16: 11758.856 | K16: 8594.6706 | L16: 2460.5334 | N16: 36345.021
E17: BRYAN ALEJANDRO V BERNAL | F17: 106474.47 | G17: 88 | H17: 1330.9309 | I17: 149.1379 | J17: 2585.7252 | K17: 637.925 | L17: 381.2094 | M17: 393.3669 | N17: 5478.2953
E18: ALFONSO M CARBALLAR | F18: 109150.63 | G18: 73 | I18: 54.8706 | J18: 2963.535 | K18: 752.236 | L18: 415.8648 | N18: 4186.5064
E19: ANGEL DANILO RODRIGUEZ LOPEZ | F19: 108223.96 | G19: 98 | H19: 2164.4792 | I19: 243.1032 | J19: 1867.7604 | K19: 478.099 | L19: 589.1418 | N19: 5342.5836
N20: =SUM(N3:N19) -> 128642.26

Sheet Pastilla
B4: UBICACION | C4: FECHA | D4: VENDEDOR | E4: SKU | F4: ARTICULO | G4: FAMILIA COMERCIAL | H4: MARCA | I4: CANTIDAD | J4: SUBTOT
B5: Arcos-C | C5: 02/01/2026 | D5: NOE JONAS D CEL | E5: 7503013378690 | F5: Shumatsu 3 pzas - DUSA | G5: CONSUMIBLE PROPIO | H5: DUSA | I5: 1 | J5: 577.59
B6: Arcos-C | C6: 16/01/2026 | D6: NOE JONAS D CEL | E6: 7503013378690 | F6: Shumatsu 3 pzas - DUSA | G6: CONSUMIBLE PROPIO | H6: DUSA | I6: 1 | J6: 577.59
B7: Arcos-C | C7: 17/01/2026 | D7: NOE JONAS D CEL | E7: 7503013378690 | F7: Shumatsu 3 pzas - DUSA | G7: CONSUMIBLE PROPIO | H7: DUSA | I7: 3 | J7: 1732.77
B8: Arcos-C | C8: 23/01/2026 | D8: NOE JONAS D CEL | E8: 7503013378690 | F8: Shumatsu 3 pzas - DUSA | G8: CONSUMIBLE PROPIO | H8: DUSA | I8: 5 | J8: 2887.95
B9: Arcos-C | C9: 24/01/2026 | D9: NOE JONAS D CEL | E9: 7503013378690 | F9: Shumatsu 3 pzas - DUSA | G9: CONSUMIBLE PROPIO | H9: DUSA | I9: 1 | J9: 577.59 | L9: Etiquetas de fila | M9: Suma de SUBTOT | O9: 0.06 | P9: 0.03
B10: Arcos-C | C10: 30/01/2026 | D10: NOE JONAS D CEL | E10: 7503013378690 | F10: Shumatsu 3 pzas - DUSA | G10: CONSUMIBLE PROPIO | H10: DUSA | I10: 1 | J10: 577.59 | L10: ALFONSO M CARBALLAR | M10: 6931.08 | O10: =M10*$O$9 -> 415.8648
B11: Camino Real -C | C11: 02/01/2026 | D11: JESUS ALBERTO M GARCIA | E11: 7503013378690 | F11: Shumatsu 3 pzas - DUSA | G11: CONSUMIBLE PROPIO | H11: DUSA | I11: 1 | J11: 577.59 | L11: ANGEL DANILO RODRIGUEZ LOPEZ | M11: 9819.03 | O11: =M11*$O$9 -> 589.1418
B12: Camino Real -C | C12: 03/01/2026 | D12: JESUS ALBERTO M GARCIA | E12: 7503013378690 | F12: Shumatsu 3 pzas - DUSA | G12: CONSUMIBLE PROPIO | H12: DUSA | I12: 1 | J12: 577.59 | L12: ANTONIO EDMUNDO E CAMBEROS | M12: 16750.11 | O12: =M12*$O$9 -> 1005.0066
B13: Camino Real -C | C13: 05/01/2026 | D13: ALFONSO M CARBALLAR | E13: 7503013378690 | F13: Shumatsu 3 pzas - DUSA | G13: CONSUMIBLE PROPIO | H13: DUSA | I13: 1 | J13: 577.59 | L13: BERTHA SOFIA O BERMEJO | M13: 4620.72 | O13: =M13*$O$9 -> 277.2432
B14: Camino Real -C | C14: 06/01/2026 | D14: JESUS ALBERTO M GARCIA | E14: 7503013378690 | F14: Shumatsu 3 pzas - DUSA | G14: CONSUMIBLE PROPIO | H14: DUSA | I14: 2 | J14: 1155.18 | L14: BRYAN ALEJANDRO V BERNAL | M14: 6353.49 | O14: =M14*$O$9 -> 381.2094
B15: Camino Real -C | C15: 17/01/2026 | D15: JESUS ALBERTO M GARCIA | E15: 7503013378690 | F15: Shumatsu 3 pzas - DUSA | G15: CONSUMIBLE PROPIO | H15: DUSA | I15: 5 | J15: 2887.95 | L15: CELINA HERMILA M GUILLEN | M15: 6353.49 | O15: =M15*$O$9 -> 381.2094
B16: Camino Real -C | C16: 21/01/2026 | D16: JESUS ALBERTO M GARCIA | E16: 7503013378690 | F16: Shumatsu 3 pzas - DUSA | G16: CONSUMIBLE PROPIO | H16: DUSA | I16: 4 | J16: 2310.36 | L16: DELIA AGUIRRE CERVANTES | M16: 8086.26 | O16: =M16*$O$9 -> 485.1756
B17: Camino Real -C | C17: 22/01/2026 | D17: JESUS ALBERTO M GARCIA | E17: 7503013378690 | F17: Shumatsu 3 pzas - DUSA | G17: CONSUMIBLE PROPIO | H17: DUSA | I17: 1 | J17: 577.59 | L17: EDGAR MOISES A NAVARRO | M17: 9819.03 | O17: =M17*$O$9 -> 589.1418
B18: Camino Real -C | C18: 23/01/2026 | D18: JESUS ALBERTO M GARCIA | E18: 7503013378690 | F18: Shumatsu 3 pzas - DUSA | G18: CONSUMIBLE PROPIO | H18: DUSA | I18: 1 | J18: 577.59 | L18: FATIMA CAROLINA VALENCIA ENRIQUEZ | M18: 11551.8 | O18: =M18*$O$9 -> 693.108
B19: Camino Real -C | C19: 24/01/2026 | D19: JESUS ALBERTO M GARCIA | E19: 7503013378690 | F19: Shumatsu 3 pzas - DUSA | G19: CONSUMIBLE PROPIO | H19: DUSA | I19: 1 | J19: 577.59 | L19: GERMAN GUZMAN AGUIRRE | M19: 6931.08 | O19: 0
B20: Camino Real -C | C20: 25/01/2026 | D20: JESUS ALBERTO M GARCIA | E20: 7503013378690 | F20: Shumatsu 3 pzas - DUSA | G20: CONSUMIBLE PROPIO | H20: DUSA | I20: 1 | J20: 577.59 | L20: HECTOR MANUEL P CELEST | M20: 12706.98 | O20: =M20*$O$9 -> 762.4188
B21: Camino Real -C | C21: 26/01/2026 | D21: JESUS ALBERTO M GARCIA | E21: 7503013378690 | F21: Shumatsu 3 pzas - DUSA | G21: CONSUMIBLE PROPIO | H21: DUSA | I21: 1 | J21: 577.59 | L21: IRIS CRISTINA RIVERA PEREZ CELESTERRA | M21: 6931.08 | O21: =M21*$O$9 -> 415.8648
B22: Camino Real -C | C22: 27/01/2026 | D22: JESUS ALBERTO M GARCIA | E22: 7503013378690 | F22: Shumatsu 3 pzas - DUSA | G22: CONSUMIBLE PROPIO | H22: DUSA | I22: 3 | J22: 1732.77 | L22: JESáS ULISES PEREZ VARGAS | M22: 5775.9 | O22: =M22*$O$9 -> 346.554
B23: Camino Real -C | C23: 30/01/2026 | D23: JESUS ALBERTO M GARCIA | E23: 7503013378690 | F23: Shumatsu 3 pzas - DUSA | G23: CONSUMIBLE PROPIO | H23: DUSA | I23: 2 | J23: 1155.18 | L23: JESUS ALBERTO M GARCIA | M23: 13284.57 | O23: =M23*$O$9 -> 797.0742
B24: Circunvalación CELESTERRA | C24: 02/01/2026 | D24: ANGEL DANILO RODRIGUEZ LOPEZ | E24: 7503013378690 | F24: Shumatsu 3 pzas - DUSA | G24: CONSUMIBLE PROPIO | H24: DUSA | I24: 3 | J24: 1732.77 | L24: MARIA EDUWIGES DEL TORO ORTEGA | M24: 8086.26 | O24: 0
B25: Circunvalación CELESTERRA | C25: 03/01/2026 | D25: IRIS CRISTINA RIVERA PEREZ CELESTERRA | E25: 7503013378690 | F25: Shumatsu 3 pzas - DUSA | G25: CONSUMIBLE PROPIO | H25: DUSA | I25: 1 | J25: 577.59 | L25: NICOLAS H ACEVES | M25: 6931.08 | O25: 0
B26: Circunvalación CELESTERRA | C26: 19/01/2026 | D26: IRIS CRISTINA RIVERA PEREZ CELESTERRA | E26: 7503013378690 | F26: Shumatsu 3 pzas - DUSA | G26: CONSUMIBLE PROPIO | H26: DUSA | I26: 1 | J26: 577.59 | L26: NINOSCHKA VILLAREAL GONZALEZ | M26: 4620.72 | O26: 0
B27: Circunvalación CELESTERRA | C27: 20/01/2026 | D27: IRIS CRISTINA RIVERA PEREZ CELESTERRA | E27: 7503013378690 | F27: Shumatsu 3 pzas - DUSA | G27: CONSUMIBLE PROPIO | H27: DUSA | I27: 1 | J27: 577.59 | L27: NOE JONAS D CEL | M27: 6931.08 | O27: =M27*$O$9 -> 415.8648
B28: Circunvalación CELESTERRA | C28: 22/01/2026 | D28: IRIS CRISTINA RIVERA PEREZ CELESTERRA | E28: 7503013378690 | F28: Shumatsu 3 pzas - DUSA | G28: CONSUMIBLE PROPIO | H28: DUSA | I28: 2 | J28: 1155.18 | L28: OSCAR ANTONIO L CEL | M28: 4620.72 | O28: =M28*$O$9 -> 277.2432
B29: Circunvalación CELESTERRA | C29: 23/01/2026 | D29: IRIS CRISTINA RIVERA PEREZ CELESTERRA | E29: 7503013378690 | F29: Shumatsu 3 pzas - DUSA | G29: CONSUMIBLE PROPIO | H29: DUSA | I29: 2 | J29: 1155.18 | L29: Rodolfo Serrano Amezcua | M29: 6931.08 | O29: =M29*$O$9 -> 415.8648
B30: Circunvalación CELESTERRA | C30: 24/01/2026 | D30: JESáS ULISES PEREZ VARGAS | E30: 7503013378690 | F30: Shumatsu 3 pzas - DUSA | G30: CONSUMIBLE PROPIO | H30: DUSA | I30: 2 | J30: 1155.18 | L30: Total general | M30: 164035.56 | O30: =SUM(O10:O29) -> 8247.9852
B31: Circunvalación CELESTERRA | C31: 26/01/2026 | D31: GERMAN GUZMAN AGUIRRE | E31: 7503013378690 | F31: Shumatsu 3 pzas - DUSA | G31: CONSUMIBLE PROPIO | H31: DUSA | I31: 1 | J31: 577.59
B32: Circunvalación CELESTERRA | C32: 28/01/2026 | D32: IRIS CRISTINA RIVERA PEREZ CELESTERRA | E32: 7503013378690 | F32: Shumatsu 3 pzas - DUSA | G32: CONSUMIBLE PROPIO | H32: DUSA | I32: 1 | J32: 577.59
B33: Circunvalación CELESTERRA | C33: 29/01/2026 | D33: IRIS CRISTINA RIVERA PEREZ CELESTERRA | E33: 7503013378690 | F33: Shumatsu 3 pzas - DUSA | G33: CONSUMIBLE PROPIO | H33: DUSA | I33: 1 | J33: 577.59
B34: Circunvalación CELESTERRA | C34: 31/01/2026 | D34: IRIS CRISTINA RIVERA PEREZ CELESTERRA | E34: 7503013378690 | F34: Shumatsu 3 pzas - DUSA | G34: CONSUMIBLE PROPIO | H34: DUSA | I34: 3 | J34: 1732.77
B35: Conchitas CEL | C35: 02/01/2026 | D35: ALFONSO M CARBALLAR | E35: 7503013378690 | F35: Shumatsu 3 pzas - DUSA | G35: CONSUMIBLE PROPIO | H35: DUSA | I35: 4 | J35: 2310.36
B36: Conchitas CEL | C36: 04/01/2026 | D36: HECTOR MANUEL P CELEST | E36: 7503013378690 | F36: Shumatsu 3 pzas - DUSA | G36: CONSUMIBLE PROPIO | H36: DUSA | I36: 4 | J36: 2310.36
B37: Conchitas CEL | C37: 05/01/2026 | D37: HECTOR MANUEL P CELEST | E37: 7503013378690 | F37: Shumatsu 3 pzas - DUSA | G37: CONSUMIBLE PROPIO | H37: DUSA | I37: 2 | J37: 1155.18
B38: Conchitas CEL | C38: 06/01/2026 | D38: HECTOR MANUEL P CELEST | E38: 7503013378690 | F38: Shumatsu 3 pzas - DUSA | G38: CONSUMIBLE PROPIO | H38: DUSA | I38: 1 | J38: 577.59
B39: Conchitas CEL | C39: 09/01/2026 | D39: HECTOR MANUEL P CELEST | E39: 7503013378690 | F39: Shumatsu 3 pzas - DUSA | G39: CONSUMIBLE PROPIO | H39: DUSA | I39: 1 | J39: 577.59
B40: Conchitas CEL | C40: 16/01/2026 | D40: HECTOR MANUEL P CELEST | E40: 7503013378690 | F40: Shumatsu 3 pzas - DUSA | G40: CONSUMIBLE PROPIO | H40: DUSA | I40: 3 | J40: 1732.77
B41: Conchitas CEL | C41: 17/01/2026 | D41: HECTOR MANUEL P CELEST | E41: 7503013378690 | F41: Shumatsu 3 pzas - DUSA | G41: CONSUMIBLE PROPIO | H41: DUSA | I41: 1 | J41: 577.59
B42: Conchitas CEL | C42: 19/01/2026 | D42: HECTOR MANUEL P CELEST | E42: 7503013378690 | F42: Shumatsu 3 pzas - DUSA | G42: CONSUMIBLE PROPIO | H42: DUSA | I42: 1 | J42: 577.59
... B178: Provenza-Cel | C178: 30/01/2026 | D178: BRYAN ALEJANDRO V BERNAL | E178: 7503013378690 | F178: Shumatsu 3 pzas - DUSA | G178: CONSUMIBLE PROPIO | H178: DUSA | I178: 1 | J178: 577.59

Sheet DUSA
B4: UBICACION | C4: FECHA | D4: VENDEDOR | E4: SKU | F4: ARTICULO | G4: FAMILIA COMERCIAL | H4: MARCA | I4: CANTIDAD | J4: SUBTOT
B5: Arcos-C | C5: 02/01/2026 | D5: NOE JONAS D CEL | E5: 7503013378652 | F5: Liquid Love Backdoor 100ml - DUSA | G5: CONSUMIBLE PROPIO | H5: DUSA | I5: 1 | J5: 1077.59
B6: Arcos-C | C6: 04/01/2026 | D6: ANGEL DANILO RODRIGUEZ LOPEZ | E6: 7503032300993 | F6: Liquid Love Pleasure 30ml - DUSA | G6: CONSUMIBLE PROPIO | H6: DUSA | I6: 1 | J6: 301.72
B7: Arcos-C | C7: 04/01/2026 | D7: ANGEL DANILO RODRIGUEZ LOPEZ | E7: 7503050524241 | F7: Orgasmik 30ml - DUSA | G7: CONSUMIBLE PROPIO | H7: DUSA | I7: 1 | J7: 431.03 | L7: Etiquetas de fila | M7: Suma de SUBTOT | O7: 0.02 | P7: 0.01
B8: Arcos-C | C8: 05/01/2026 | D8: NOE JONAS D CEL | E8: 7503013378492 | F8: Clean Whisper 120ml - DUSA | G8: CONSUMIBLE PROPIO | H8: DUSA | I8: 1 | J8: 301.72 | L8: ALFONSO M CARBALLAR | M8: 37611.8 | O8: =M8*$O$7 -> 752.236
B9: Arcos-C | C9: 06/01/2026 | D9: NOE JONAS D CEL | E9: 7503032300993 | F9: Liquid Love Pleasure 30ml - DUSA | G9: CONSUMIBLE PROPIO | H9: DUSA | I9: 1 | J9: 301.72 | L9: ANGEL DANILO RODRIGUEZ LOPEZ | M9: 23904.95 | O9: =M9*$O$7 -> 478.099
B10: Arcos-C | C10: 06/01/2026 | D10: NOE JONAS D CEL | E10: 7503013378010 | F10: Rigidex 2 pzas - DUSA | G10: CONSUMIBLE PROPIO | H10: DUSA | I10: 1 | J10: 431.03 | L10: ANTONIO EDMUNDO E CAMBEROS | M10: 33370.37 | O10: =M10*$O$7 -> 667.4074
B11: Arcos-C | C11: 06/01/2026 | D11: NOE JONAS D CEL | E11: 7503020596957 | F11: Shot Shumatsu Fun Hombre - DUSA | G11: CONSUMIBLE PROPIO | H11: DUSA | I11: 1 | J11: 172.41 | L11: BERTHA SOFIA O BERMEJO | M11: 18189.46 | O11: =M11*$O$7 -> 363.7892
B12: Arcos-C | C12: 06/01/2026 | D12: NOE JONAS D CEL | E12: 7503024256192 | F12: Shot Shumatsu Fun Mujer - DUSA | G12: CONSUMIBLE PROPIO | H12: DUSA | I12: 1 | J12: 172.41 | L12: BRYAN ALEJANDRO V BERNAL | M12: 31896.25 | O12: =M12*$O$7 -> 637.925
B13: Arcos-C | C13: 07/01/2026 | D13: NOE JONAS D CEL | E13: 7503013378645 | F13: Liquid Love Pleasure 100ml - DUSA | G13: CONSUMIBLE PROPIO | H13: DUSA | I13: 2 | J13: 1551.72 | L13: CELINA HERMILA M GUILLEN | M13: 16301.58 | O13: =M13*$O$7 -> 326.0316
B14: Arcos-C | C14: 07/01/2026 | D14: NOE JONAS D CEL | E14: 7503050524241 | F14: Orgasmik 30ml - DUSA | G14: CONSUMIBLE PROPIO | H14: DUSA | I14: 1 | J14: 431.03 | L14: DELIA AGUIRRE CERVANTES | M14: 21853.21 | O14: =M14*$O$7 -> 437.0642
B15: Arcos-C | C15: 08/01/2026 | D15: NOE JONAS D CEL | E15: 7503013378980 | F15: Lubricante Body Surf Termico Chicle DUSA 60ml | G15: CONSUMIBLE PROPIO | H15: DUSA | I15: 1 | J15: 387.93 | L15: EDGAR MOISES A NAVARRO | M15: 35215.28 | O15: =M15*$O$7 -> 704.3056
B16: Arcos-C | C16: 09/01/2026 | D16: NOE JONAS D CEL | E16: 7503013378645 | F16: Liquid Love Pleasure 100ml - DUSA | G16: CONSUMIBLE PROPIO | H16: DUSA | I16: 3 | J16: 2327.58 | L16: FATIMA CAROLINA VALENCIA ENRIQUEZ | M16: 32715.24 | O16: =M16*$O$7 -> 654.3048
B17: Arcos-C | C17: 09/01/2026 | D17: NOE JONAS D CEL | E17: 7503013378980 | F17: Lubricante Body Surf Termico Chicle DUSA 60ml | G17: CONSUMIBLE PROPIO | H17: DUSA | I17: 1 | J17: 387.93 | L17: GERMAN GUZMAN AGUIRRE | M17: 19223.99 | O17: 0
B18: Arcos-C | C18: 10/01/2026 | D18: NOE JONAS D CEL | E18: 7503043917012 | F18: Liquid Love Backdoor 30ml - DUSA | G18: CONSUMIBLE PROPIO | H18: DUSA | I18: 1 | J18: 301.72 | L18: HECTOR MANUEL P CELEST | M18: 41749.63 | O18: =M18*$O$7 -> 834.9926
B19: Arcos-C | C19: 10/01/2026 | D19: NOE JONAS D CEL | E19: 7503013378645 | F19: Liquid Love Pleasure 100ml - DUSA | G19: CONSUMIBLE PROPIO | H19: DUSA | I19: 1 | J19: 775.86 | L19: IRIS CRISTINA RIVERA PEREZ CELESTERRA | M19: 24784.35 | O19: =M19*$O$7 -> 495.687
B20: Arcos-C | C20: 10/01/2026 | D20: NOE JONAS D CEL | E20: 7503024256154 | F20: Lubricante Body Surf Termico Cereza DUSA 60ml | G20: CONSUMIBLE PROPIO | H20: DUSA | I20: 1 | J20: 387.93 | L20: JESáS ULISES PEREZ VARGAS | M20: 25473.89 | O20: =M20*$O$7 -> 509.4778
B21: Arcos-C | C21: 10/01/2026 | D21: NOE JONAS D CEL | E21: 7503013378010 | F21: Rigidex 2 pzas - DUSA | G21: CONSUMIBLE PROPIO | H21: DUSA | I21: 3 | J21: 1293.1 | L21: JESUS ALBERTO M GARCIA | M21: 40154.78 | O21: =M21*$O$7 -> 803.0956
B22: Arcos-C | C22: 10/01/2026 | D22: NOE JONAS D CEL | E22: 7503020596049 | F22: Sensicool - DUSA | G22: CONSUMIBLE PROPIO | H22: DUSA | I22: 1 | J22: 431.03 | L22: MARIA EDUWIGES DEL TORO ORTEGA | M22: 17111.93 | O22: 0
B23: Arcos-C | C23: 10/01/2026 | D23: NOE JONAS D CEL | E23: 7503020596957 | F23: Shot Shumatsu Fun Hombre - DUSA | G23: CONSUMIBLE PROPIO | H23: DUSA | I23: 1 | J23: 172.41 | L23: NICOLAS H ACEVES | M23: 49741.11 | O23: 0
B24: Arcos-C | C24: 13/01/2026 | D24: NOE JONAS D CEL | E24: 7503013378645 | F24: Liquid Love Pleasure 100ml - DUSA | G24: CONSUMIBLE PROPIO | H24: DUSA | I24: 2 | J24: 1551.72 | L24: NINOSCHKA VILLAREAL GONZALEZ | M24: 12930.87 | O24: 0
B25: Arcos-C | C25: 13/01/2026 | D25: NOE JONAS D CEL | E25: 7503013378010 | F25: Rigidex 2 pzas - DUSA | G25: CONSUMIBLE PROPIO | H25: DUSA | I25: 3 | J25: 1293.1 | L25: NOE JONAS D CEL | M25: 33792.89 | O25: =M25*$O$7 -> 675.8578
B26: Arcos-C | C26: 14/01/2026 | D26: NOE JONAS D CEL | E26: 7503013378645 | F26: Liquid Love Pleasure 100ml - DUSA | G26: CONSUMIBLE PROPIO | H26: DUSA | I26: 1 | J26: 775.86 | L26: OSCAR ANTONIO L CEL | M26: 39042.82 | O26: =M26*$O$7 -> 780.8564
B27: Arcos-C | C27: 14/01/2026 | D27: NOE JONAS D CEL | E27: 7503013378010 | F27: Rigidex 2 pzas - DUSA | G27: CONSUMIBLE PROPIO | H27: DUSA | I27: 1 | J27: 431.03 | L27: Rodolfo Serrano Amezcua | M27: 17913.64 | O27: =M27*$O$7 -> 358.2728
B28: Arcos-C | C28: 14/01/2026 | D28: NOE JONAS D CEL | E28: 7503020596957 | F28: Shot Shumatsu Fun Hombre - DUSA | G28: CONSUMIBLE PROPIO | H28: DUSA | I28: 3 | J28: 517.23 | L28: Total general | M28: 572978.04 | O28: =SUM(O8:O27) -> 9479.4028
B29: Arcos-C | C29: 14/01/2026 | D29: NOE JONAS D CEL | E29: 7503024256192 | F29: Shot Shumatsu Fun Mujer - DUSA | G29: CONSUMIBLE PROPIO | H29: DUSA | I29: 2 | J29: 344.82
B30: Arcos-C | C30: 15/01/2026 | D30: NOE JONAS D CEL | E30: 7503013378492 | F30: Clean Whisper 120ml - DUSA | G30: CONSUMIBLE PROPIO | H30: DUSA | I30: 2 | J30: 603.44
B31: Arcos-C | C31: 15/01/2026 | D31: NOE JONAS D CEL | E31: 7503013378799 | F31: Lubricante Body Surf Termico Citricos DUSA 60ml | G31: CONSUMIBLE PROPIO | H31: DUSA | I31: 1 | J31: 387.93
B32: Arcos-C | C32: 15/01/2026 | D32: NOE JONAS D CEL | E32: 7503050524241 | F32: Orgasmik 30ml - DUSA | G32: CONSUMIBLE PROPIO | H32: DUSA | I32: 3 | J32: 1293.09
B33: Arcos-C | C33: 15/01/2026 | D33: NOE JONAS D CEL | E33: 7503013378010 | F33: Rigidex 2 pzas - DUSA | G33: CONSUMIBLE PROPIO | H33: DUSA | I33: 1 | J33: 431.03
B34: Arcos-C | C34: 15/01/2026 | D34: NOE JONAS D CEL | E34: 7503020596049 | F34: Sensicool - DUSA | G34: CONSUMIBLE PROPIO | H34: DUSA | I34: 1 | J34: 431.03
B35: Arcos-C | C35: 15/01/2026 | D35: NOE JONAS D CEL | E35: 7503050524258 | F35: Sensicool 30ml - DUSA | G35: CONSUMIBLE PROPIO | H35: DUSA | I35: 2 | J35: 862.07
B36: Arcos-C | C36: 17/01/2026 | D36: NOE JONAS D CEL | E36: 7503013378645 | F36: Liquid Love Pleasure 100ml - DUSA | G36: CONSUMIBLE PROPIO | H36: DUSA | I36: 1 | J36: 775.86
B37: Arcos-C | C37: 18/01/2026 | D37: GERMAN GUZMAN AGUIRRE | E37: 7503013378492 | F37: Clean Whisper 120ml - DUSA | G37: CONSUMIBLE PROPIO | H37: DUSA | I37: 1 | J37: 301.72
B38: Arcos-C | C38: 18/01/2026 | D38: GERMAN GUZMAN AGUIRRE | E38: 7503013378645 | F38: Liquid Love Pleasure 100ml - DUSA | G38: CONSUMIBLE PROPIO | H38: DUSA | I38: 1 | J38: 775.86
B39: Arcos-C | C39: 21/01/2026 | D39: NOE JONAS D CEL | E39: 7503043917012 | F39: Liquid Love Backdoor 30ml - DUSA | G39: CONSUMIBLE PROPIO | H39: DUSA | I39: 1 | J39: 301.72
B40: Arcos-C | C40: 21/01/2026 | D40: NOE JONAS D CEL | E40: 7503020596957 | F40: Shot Shumatsu Fun Hombre - DUSA | G40: CONSUMIBLE PROPIO | H40: DUSA | I40: 5 | J40: 862.05
... B1154: Provenza-Cel | C1154: 31/01/2026 | D1154: ANGEL DANILO RODRIGUEZ LOPEZ | E1154: 7503043917012 | F1154: Liquid Love Backdoor 30ml - DUSA | G1154: CONSUMIBLE PROPIO | H1154: DUSA | I1154: 1 | J1154: 301.72

Sheet CXO
B4: UBICACION | C4: FECHA | D4: VENDEDOR | E4: SKU | F4: ARTICULO | G4: FAMILIA COMERCIAL | H4: MARCA | I4: CANTIDAD | J4: SUBTOT
B5: Arcos-C | C5: 03/01/2026 | D5: NOE JONAS D CEL | E5: 7503032300443 | F5: Zoe bala vibradora RETAIL - CXO | G5: JUGUETE PROPIO | H5: CXO | I5: 2 | J5: 310.34
B6: Arcos-C | C6: 05/01/2026 | D6: NOE JONAS D CEL | E6: 7503030211021 | F6: Anillo desechable para pene Donut - CXO | G6: JUGUETE PROPIO | H6: CXO | I6: 1 | J6: 34.48
B7: Arcos-C | C7: 05/01/2026 | D7: NOE JONAS D CEL | E7: 7503043917081 | F7: Blade rosa anillo vibrador - CXO | G7: JUGUETE PROPIO | H7: CXO | I7: 1 | J7: 81.9
B8: Arcos-C | C8: 05/01/2026 | D8: NOE JONAS D CEL | E8: 7503032300443 | F8: Zoe bala vibradora RETAIL - CXO | G8: JUGUETE PROPIO | H8: CXO | I8: 2 | J8: 310.34
B9: Arcos-C | C9: 07/01/2026 | D9: NOE JONAS D CEL | E9: 7503030111031 | F9: Anillo vibrador de aro doble con estimulador y dildo Javier - CXO | G9: JUGUETE PROPIO | H9: CXO | I9: 1 | J9: 1681.03 | L9: Etiquetas de fila | M9: Suma de SUBTOT | O9: 0.06 | P9: 0.03
B10: Arcos-C | C10: 07/01/2026 | D10: NOE JONAS D CEL | E10: 7503043917081 | F10: Blade rosa anillo vibrador - CXO | G10: JUGUETE PROPIO | H10: CXO | I10: 3 | J10: 245.7 | L10: ALFONSO M CARBALLAR | M10: 49392.25 | O10: =M10*$O$9 -> 2963.535
B11: Arcos-C | C11: 07/01/2026 | D11: NOE JONAS D CEL | E11: M-22056 | F11: Dildo L 21cm - CXO | G11: JUGUETE PROPIO | H11: CXO | I11: 1 | J11: 689.66 | L11: ANGEL DANILO RODRIGUEZ LOPEZ | M11: 31129.34 | O11: =M11*$O$9 -> 1867.7604
B12: Arcos-C | C12: 07/01/2026 | D12: NOE JONAS D CEL | E12: 7503030102034 | F12: Dildo vibrador con control Anthony - CXO | G12: JUGUETE PROPIO | H12: CXO | I12: 1 | J12: 2112.07 | L12: ANTONIO EDMUNDO E CAMBEROS | M12: 51883.62 | O12: =M12*$O$9 -> 3113.0172
B13: Arcos-C | C13: 07/01/2026 | D13: NOE JONAS D CEL | E13: 7503032300443 | F13: Zoe bala vibradora RETAIL - CXO | G13: JUGUETE PROPIO | H13: CXO | I13: 3 | J13: 465.51 | L13: BERTHA SOFIA O BERMEJO | M13: 49172.38 | O13: =M13*$O$9 -> 2950.3428
B14: Arcos-C | C14: 08/01/2026 | D14: NOE JONAS D CEL | E14: 7503043917081 | F14: Blade rosa anillo vibrador - CXO | G14: JUGUETE PROPIO | H14: CXO | I14: 1 | J14: 81.9 | L14: BRYAN ALEJANDRO V BERNAL | M14: 43095.42 | O14: =M14*$O$9 -> 2585.7252
B15: Arcos-C | C15: 08/01/2026 | D15: NOE JONAS D CEL | E15: 7503030102034 | F15: Dildo vibrador con control Anthony - CXO | G15: JUGUETE PROPIO | H15: CXO | I15: 1 | J15: 2112.07 | L15: CELINA HERMILA M GUILLEN | M15: 20073.28 | O15: =M15*$O$9 -> 1204.3968
B16: Arcos-C | C16: 09/01/2026 | D16: NOE JONAS D CEL | E16: 7503043917081 | F16: Blade rosa anillo vibrador - CXO | G16: JUGUETE PROPIO | H16: CXO | I16: 1 | J16: 81.9 | L16: DELIA AGUIRRE CERVANTES | M16: 49125.07 | O16: =M16*$O$9 -> 2947.5042
B17: Arcos-C | C17: 09/01/2026 | D17: NOE JONAS D CEL | E17: 7503030102034 | F17: Dildo vibrador con control Anthony - CXO | G17: JUGUETE PROPIO | H17: CXO | I17: 1 | J17: 2112.07 | L17: EDGAR MOISES A NAVARRO | M17: 30372.2 | O17: =M17*$O$9 -> 1822.332
B18: Arcos-C | C18: 09/01/2026 | D18: NOE JONAS D CEL | E18: 7503030119041 | F18: Dildo vibrador con movimiento impulsor Arma - CXO | G18: JUGUETE PROPIO | H18: CXO | I18: 1 | J18: 1706.9 | L18: FATIMA CAROLINA VALENCIA ENRIQUEZ | M18: 29867.91 | O18: =M18*$O$9 -> 1792.0746
B19: Arcos-C | C19: 09/01/2026 | D19: NOE JONAS D CEL | E19: 7503020310205 | F19: Dildo Vibrador Termico Realista 3 en 1 con movimiento Hades-CXO | G19: JUGUETE PROPIO | H19: CXO | I19: 1 | J19: 2500 | L19: GERMAN GUZMAN AGUIRRE | M19: 27728.45 | O19: 0
B20: Arcos-C | C20: 09/01/2026 | D20: NOE JONAS D CEL | E20: 7503020104075 | F20: Vibrador multiorgásmico texturizado con succionador de clítoris Yeni - CXO | G20: JUGUETE PROPIO | H20: CXO | I20: 1 | J20: 2465.52 | L20: HECTOR MANUEL P CELEST | M20: 63104.03 | O20: =M20*$O$9 -> 3786.2418
B21: Arcos-C | C21: 10/01/2026 | D21: NOE JONAS D CEL | E21: 7503043917081 | F21: Blade rosa anillo vibrador - CXO | G21: JUGUETE PROPIO | H21: CXO | I21: 4 | J21: 327.6 | L21: IRIS CRISTINA RIVERA PEREZ CELESTERRA | M21: 43992.56 | O21: =M21*$O$9 -> 2639.5536
B22: Arcos-C | C22: 10/01/2026 | D22: NOE JONAS D CEL | E22: 7503032300443 | F22: Zoe bala vibradora RETAIL - CXO | G22: JUGUETE PROPIO | H22: CXO | I22: 6 | J22: 931.03 | L22: JESáS ULISES PEREZ VARGAS | M22: 25504.32 | O22: =M22*$O$9 -> 1530.2592
B23: Arcos-C | C23: 12/01/2026 | D23: NOE JONAS D CEL | E23: 7503032300443 | F23: Zoe bala vibradora RETAIL - CXO | G23: JUGUETE PROPIO | H23: CXO | I23: 1 | J23: 155.17 | L23: JESUS ALBERTO M GARCIA | M23: 56875 | O23: =M23*$O$9 -> 3412.5
B24: Arcos-C | C24: 13/01/2026 | D24: NOE JONAS D CEL | E24: 7503043917081 | F24: Blade rosa anillo vibrador - CXO | G24: JUGUETE PROPIO | H24: CXO | I24: 3 | J24: 245.7 | L24: MARIA EDUWIGES DEL TORO ORTEGA | M24: 18107.8 | O24: 0
B25: Arcos-C | C25: 13/01/2026 | D25: NOE JONAS D CEL | E25: 7503032300443 | F25: Zoe bala vibradora RETAIL - CXO | G25: JUGUETE PROPIO | H25: CXO | I25: 1 | J25: 155.17 | L25: NICOLAS H ACEVES | M25: 55935.36 | O25: 0
B26: Arcos-C | C26: 14/01/2026 | D26: NOE JONAS D CEL | E26: 7503032300443 | F26: Zoe bala vibradora RETAIL - CXO | G26: JUGUETE PROPIO | H26: CXO | I26: 1 | J26: 155.17 | L26: NINOSCHKA VILLAREAL GONZALEZ | M26: 22323.28 | O26: 0
B27: Arcos-C | C27: 15/01/2026 | D27: NOE JONAS D CEL | E27: 7503043917081 | F27: Blade rosa anillo vibrador - CXO | G27: JUGUETE PROPIO | H27: CXO | I27: 2 | J27: 163.8 | L27: NOE JONAS D CEL | M27: 43051.76 | O27: =M27*$O$9 -> 2583.1056
B28: Arcos-C | C28: 15/01/2026 | D28: NOE JONAS D CEL | E28: USK-V11 | F28: Multiorgasmico con Lenguita Ceci - CXO | G28: JUGUETE PROPIO | H28: CXO | I28: 1 | J28: 2474.14 | L28: OSCAR ANTONIO L CEL | M28: 26637.96 | O28: =M28*$O$9 -> 1598.2776
B29: Arcos-C | C29: 15/01/2026 | D29: NOE JONAS D CEL | E29: 7503032300443 | F29: Zoe bala vibradora RETAIL - CXO | G29: JUGUETE PROPIO | H29: CXO | I29: 1 | J29: 155.17 | L29: Rodolfo Serrano Amezcua | M29: 46551.74 | O29: =M29*$O$9 -> 2793.1044
B30: Arcos-C | C30: 17/01/2026 | D30: NOE JONAS D CEL | E30: 7503030211021 | F30: Anillo desechable para pene Donut - CXO | G30: JUGUETE PROPIO | H30: CXO | I30: 1 | J30: 34.48 | L30: Total general | M30: 783923.73 | O30: =SUM(O10:O29) -> 39589.73
B31: Arcos-C | C31: 17/01/2026 | D31: NOE JONAS D CEL | E31: 7503020111072 | F31: Anillo vibrador recargable con textura negra Hank - CXO | G31: JUGUETE PROPIO | H31: CXO | I31: 1 | J31: 1267.24
B32: Arcos-C | C32: 17/01/2026 | D32: NOE JONAS D CEL | E32: 7503043917081 | F32: Blade rosa anillo vibrador - CXO | G32: JUGUETE PROPIO | H32: CXO | I32: 3 | J32: 245.7
B33: Arcos-C | C33: 17/01/2026 | D33: NOE JONAS D CEL | E33: 7503032300474 | F33: Cola de Zorro 45cm blanco S - CXO | G33: JUGUETE PROPIO | H33: CXO | I33: 1 | J33: 258.62
B34: Arcos-C | C34: 17/01/2026 | D34: NOE JONAS D CEL | E34: 7503020220077 | F34: Juego de mesa sensual para parejas – CXO | G34: JUGUETE PROPIO | H34: CXO | I34: 1 | J34: 637.93
B35: Arcos-C | C35: 17/01/2026 | D35: NOE JONAS D CEL | E35: 7503032300443 | F35: Zoe bala vibradora RETAIL - CXO | G35: JUGUETE PROPIO | H35: CXO | I35: 3 | J35: 465.51
B36: Arcos-C | C36: 21/01/2026 | D36: NOE JONAS D CEL | E36: 7503030211021 | F36: Anillo desechable para pene Donut - CXO | G36: JUGUETE PROPIO | H36: CXO | I36: 1 | J36: 34.48
B37: Arcos-C | C37: 21/01/2026 | D37: NOE JONAS D CEL | E37: 7503024256741 | F37: Cola de Zorro 45cm café S - CXO | G37: JUGUETE PROPIO | H37: CXO | I37: 1 | J37: 258.62
B38: Arcos-C | C38: 21/01/2026 | D38: NOE JONAS D CEL | E38: 7503020202213 | F38: Dildo realista con ventosa Nick - CXO | G38: JUGUETE PROPIO | H38: CXO | I38: 1 | J38: 818.97
B39: Arcos-C | C39: 21/01/2026 | D39: NOE JONAS D CEL | E39: 7503020104076 | F39: Vibrador multiorgásmico con succión y estimulación de punto G Lulu - CXO | G39: JUGUETE PROPIO | H39: CXO | I39: 1 | J39: 2120.69
B40: Arcos-C | C40: 21/01/2026 | D40: NOE JONAS D CEL | E40: 7503032300443 | F40: Zoe bala vibradora RETAIL - CXO | G40: JUGUETE PROPIO | H40: CXO | I40: 2 | J40: 310.34
B41: Arcos-C | C41: 22/01/2026 | D41: NOE JONAS D CEL | E41: 7503043917081 | F41: Blade rosa anillo vibrador - CXO | G41: JUGUETE PROPIO | H41: CXO | I41: 1 | J41: 81.9
B42: Arcos-C | C42: 22/01/2026 | D42: NOE JONAS D CEL | E42: 7503020202214 | F42: Dildo realista con ventosa y testiculos Eddy - CXO | G42: JUGUETE PROPIO | H42: CXO | I42: 1 | J42: 948.28
... B857: Provenza-Cel | C857: 31/01/2026 | D857: ANGEL DANILO RODRIGUEZ LOPEZ | E857: 7503032300443 | F857: Zoe bala vibradora RETAIL - CXO | G857: JUGUETE PROPIO | H857: CXO | I857: 1 | J857: 155.17

Sheet Juguetes
B3: UBICACION | C3: FECHA | D3: VENDEDOR | E3: SKU | F3: ARTICULO | G3: FAMILIA COMERCIAL | H3: MARCA | I3: CANTIDAD | J3: SUBTOT
B4: Arcos-C | C4: 07/01/2026 | D4: NOE JONAS D CEL | E4: 4061504007496 | F4: Succionado con App Curvy 1+ - Satisfayer | G4: JUGUETE | H4: SATISFAYER | I4: 1 | J4: 1810.34
B5: Arcos-C | C5: 09/01/2026 | D5: NOE JONAS D CEL | E5: 716770044532 | F5: Dildo inflable 9.5 - CALEX | G5: JUGUETE | H5: CALEXOTICS | I5: 1 | J5: 1637.93
B6: Arcos-C | C6: 09/01/2026 | D6: NOE JONAS D CEL | E6: 6959633118795 | F6: Edeny - SVAKOM | G6: JUGUETE | H6: SVAKOM | I6: 1 | J6: 3275.86
B7: Arcos-C | C7: 09/01/2026 | D7: NOE JONAS D CEL | E7: 716770096036 | F7: Sheology set intercambiable kegel - CALEX | G7: JUGUETE | H7: CALEXOTICS | I7: 1 | J7: 1637.93
B8: Arcos-C | C8: 10/01/2026 | D8: NOE JONAS D CEL | E8: 7350075026157 | F8: Sona cerise - LELO | G8: JUGUETE | H8: LELO | I8: 1 | J8: 2068.97 | L8: Etiquetas de fila | M8: Suma de SUBTOT | O8: 0.01 | P8: 0.005
B9: Arcos-C | C9: 11/01/2026 | D9: GERMAN GUZMAN AGUIRRE | E9: 4251460601283 | F9: Romp Jazz | G9: JUGUETE | H9: ROMP | I9: 1 | J9: 2155.17 | L9: ALFONSO M CARBALLAR | M9: 5487.06 | O9: =M9*$O$8 -> 54.8706
B10: Arcos-C | C10: 14/01/2026 | D10: NOE JONAS D CEL | E10: 6959633103500 | F10: Chika multiorgasmico turqueza - SVAKOM | G10: JUGUETE | H10: SVAKOM | I10: 1 | J10: 2155.17 | L10: ANGEL DANILO RODRIGUEZ LOPEZ | M10: 24310.32 | O10: =M10*$O$8 -> 243.1032
B11: Arcos-C | C11: 15/01/2026 | D11: NOE JONAS D CEL | E11: 6959633166963 | F11: Ella Neo rojo- SVAKOM | G11: JUGUETE | H11: SVAKOM | I11: 1 | J11: 3017.24 | L11: ANTONIO EDMUNDO E CAMBEROS | M11: 13620.68 | O11: =M11*$O$8 -> 136.2068
B12: Arcos-C | C12: 18/01/2026 | D12: GERMAN GUZMAN AGUIRRE | E12: 6959633118795 | F12: Edeny - SVAKOM | G12: JUGUETE | H12: SVAKOM | I12: 1 | J12: 3275.86 | L12: BERTHA SOFIA O BERMEJO | M12: 15439.67 | O12: =M12*$O$8 -> 154.3967
B13: Arcos-C | C13: 21/01/2026 | D13: NOE JONAS D CEL | E13: 6959633134559 | F13: Phoenix Neo 2 rojo - SVAKOM | G13: JUGUETE | H13: SVAKOM | I13: 1 | J13: 3534.48 | L13: BRYAN ALEJANDRO V BERNAL | M13: 14913.79 | O13: =M13*$O$8 -> 149.1379
B14: Arcos-C | C14: 22/01/2026 | D14: NOE JONAS D CEL | E14: 6959633103500 | F14: Chika multiorgasmico turqueza - SVAKOM | G14: JUGUETE | H14: SVAKOM | I14: 1 | J14: 2155.17 | L14: CELINA HERMILA M GUILLEN | M14: 4275.86 | O14: =M14*$O$8 -> 42.7586
B15: Arcos-C | C15: 23/01/2026 | D15: NOE JONAS D CEL | E15: 7350075028564 | F15: Sila Cruise pink - LELO | G15: JUGUETE | H15: LELO | I15: 1 | J15: 4396.55 | L15: DELIA AGUIRRE CERVANTES | M15: 16293.09 | O15: =M15*$O$8 -> 162.9309
B16: Arcos-C | C16: 24/01/2026 | D16: NOE JONAS D CEL | E16: 6959633103494 | F16: Mora Neo multiorgasmico rosa - SVAKOM | G16: JUGUETE | H16: SVAKOM | I16: 1 | J16: 1637.93 | L16: EDGAR MOISES A NAVARRO | M16: 24741.36 | O16: =M16*$O$8 -> 247.4136
B17: Arcos-C | C17: 27/01/2026 | D17: NOE JONAS D CEL | E17: 6959633127964 | F17: Sam Neo - SVAKOM | G17: JUGUETE | H17: SVAKOM | I17: 1 | J17: 3017.24 | L17: FATIMA CAROLINA VALENCIA ENRIQUEZ | M17: 27586.19 | O17: =M17*$O$8 -> 275.8619
B18: Arcos-C | C18: 28/01/2026 | D18: NOE JONAS D CEL | E18: 6959633166963 | F18: Ella Neo rojo- SVAKOM | G18: JUGUETE | H18: SVAKOM | I18: 1 | J18: 3017.24 | L18: GERMAN GUZMAN AGUIRRE | M18: 25431.02 | O18: 0
B19: Camino Real -C | C19: 02/01/2026 | D19: JESUS ALBERTO M GARCIA | E19: 7350075027840 | F19: Soraya Wave Magenta - LELO | G19: JUGUETE | H19: LELO | I19: 1 | J19: 5862.07 | L19: HECTOR MANUEL P CELEST | M19: 36849.1 | O19: =M19*$O$8 -> 368.491
B20: Camino Real -C | C20: 03/01/2026 | D20: JESUS ALBERTO M GARCIA | E20: 6959633103500 | F20: Chika multiorgasmico turqueza - SVAKOM | G20: JUGUETE | H20: SVAKOM | I20: 1 | J20: 2155.17 | L20: IRIS CRISTINA RIVERA PEREZ CELESTERRA | M20: 16422.41 | O20: =M20*$O$8 -> 164.2241
B21: Camino Real -C | C21: 04/01/2026 | D21: JESUS ALBERTO M GARCIA | E21: 6959633103494 | F21: Mora Neo multiorgasmico rosa - SVAKOM | G21: JUGUETE | H21: SVAKOM | I21: 1 | J21: 1637.93 | L21: JESáS ULISES PEREZ VARGAS | M21: 10086.2 | O21: =M21*$O$8 -> 100.862
B22: Camino Real -C | C22: 07/01/2026 | D22: JESUS ALBERTO M GARCIA | E22: 7350075029332 | F22: Enigma wave morado - LELO | G22: JUGUETE | H22: LELO | I22: 1 | J22: 5862.07 | L22: JESUS ALBERTO M GARCIA | M22: 31133.62 | O22: =M22*$O$8 -> 311.3362
B23: Camino Real -C | C23: 08/01/2026 | D23: JESUS ALBERTO M GARCIA | E23: 6959633118795 | F23: Edeny - SVAKOM | G23: JUGUETE | H23: SVAKOM | I23: 1 | J23: 3275.86 | L23: MARIA EDUWIGES DEL TORO ORTEGA | M23: 9051.72 | O23: 0
B24: Camino Real -C | C24: 14/01/2026 | D24: JESUS ALBERTO M GARCIA | E24: 6959633103494 | F24: Mora Neo multiorgasmico rosa - SVAKOM | G24: JUGUETE | H24: SVAKOM | I24: 1 | J24: 1637.93 | L24: NICOLAS H ACEVES | M24: 75155.16
B25: Camino Real -C | C25: 16/01/2026 | D25: JESUS ALBERTO M GARCIA | E25: 603912332612 | F25: VIBRADOR ANAL FANTASY VIBRATING ASS BLATER | G25: JUGUETE | H25: PIPEDREAM | I25: 1 | J25: 2081.9 | L25: NINOSCHKA VILLAREAL GONZALEZ | M25: 3672.41 | O25: 0
B26: Camino Real -C | C26: 21/01/2026 | D26: JESUS ALBERTO M GARCIA | E26: 6959633166963 | F26: Ella Neo rojo- SVAKOM | G26: JUGUETE | H26: SVAKOM | I26: 1 | J26: 3017.24 | L26: NOE JONAS D CEL | M26: 33362.05 | O26: =M26*$O$8 -> 333.6205
B27: Camino Real -C | C27: 23/01/2026 | D27: JESUS ALBERTO M GARCIA | E27: 6959633156926 | F27: Kit Vibrador Phoenix Neo + BDSM Edición Limitada- Svakom | G27: JUGUETE | H27: SVAKOM | I27: 1 | J27: 5603.45 | L27: OSCAR ANTONIO L CEL | M27: 15431.03 | O27: =M27*$O$8 -> 154.3103
B28: Circunvalación CELESTERRA | C28: 02/01/2026 | D28: ANGEL DANILO RODRIGUEZ LOPEZ | E28: 6959633105320 | F28: Vibrador de Prostata con Calefaccion Vick Neo 2 - SVAKOM | G28: JUGUETE | H28: SVAKOM | I28: 1 | J28: 2155.17 | L28: Rodolfo Serrano Amezcua | M28: 3448.27 | O28: =M28*$O$8 -> 34.4827
B29: Circunvalación CELESTERRA | C29: 03/01/2026 | D29: IRIS CRISTINA RIVERA PEREZ CELESTERRA | E29: 6959633127964 | F29: Sam Neo - SVAKOM | G29: JUGUETE | H29: SVAKOM | I29: 1 | J29: 3017.24 | L29: Total general | M29: 406711.01 | O29: =SUM(O9:O28) -> 2934.007
B30: Circunvalación CELESTERRA | C30: 13/01/2026 | D30: IRIS CRISTINA RIVERA PEREZ CELESTERRA | E30: 6959633103494 | F30: Mora Neo multiorgasmico rosa - SVAKOM | G30: JUGUETE | H30: SVAKOM | I30: 1 | J30: 1637.93
B31: Circunvalación CELESTERRA | C31: 13/01/2026 | D31: IRIS CRISTINA RIVERA PEREZ CELESTERRA | E31: 6959633134559 | F31: Phoenix Neo 2 rojo - SVAKOM | G31: JUGUETE | H31: SVAKOM | I31: 1 | J31: 3534.48
B32: Circunvalación CELESTERRA | C32: 14/01/2026 | D32: IRIS CRISTINA RIVERA PEREZ CELESTERRA | E32: 4061504007496 | F32: Succionado con App Curvy 1+ - Satisfayer | G32: JUGUETE | H32: SATISFAYER | I32: 1 | J32: 1810.34
B33: Circunvalación CELESTERRA | C33: 16/01/2026 | D33: IRIS CRISTINA RIVERA PEREZ CELESTERRA | E33: 4061504007533 | F33: Succionador con App Love Triangle - Satisfayer | G33: JUGUETE | H33: SATISFAYER | I33: 2 | J33: 2931.04
B34: Circunvalación CELESTERRA | C34: 22/01/2026 | D34: IRIS CRISTINA RIVERA PEREZ CELESTERRA | E34: 4061504051604 | F34: Succionador Cutie Heart - Satisfayer | G34: JUGUETE | H34: SATISFAYER | I34: 1 | J34: 1896.55
B35: Circunvalación CELESTERRA | C35: 26/01/2026 | D35: GERMAN GUZMAN AGUIRRE | E35: 7350075026157 | F35: Sona cerise - LELO | G35: JUGUETE | H35: LELO | I35: 1 | J35: 2068.97
B36: Circunvalación CELESTERRA | C36: 31/01/2026 | D36: IRIS CRISTINA RIVERA PEREZ CELESTERRA | E36: 8433345113111 | F36: Vibrador dual con succionador - WOOMY | G36: JUGUETE | H36: ADRIEN LASTIC | I36: 1 | J36: 1594.83
B37: Conchitas CEL | C37: 03/01/2026 | D37: HECTOR MANUEL P CELEST | E37: 4061504007496 | F37: Succionado con App Curvy 1+ - Satisfayer | G37: JUGUETE | H37: SATISFAYER | I37: 1 | J37: 1810.34
B38: Conchitas CEL | C38: 03/01/2026 | D38: HECTOR MANUEL P CELEST | E38: 6959633104668 | F38: Vibrador Ava Neo Rosa Durazno - SVAKOM | G38: JUGUETE | H38: SVAKOM | I38: 1 | J38: 1810.34
B39: Conchitas CEL | C39: 03/01/2026 | D39: HECTOR MANUEL P CELEST | E39: 6959633105313 | F39: Vibrador de Prostata con Pulsaciones Iker Neo - SVAKOM | G39: JUGUETE | H39: SVAKOM | I39: 1 | J39: 3879.31
B40: Conchitas CEL | C40: 06/01/2026 | D40: HECTOR MANUEL P CELEST | E40: 4251460601283 | F40: Romp Jazz | G40: JUGUETE | H40: ROMP | I40: 1 | J40: 2155.17
B41: Conchitas CEL | C41: 08/01/2026 | D41: HECTOR MANUEL P CELEST | E41: 7350075029288 | F41: HUGO 2 Remote Green - LELO | G41: JUGUETE | H41: LELO | I41: 1 | J41: 5172.41
... B148: Provenza-Cel | C148: 30/01/2026 | D148: BRYAN ALEJANDRO V BERNAL | E148: 4061504007496 | F148: Succionado con App Curvy 1+ - Satisfayer | G148: JUGUETE | H148: SATISFAYER | I148: 1 | J148: 1810.34

Sheet SUPERVISOR
C1: ESQUEMA DE COMISIONES 2026 supervisor
E3: CUMPLIMIENTO | F3: Cumplimiento Cuota | G3: Ticket promedio | H3: Unidades por ticket | I3: CXO / LUA | J3: JUGUETES ARRIBA DE 1500 ANTES DE IVA | K3: DUSA | L3: PASTILLA SHUMATSU | M3: Lenceria
E4: MENOR AL 60% | F4: ESQUEMA DE ENCARGADO DE BOUTIQUE
E5: 60% AL 74% | F5: 0.003 | G5: 0.0005 | H5: 0.0005 | I5: 0.01 | J5: 0.005 | K5: 0.01 | L5: 0.01 | M5: 0.01
E6: 70% AL 79% | F6: 0.003 | G6: 0.0015 | H6: 0.0015 | I6: 0.01 | J6: 0.003 | K6: 0.01 | L6: 0.01 | M6: 0.01
E7: 80% AL 90% | F7: 0.004 | G7: 0.002 | H7: 0.002 | I7: 0.015 | J7: 0.005 | K7: 0.015 | L7: 0.015 | M7: 0.015
E8: 91% AL 110% | F8: 0.005 | G8: 0.0035 | H8: 0.0035 | I8: 0.015 | J8: 0.005 | K8: 0.015 | L8: 0.015 | M8: 0.015
E9: 110% En adelante | F9: 0.006 | G9: 0.004 | H9: 0.004 | I9: 0.02 | J9: 0.005 | K9: 0.02 | L9: 0.02 | M9: 0.02
C12: CUMPLIMIENTO | D12: PPTO VENTA | E12: Cumplimiento Cuota | F12: PPTO TICKET | G12: Ticket promedio | H12: PPTO UNIDADES | I12: Unidades por ticket | J12: CXO | K12: JUGUETES ARRIBA DE 1500 ANTES DE IVA | L12: DUSA | M12: SHUMA | N12: LENCERIA | O12: COMISION GENERADA
C13: VENTA GENERADA | D13: =ERECTUS!C92 -> 2680000 | E13: =ERECTUS!D92 -> 2192751 | F13: 1500 | G13: 1025.31 | H13: 3 | I13: 1.9 | J13: =SUMIF('BASE GENERAL'!H4:H3114,SUPERVISOR!J12,'BASE GENERAL'!J4:J3114) -> 783923.73 | K13: =GETPIVOTDATA("SUBTOT",Juguetes!$L$8) -> 406711.01 | L13: =GETPIVOTDATA("SUBTOT",DUSA!$L$7) -> 572978.04 | M13: =GETPIVOTDATA("SUBTOT",Pastilla!$L$9) -> 164035.56 | N13: =SUMIF('BASE GENERAL'!G4:G3114,SUPERVISOR!N12,'BASE GENERAL'!J4:J3114) -> 35576.71 | O13: =O15 -> 36345.021
B14: NICK | C14: =E13/D13 -> 0.81819068 | D14: ESQUEMA DE ENCARGADO DE BOUTIQUE
D15: =E13/D13 -> 0.81819068 | E15: =$E$13*F7 -> 8771.004 | F15: =$G$13/$F$13 -> 0.68354 | G15: =E13*G5 -> 1096.3755 | H15: =$I$13/$H$13 -> 0.63333333 | I15: =E13*H5 -> 1096.3755 | J15: =$J$13*I7 -> 11758.856 | K15: =$K$13*J7 -> 2033.5551 | L15: =L13*K7 -> 8594.6706 | M15: =$M$13*L7 -> 2460.5334 | N15: =$N$13*M7 -> 533.65065 | O15: =E15+G15+I15+J15+K15+L15+M15+N15 -> 36345.021
