Workbook
Name AÑO: [1]FILTROS!$A$1:$A$6
Name base: #REF!

Sheet Pedidos
A1: Número de pedido | B1: Estado del pedido | C1: Fecha del pedido | D1: Sucursal | E1: Importe total del pedido | F1: Sucursal | G1: Product Name
A2: 58160 | B2: Enviado | C2: 45716.987 | D2: 306 | E2: 2000 | F2: SAUCES | G2: Vigorizante masculino Rigidex 2 tabletas - Dusa
A3: 58123 | B3: Enviado | C3: 45713.772 | D3: 306 | E3: 1511 | F3: SAUCES | G3: Masturbador Realista Boca Real Mouth Stroker
A4: 58117 | B4: Enviado | C4: 45713.554 | D4: 300 | E4: 204 | F4: PLAZA CONCHITAS | G4: W50 Schmidt Schuler 60 pzs
A5: 58095 | B5: Enviado | C5: 45712.729 | D5: 286 | E5: 580 | F5: HIDALGO | G5: Lubricante Body Surf DUSA 60ml - Cereza
A6: 57883 | B6: Enviado | C6: 45701.585 | D6: 310 | E6: 449 | F6: PROVENZA | G6: Feromonas Exclusive Diamante - Spray 25 ml - Ella
A7: 57821 | B7: Enviado | C7: 45698.789 | D7: 306 | E7: 449 | F7: SAUCES | G7: Concentrado de feromonas - Diamante - Hombre
A8: 57785 | B8: Enviado | C8: 45695.831 | D8: 300 | E8: 198 | F8: PLAZA CONCHITAS | G8: Bolis divertido y con un sabor delicioso
A9: 57752 | B9: Enviado | C9: 45694.512 | D9: 312 | E9: 920 | F9: ZENTER | G9: Crema retardante Prolong Delay Creme
A10: 57737 | B10: Cancelado | C10: 45693.398 | D10: 312 | E10: 7100 | F10: ZENTER | G10: Succionador Classic 2 Marilyn Monroe Edition Red
A11: 57732 | B11: Cancelado | C11: 45692.584 | D11: 312 | E11: 860 | F11: ZENTER | G11: Retardante en crema Sta Erect Delay Creme 56g (2 oz.)
A12: 57731 | B12: Cancelado | C12: 45692.471 | D12: 312 | E12: 900 | F12: ZENTER | G12: Succionador de clitoris Kevin - CXO
A13: 57718 | B13: Enviado | C13: 45691.817 | D13: 306 | E13: 250 | F13: SAUCES | G13: Látigo negro Cat-O-Nine Tails - Pipedream

Sheet ERECTUS
I1: x
H2: CUMPLIMIENTO | I2: Cumplimiento Cuota | J2: JUGUETES ARRIBA DE 1500 ANTES DE IVA | K2: CXO / LUA | L2: DUSA | M2: PASTILLA DUSA
H3: MENOR AL 69% | I3: 0 | J3: 0 | K3: 0 | L3: 0 | M3: 0
B4: TIENDAS / BLOQUES DE CUMPLIMIENTO PPTO MENSUAL | H4: 70% AL 75% | I4: 0.005 | J4: 0.005 | K4: 0.03 | L4: 0.01 | M4: 0.03
C5: Bloque 1 | D5: Bloque 2 | E5: Bloque 3 | F5: Bloque 4 | H5: 76 % AL 80% | I5: 0.01 | J5: 0.0075 | K5: 0.045 | L5: 0.015 | M5: 0.045
B6: PORCENTAJES | C6: 75 A 79 % | D6: 80% a 89% | E6: 90 A 109% | F6: 110% en adelante | H6: 81% AL 100% | I6: 0.02 | J6: 0.01 | K6: 0.06 | L6: 0.02 | M6: 0.06
B7: Venta Total | C7: 0.0075 | D7: 0.0125 | E7: 0.02 | F7: 0.025 | H7: 110% en Adelante | I7: 0.025 | J7: 0.01 | K7: 0.06 | L7: 0.02 | M7: 0.06
C11: PRESUPUESTO | D11: VENTA | E11: % ALCANCE | F11: CUMPLIMIENTO | I11: PAGO DE COMISIONES | P11: PAGO
B12: Sucursal | C12: Presupuesto | D12: Venta | E12: Venta | F12: EMPLEADO | G12: Venta por vendedor | H12: VTA ECOMMERCE | I12: CUOTA MENSUAL | J12: Juguetes en General $ 1,500 | K12: CXO | L12: DUSA | M12: PASTILLA SHUMA | N12: SEMANAL | O12: BONO PREMIO CXO | P12: SUBTOTAL | Q12: % ALCANCE VS LA VENTA | R12: % DE ALCANCE VS LA VTA GLOBAL
B13: ARCOS | C13: 185000 | D13: 186925.3 | E13: =D13/C13 -> 1.010407 | F13: ANGEL DANILO RODRIGUEZ LOPEZ | G13: 5689.65 | P13: =SUM(I13:O13) -> 0
F14: NOE JONAS D CEL | G14: 181235.65 | I14: =G14*E7 -> 3624.713 | J14: 295.6895 | K14: 4414.2468 | L14: 527.2392 | M14: 1420.8714 | N14: ='[2]SEMANA 2'!$M$6+'[2]SEMANA 1'!$N$6 -> 1059.7177 | P14: =SUM(I14:O14) -> 11342.478 | Q14: =P14/D13 -> 0.0606792 | R14: =P14/$D$91 -> 0.0047402312
P15: =SUM(I15:O15) -> 0
P16: =SUM(I16:O16) -> 0
P17: =SUM(I17:O17) -> 0
P18: =SUM(I18:O18) -> 0
B19: CAMINO REAL | C19: 180000 | D19: 194209.58 | E19: =D19/C19 -> 1.0789421 | F19: ALFONSO M CARBALLAR | G19: 35900.83 | P19: =SUM(I19:O19) -> 0
F20: JESUS ALBERTO M GARCIA | G20: 158308.75 | I20: =G20*E7 -> 3166.175 | J20: 224.9999 | K20: 3106.5876 | L20: 735.8568 | M20: 1767.4254 | N20: ='[2]SEMANA 2'!$M$7+'[2]SEMANA 1'!$N$7 -> 1014.6607 | P20: =SUM(I20:O20) -> 10015.705 | Q20: =P20/D19 -> 0.051571634 | R20: =P20/$D$91 -> 0.0041857485
P21: =SUM(I21:O21) -> 0
P22: =SUM(I22:O22) -> 0
B23: CIRCUNVALACION | C23: 130000 | D23: 126090.94 | E23: =D23/C23 -> 0.96993031 | F23: ANGEL DANILO RODRIGUEZ LOPEZ | G23: 8642.25 | P23: =SUM(I23:O23) -> 0
F24: GERMAN GUZMAN AGUIRRE | G24: 12370.68 | P24: =SUM(I24:O24) -> 0
F25: IRIS CRISTINA RIVERA PEREZ CELESTERRA | G25: 96314.5 | I25: =G25*E7 -> 1926.29 | J25: 99.1378 | K25: 2460.2598 | L25: 456.0306 | M25: 311.8986 | P25: =SUM(I25:O25) -> 5253.6168 | Q25: =P25/D23 -> 0.0416653 | R25: =P25/$D$91 -> 0.0021955836
F26: LAURA KARINA RIVAS RADA | G26: 8763.51 | P26: =SUM(I26:O26) -> 0
P27: =SUM(I27:O27) -> 0
P28: =SUM(I28:O28) -> 0
B29: CONCHITAS | C29: 185000 | D29: 183425.03 | E29: =D29/C29 -> 0.99148665 | F29: ALFONSO M CARBALLAR | G29: 7728.44 | P29: =SUM(I29:O29) -> 0
F30: GERMAN GUZMAN AGUIRRE | G30: 9965.52 | P30: =SUM(I30:O30) -> 0
F31: HECTOR MANUEL P CELEST | G31: 165731.07 | I31: =G31*E7 -> 3314.6214 | J31: 382.7585 | K31: 3111.9822 | L31: 681.3752 | M31: 623.7972 | N31: ='[2]SEMANA 3'!$O$10 -> 463.6243 | P31: =SUM(I31:O31) -> 8578.1588 | Q31: =P31/D29 -> 0.046766566 | R31: =P31/$D$91 -> 0.0035849712
P32: =SUM(I32:O32) -> 0
P33: =SUM(I33:O33) -> 0
B34: FEDERALISMO | C34: 125000 | D34: 83315.13 | E34: =D34/C34 -> 0.66652104 | F34: ANGEL DANILO RODRIGUEZ LOPEZ | G34: 6159.46 | P34: =SUM(I34:O34) -> 0
F35: GERMAN GUZMAN AGUIRRE | G35: 2604.02 | P35: =SUM(I35:O35) -> 0
F36: MARIA EDUWIGES DEL TORO ORTEGA | G36: 74551.65 | P36: =SUM(I36:O36) -> 0
P37: =SUM(I37:O37) -> 0
P38: =SUM(I38:O38) -> 0
B39: HIDALGO | C39: 123500 | D39: 88749.83 | E39: =D39/C39 -> 0.71862211 | F39: CELINA HERMILA M GUILLEN | G39: 66939.48 | I39: =G39*I4 -> 334.6974 | J39: 39.6551 | K39: 1595.694 | L39: 378.4446 | M39: 381.2094 | P39: =SUM(I39:O39) -> 2729.7005 | Q39: =P39/D39 -> 0.030757248 | R39: =P39/$D$91 -> 0.0011407923
F40: GERMAN GUZMAN AGUIRRE | G40: 21465.52 | P40: =SUM(I40:O40) -> 0
F41: LAURA KARINA RIVAS RADA | G41: 344.83 | P41: =SUM(I41:O41) -> 0
P42: =SUM(I42:O42) -> 0
P43: =SUM(I43:O43) -> 0
B44: REYES | C44: 110000 | D44: 68978.3 | E44: =D44/C44 -> 0.62707545 | F44: ANGEL DANILO RODRIGUEZ LOPEZ | G44: 6387.92 | P44: =SUM(I44:O44) -> 0
F45: GERMAN GUZMAN AGUIRRE | G45: 3275.86 | P45: =SUM(I45:O45) -> 0
F46: NINOSCHKA VILLAREAL GONZALEZ | G46: 59314.52 | P46: =SUM(I46:O46) -> 0
P47: =SUM(I47:O47) -> 0
B48: LEON 1 | C48: 132500 | D48: 80560.36 | E48: =D48/C48 -> 0.60800272 | F48: Rodolfo Serrano Amezcua | G48: 80560.36 | J48: 56.0345 | K48: 2460.7794 | L48: 256.8948 | M48: 554.4864 | P48: =SUM(I48:O48) -> 3328.1951 | Q48: =P48/D48 -> 0.041313061 | R48: =P48/$D$91 -> 0.0013909143
P49: =SUM(I49:O49) -> 0
B50: NACIONES UNIDAS | C50: 160000 | D50: 92292.13 | E50: =D50/C50 -> 0.57682581 | F50: EDGAR MOISES A NAVARRO | G50: 92292.13 | J50: 35.3448 | K50: 2564.2218 | L50: 310.3424 | M50: 450.5202 | P50: =SUM(I50:O50) -> 3360.4292 | Q50: =P50/D50 -> 0.036410788 | R50: =P50/$D$91 -> 0.0014043855
P51: =SUM(I51:O51) -> 0
P52: =SUM(I52:O52) -> 0
B53: PATRIA | C53: 185000 | D53: 139202.5 | E53: =D53/C53 -> 0.75244595 | F53: ANGEL DANILO RODRIGUEZ LOPEZ | G53: 387.93 | P53: =SUM(I53:O53) -> 0
F54: ANTONIO EDMUNDO E CAMBEROS | G54: 120180.93 | I54: =G54*C7 -> 901.35697 | J54: 120.6895 | K54: 2835.5178 | L54: 488.0996 | M54: 935.6958 | P54: =SUM(I54:O54) -> 5281.3597 | Q54: =P54/D53 -> 0.037940121 | R54: =P54/$D$91 -> 0.0022071779
F55: GERMAN GUZMAN AGUIRRE | G55: 18633.64 | P55: =SUM(I55:O55) -> 0
P56: =SUM(I56:O56) -> 0
P57: =SUM(I57:O57) -> 0
P58: =SUM(I58:O58) -> 0
B59: ALAMO | C59: 130000 | D59: 108497.66 | E59: =D59/C59 -> 0.83459738 | F59: ANGEL DANILO RODRIGUEZ LOPEZ | G59: 17387.9 | P59: =SUM(I59:O59) -> 0
F60: DELIA AGUIRRE CERVANTES | G60: 87652.88 | I60: =G60*D7 -> 1095.661 | K60: 2614.3974 | L60: 393.9624 | M60: 381.2094 | P60: =SUM(I60:O60) -> 4485.2302 | Q60: =P60/D59 -> 0.041339419 | R60: =P60/$D$91 -> 0.0018744607
F61: NICOLAS H ACEVES | G61: 3456.88 | P61: =SUM(I61:O61) -> 0
P62: =SUM(I62:O62) -> 0
B63: PLAZA CONCHITAS | C63: 150000 | D63: 169873.04 | E63: =D63/C63 -> 1.1324869 | F63: ALFONSO M CARBALLAR | G63: 20525.82 | P63: =SUM(I63:O63) -> 0
F64: GERMAN GUZMAN AGUIRRE | G64: 5784.48 | P64: =SUM(I64:O64) -> 0
F65: OSCAR ANTONIO L CEL | G65: 143562.74 | I65: =G65*F7 -> 3589.0685 | J65: 256.0343 | K65: 2636.9286 | L65: 738.788 | M65: 1074.3174 | N65: ='[2]SEMANA 2'!$M$18+'[2]SEMANA 1'!$N$18+'[2]SEMANA 4'!$N$19 -> 1362.5024 | P65: =SUM(I65:O65) -> 9657.6392 | Q65: =P65/D63 -> 0.056852101 | R65: =P65/$D$91 -> 0.004036106
P66: =SUM(I66:O66) -> 0
B67: MADISON | C67: 150000 | D67: 137443.88 | E67: =D67/C67 -> 0.91629253 | F67: ALFONSO M CARBALLAR | G67: 19353.43 | P67: =SUM(I67:O67) -> 0
F68: BERTHA SOFIA O BERMEJO | G68: 118090.45 | I68: =G68*E7 -> 2361.809 | J68: 125.862 | K68: 2673.6198 | L68: 358.6176 | M68: 935.6958 | P68: =SUM(I68:O68) -> 6455.6042 | Q68: =P68/D67 -> 0.046969019 | R68: =P68/$D$91 -> 0.0026979164
P69: =SUM(I69:O69) -> 0
P70: =SUM(I70:O70) -> 0
B71: LAS TORRES | C71: 150000 | D71: 153297.99 | E71: =D71/C71 -> 1.0219866 | F71: ANGEL DANILO RODRIGUEZ LOPEZ | G71: 6457.49 | P71: =SUM(I71:O71) -> 0
F72: GERMAN GUZMAN AGUIRRE | G72: 18465.5 | P72: =SUM(I72:O72) -> 0
F73: JESáS ULISES PEREZ VARGAS | G73: 128375 | I73: =G73*E7 -> 2567.5 | J73: 132.7585 | K73: 2859.051 | L73: 618.2712 | M73: 1005.0066 | N73: ='[2]SEMANA 1'!$N$19 -> 423.0615 | P73: =SUM(I73:O73) -> 7605.6488 | Q73: =P73/D71 -> 0.049613493 | R73: =P73/$D$91 -> 0.0031785413
P74: =SUM(I74:O74) -> 0
B75: SAUCES | C75: 150000 | D75: 122850.91 | E75: =D75/C75 -> 0.81900607 | F75: ALFONSO M CARBALLAR | G75: 10267.25 | P75: =SUM(I75:O75) -> 0
F76: FATIMA CAROLINA VALENCIA ENRIQUEZ | G76: 98570.7 | I76: =G76*D7 -> 1232.1337 | J76: 21.5517 | K76: 1585.3452 | L76: 488.7896 | M76: 1005.0066 | N76: ='[2]SEMANA 3'!$O$22 -> 350.0865 | P76: =SUM(I76:O76) -> 4682.9133 | Q76: =P76/D75 -> 0.03811867 | R76: =P76/$D$91 -> 0.0019570761
F77: GERMAN GUZMAN AGUIRRE | G77: 1681.04 | P77: =SUM(I77:O77) -> 0
F78: LAURA KARINA RIVAS RADA | G78: 12331.92 | P78: =SUM(I78:O78) -> 0
P79: =SUM(I79:O79) -> 0
B80: ZENTER | C80: 355000 | D80: 297227.83 | E80: =D80/C80 -> 0.83726149 | F80: ALFONSO M CARBALLAR | G80: 46784.43 | P80: =SUM(I80:O80) -> 0
F81: ANGEL DANILO RODRIGUEZ LOPEZ | G81: 15379 | P81: =SUM(I81:O81) -> 0
F82: LAURA KARINA RIVAS RADA | G82: 42527.98 | P82: =SUM(I82:O82) -> 0
F83: NICOLAS H ACEVES | G83: 192536.42 | I83: =SUPERVISOR!E15+SUPERVISOR!G15+SUPERVISOR!I15+SUPERVISOR!N15 -> 12398.935 | J83: =SUPERVISOR!K15 -> 1691.0765 | K83: =SUPERVISOR!J15 -> 13657.506 | L83: =SUPERVISOR!L15 -> 7431.4151 | M83: =SUPERVISOR!M15 -> 3812.094 | P83: =SUM(I83:O83) -> 38991.027 | Q83: =P83/D80 -> 0.13118229 | R83: =P83/$D$91 -> 0.016295071
B84: PROVENZA | C84: 150000 | D84: 159870.66 | E84: =D84/C84 -> 1.0658044 | F84: ALFONSO M CARBALLAR | G84: 2793.09 | P84: =SUM(I84:O84) -> 0
F85: ANGEL DANILO RODRIGUEZ LOPEZ | G85: 23961.21 | P85: =SUM(I85:O85) -> 0
F86: BRYAN ALEJANDRO V BERNAL | G86: 133116.36 | I86: =G86*E7 -> 2662.3272 | J86: 281.0343 | K86: 3334.398 | L86: 468.9624 | M86: 450.5202 | N86: ='[2]SEMANA 3'!$O$24 -> 390.4742 | P86: =SUM(I86:O86) -> 7587.7163 | Q86: =P86/D84 -> 0.047461594 | R86: =P86/$D$91 -> 0.003171047
P87: =SUM(I87:O87) -> 0
B88: ALFONSO M CARBALLAR | C88: 120000 | D88: =G88 -> 143353.29 | E88: =D88/C88 -> 1.1946107 | F88: ALFONSO M CARBALLAR | G88: =G19+G29+G63+G67+G75+G80+G84 -> 143353.29 | I88: =G88*F7 -> 3583.8322 | J88: 190.5171 | K88: 3915.2532 | L88: 591.3754 | M88: 1108.9728 | P88: =SUM(I88:O88) -> 9389.9507 | Q88: =P88/D88 -> 0.065502164 | R88: =P88/D91 -> 0.0039242341
B89: ANGEL DANILO RODRIGUEZ LOPEZ | C89: 120000 | D89: =G89 -> 90452.81 | E89: =D89/C89 -> 0.75377342 | F89: ANGEL DANILO RODRIGUEZ LOPEZ | G89: =G13+G23+G34+G44+G53+G59+G71+G81+G85 -> 90452.81 | I89: =G89*I4 -> 452.26405 | J89: 83.4051 | K89: 898.4655 | L89: 196.5504 | M89: 277.2432 | P89: =SUM(I89:O89) -> 1907.9282 | Q89: =P89/D89 -> 0.021093079 | R89: =P89/$D$91 -> 0.0007973585
B90: GERMAN GUZMAN AGUIRRE | C90: 120000 | D90: =G90 -> 94246.26 | E90: =D90/C90 -> 0.7853855 | F90: GERMAN GUZMAN AGUIRRE | G90: =G24+G30+G35+G40+G45+G55+G64+G72+G77 -> 94246.26 | I90: =G90*I5 -> 942.4626 | J90: 10.34485 | K90: 1844.4452 | L90: 311.6358 | M90: 571.8141 | P90: =SUM(I90:O90) -> 3680.7025 | Q90: =P90/D90 -> 0.039054096 | R90: =P90/D91 -> 0.0015382336
C91: =SUM(C13:C87) -> 2751000 | D91: =SUM(D13:D87) -> 2392811.1 | E91: =D91/C91 -> 0.86979683 | G91: =SUM(G3:G87) -> 2392811.1 | H91: =SUM(H13:H90) -> 0 | I91: =SUM(I13:I90) -> 44153.847 | J91: =SUM(J13:J90) -> 4046.8939 | K91: =SUM(K13:K90) -> 58568.699 | L91: =SUM(L13:L90) -> 15432.651 | M91: =SUM(M13:M90) -> 17067.784 | N91: =SUM(N13:N90) -> 5064.1273 | O91: =SUM(O13:O90) -> 0 | P91: =SUM(P13:P90) -> 144334 | R91: =P91/D91 -> 0.060319849
H93: % de participación | I93: =I91/D91 -> 0.018452709 | J93: =J91/D91 -> 0.0016912718 | K93: =K91/D91 -> 0.024476943 | L93: =L91/D91 -> 0.0064495903 | M93: =M91/D91 -> 0.0071329428 | N93: =N91/D91 -> 0.0021163925 | O93: =O91/D91 -> 0 | P93: =P91/D91 -> 0.060319849

Sheet cuentas bancarias
B3: BANCO | C3: SUCURSAL | D3: EMPLEADO | E3: DEPOSITAR | G3: DIF | H3: ADEUDO
B4: SANTANDER | C4: ARCOS | D4: NOE JONAS D CEL | E4: 10995 | G4: =K4-E4 -> -10995 | H4: 200 | K4: =ERECTUS!P17 -> 0
B5: SANTANDER | C5: FEDERALIMO | D5: MARIA EDUWIGES DEL TORO ORTEGA | E5: 1300 | G5: =K5-E5 -> -1300 | K5: =ERECTUS!P34 -> 0
B6: SANTANDER | C6: HIDALGO | D6: CELINA HERMILA M GUILLEN | E6: 2378.8382 | G6: =K6-E6 -> -2378.8382 | K6: =ERECTUS!P40 -> 0
B7: SANTANDER | C7: REYES | D7: NINOSCHKA VILLAREAL GONZALEZ | E7: 500 | G7: =K7-E7 -> -500 | H7: 630 | K7: =ERECTUS!P45 -> 0
B8: SANTANDER | C8: LAS TORRES | D8: JESáS ULISES PEREZ VARGAS | E8: 5990 | G8: =K8-E8 -> 0 | K8: 5990
B9: SANTANDER | C9: HIDALGO | D9: ALFONSO M CARBALLAR | E9: 4150 | G9: =K9-E9 -> 5239.9507 | H9: 173 | K9: =ERECTUS!P88 -> 9389.9507
C10: PLAZA CONCHITAS | D10: OSCAR ANTONIO L CEL | E10: 5005 | G10: =K10-E10 -> -5005 | H10: 2002 | K10: =ERECTUS!P64 -> 0
C11: PROVENZA | D11: BRAYAN | E11: 3150 | G11: =K11-E11 -> -3150 | H11: 500 | K11: =ERECTUS!P87 -> 0
C13: SUCURSAL | D13: EMPLEADO | E13: IMPORTE
B14: SANTANDER | C14: CIRCUNVAALCION | D14: IRIS CRISTINA RIVERA PEREZ CELESTERRA | E14: 12304 | G14: =K14-E14 -> -12304 | K14: =ERECTUS!P23 -> 0
B15: SANTANDER | C15: PATRIA 1 | D15: ANGEL DANILO RODRIGUEZ LOPEZ | E15: 1252 | G15: =K15-E15 -> 4029.3597 | K15: =ERECTUS!P54 -> 5281.3597
B16: SANTANDER | C16: MADISON | D16: BERTHA SOFIA O BERMEJO | E16: 5464 | G16: =K16-E16 -> -5464 | K16: =ERECTUS!P67 -> 0
B17: SANTANDER | C17: SAUCES | D17: FATIMA CAROLINA VALENCIA ENRIQUEZ | E17: 11615 | G17: =K17-E17 -> -11615 | K17: =ERECTUS!P78 -> 0
B18: SANTANDER | C18: ZENTER | D18: NICOLAS H ACEVES | E18: 22722 | G18: =K18-E18 -> -22722 | K18: =ERECTUS!P81 -> 0
B19: SANTANDER | C19: NACIONES | D19: EDGAR MOISES A NAVARRO | E19: 5420 | G19: =K19-E19 -> -2059.5708 | K19: =ERECTUS!P50 -> 3360.4292
B20: SANTANDER | C20: CAMINO REAL | D20: JESUS ALBERTO M GARCIA | E20: 5222 | G20: =K20-E20 -> -5222 | K20: =ERECTUS!P22 -> 0
B21: SANTANDER | C21: CONCHITAS | D21: HECTOR | E21: 5860 | G21: =K21-E21 -> -5860 | K21: =ERECTUS!P29 -> 0
B22: BANCOMER | C22: LEON 1 | D22: RODOLFO | E22: 10300 | G22: =K22-E22 -> -6971.8049 | H22: 1032 | K22: =ERECTUS!P48 -> 3328.1951
E25: =SUM(E4:E24) -> 113627.84 | G25: =SUM(G4:G24) -> -86277.903 | H25: =SUM(H4:H24) -> 4537 | K25: =SUM(K4:K24) -> 27349.935

Sheet SUPERVISOR
C1: ESQUEMA DE COMISIONES 2024 supervisor
E3: CUMPLIMIENTO | F3: Cumplimiento Cuota | G3: Ticket promedio | H3: Unidades por ticket | I3: CXO / LUA | J3: JUGUETES ARRIBA DE 1500 ANTES DE IVA | K3: DUSA | L3: PASTILLA SHUMATSU | M3: Lenceria
E4: MENOR AL 60% | F4: ESQUEMA DE ENCARGADO DE BOUTIQUE
E5: 60% AL 74% | F5: 0.003 | G5: 0.0005 | H5: 0.0005 | I5: 0.01 | J5: 0.005 | K5: 0.01 | L5: 0.01 | M5: 0.01
E6: 70% AL 79% | F6: 0.003 | G6: 0.0015 | H6: 0.0015 | I6: 0.01 | J6: 0.003 | K6: 0.01 | L6: 0.01 | M6: 0.01
E7: 80% AL 90% | F7: 0.004 | G7: 0.002 | H7: 0.002 | I7: 0.015 | J7: 0.005 | K7: 0.015 | L7: 0.015 | M7: 0.015
E8: 91% AL 110% | F8: 0.005 | G8: 0.0035 | H8: 0.0035 | I8: 0.015 | J8: 0.005 | K8: 0.015 | L8: 0.015 | M8: 0.015
E9: 110% En adelante | F9: 0.006 | G9: 0.004 | H9: 0.004 | I9: 0.02 | J9: 0.005 | K9: 0.02 | L9: 0.02 | M9: 0.02
C12: CUMPLIMIENTO | D12: PPTO VENTA | E12: Cumplimiento Cuota | F12: PPTO TICKET | G12: Ticket promedio | H12: PPTO UNIDADES | I12: Unidades por ticket | J12: CXO / LUA | K12: JUGUETES ARRIBA DE 1500 ANTES DE IVA | L12: DUSA | M12: SHUMA | N12: Lenceria | O12: COMISION GENERADA
C13: VENTA GENERADA | D13: =ERECTUS!C91 -> 2751000 | E13: =ERECTUS!D91 -> 2392811.1 | F13: 1500 | G13: 997 | H13: 3 | I13: 2.1 | J13: 910500.4 | K13: 338215.29 | L13: 495427.67 | M13: 254139.6 | N13: 43488 | O13: =O15 -> 38991.027
B14: NICK | C14: MENOR AL 60% | D14: ESQUEMA DE ENCARGADO DE BOUTIQUE
C15: 60% AL 74% | D15: =E13/D13 -> 0.86979683 | E15: =$E$13*F7 -> 9571.2443 | F15: =$G$13/$F$13 -> 0.66466667 | G15: =E13*G5 -> 1196.4055 | H15: =$I$13/$H$13 -> 0.7 | I15: =E13*H5 -> 1196.4055 | J15: =$J$13*I7 -> 13657.506 | K15: =$K$13*J7 -> 1691.0765 | L15: =$L$13*K7 -> 7431.4151 | M15: =$M$13*L7 -> 3812.094 | N15: =$N$13*M5 -> 434.88 | O15: =E15+G15+I15+J15+K15+L15+M15+N15 -> 38991.027
C16: 75 % AL 79% | E16: 0 | G16: 0 | O16: =E16+G16+I16+J16+K16+L16+M16+N16+#REF! -> #REF!
C17: 80% AL 90% | E17: 0 | G17: 0 | O17: =E17+G17+I17+J17+K17+L17+M17+N17+#REF! -> #REF!
C18: 91% AL 110% | E18: 0 | G18: 0 | H18: 0 | O18: =E18+G18+I18+J18+K18+L18+M18+N18+#REF! -> #REF!
C19: 111% En adelante | E19: 0 | G19: 0 | O19: =E19+G19+I19+J19+K19+L19+M19+N19+#REF! -> #REF!

Sheet Hoja1
B3: DEUDA NETA | C3: IVA | D3: TOTAL | G3: ADEUDOS DE SERVICIOS DE FRANQUICIAS
B4: 1400000 | C4: =B4*16% -> 224000 | D4: =C4+B4 -> 1624000 | G4: Tienda | H4: Motivo | I4: Monto | J4: Fecha Bimestre | K4: Días de Corte | L4: Estatus
B5: ABONOS FECHA | C5: IMPORTE | D5: SUMA ABONOS | E5: PENDIENTE POR LIQUIDAR | G5: Camino Real | H5: CFE | I5: 1716 | J5: ADEUDO MAYO | K5: Totalidad | L5: PAGADO
B6: 45488 | C6: 405384 | D6: =C6 -> 405384 | E6: =D4-C6 -> 1218616 | G6: Alamo | H6: CFE | I6: 2924 | J6: ABR 24-25 JUN 24 | K6: 43 | L6: PAGADO
B7: 45513 | C7: 366601.44 | D7: =D6+C7 -> 771985.44 | E7: =E6-C7 -> 852014.56 | G7: Las Torres | H7: CFE | I7: 2153.9 | J7: ABR 24-24 JUN 24 | K7: 42 | L7: PAGADO
B8: 45568 | C8: 100000 | D8: =D7+C8 -> 871985.44 | E8: =E7-C8 -> 752014.56 | G8: Circunvalación | H8: CFE | I8: 4007 | J8: ABR 24-13 JUN 24 | K8: Totalidad | L8: PAGADO
B9: 45587 | C9: 100000 | D9: =D8+C9 -> 971985.44 | E9: =E8-C9 -> 652014.56 | G9: Circunvalación | H9: SIAPA | I9: 13023.06 | J9: 01 NOV 22 - 02 JUN 24 | K9: Totalidad | L9: PAGADO
B10: 45603 | C10: 100000 | D10: =D9+C10 -> 1071985.4 | E10: =E9-C10 -> 552014.56 | G10: Circunvalación | H10: LICENCIA | I10: 3666.83 | J10: RECARGOS | K10: Totalidad | L10: PAGADO
B11: 45617 | C11: 100064.97 | D11: =D10+C11 -> 1172050.4 | E11: =E10-C11 -> 451949.59 | G11: Las Torres | H11: LICENCIA | I11: 7704.03 | J11: RECARGOS | K11: Totalidad | L11: PAGADO
B12: 45666 | C12: 100002.14 | D12: =D11+C12 -> 1272052.5 | E12: =E11-C12 -> 351947.45 | G12: Camino Real | H12: LICENCIA | I12: 63000 | J12: RECARGOS 2019 A 2024 | K12: Totalidad | L12: PENDIENTE POR PAGAR
B13: 45701 | C13: 99999.78 | D13: =D12+C13 -> 1372052.3 | E13: =E12-C13 -> 251947.67 | G13: TOTAL | I13: =SUM(I5:I12) -> 98194.82
B14: 45757 | C14: 100000 | D14: =D13+C14 -> 1472052.3 | E14: =E13-C14 -> 151947.67
B15: RECARGOS CFE Y LICENCIAS | C15: =I13 -> 98194.82 | D15: =D14+C15 -> 1570247.1 | E15: =E14-C15 -> 53752.85
B16: FACTURA DAMSA | C16: 23203.52 | D16: =D15+C16 -> 1593450.7 | E16: =E15-C16 -> 30549.33
B18: TOTALES | C18: =SUM(C6:C16) -> 1593450.7 | E18: =D4-C18 -> 30549.33

Sheet ZONA
C5: SUCURSAL | D5: PPTO | E5: VTAS | H5: SUCURSAL | I5: PPTO | J5: VTAS | K5: RAPPI
B6: NICOLAS | C6: Zenter | D6: =ERECTUS!C80 -> 355000 | E6: =ERECTUS!D80 -> 297227.83 | G6: EDMUNDO | H6: Camino Real | I6: 250000 | J6: 188172.43
C7: Conchitas | D7: =ERECTUS!C29 -> 185000 | E7: =ERECTUS!D29 -> 183425.03 | H7: Arcos | I7: 245000 | J7: 143456.8 | K7: 3625.0086
C8: Federalismo | D8: =ERECTUS!C34 -> 125000 | E8: =ERECTUS!D34 -> 83315.13 | H8: Hidalgo | I8: 150000 | J8: 79563.58
C9: Sauces | D9: =ERECTUS!C75 -> 150000 | E9: =ERECTUS!D75 -> 122850.91 | H9: Hotel Reyes | I9: 130000 | J9: 49412.908 | K9: 1163.8017
C10: Alamo | D10: =ERECTUS!C59 -> 130000 | E10: =ERECTUS!D59 -> 108497.66 | H10: Leon 1 | I10: 100000 | J10: 62806.356 | K10: 750
C11: Circunvalación | D11: =ERECTUS!C23 -> 130000 | E11: =ERECTUS!D23 -> 126090.94 | H11: Naciones | I11: 165000 | J11: 86410.89 | K11: 1413.7931
C12: PATRIA 1 | D12: =ERECTUS!C53 -> 185000 | E12: 79402 | H12: Patria 2 | I12: 110000 | J12: 37934.993
C13: P.Conchitas | D13: =ERECTUS!C63 -> 150000 | E13: =ERECTUS!D63 -> 169873.04 | H13: Las Torres | I13: 180000 | J13: 121764.89
C14: Madison | D14: =ERECTUS!C67 -> 150000 | E14: =ERECTUS!#REF! -> #REF! | H14: Provenza | I14: 165000 | J14: 81034.111
H15: pastillas | J15: 25862.07
C18: NI | E18: =SUM(D6:D14) -> 1560000 | H18: EDMUNDO | J18: =SUM(I6:I15) -> 1495000
C19: vta | E19: =SUM(E6:E14) -> #REF! | H19: vta | J19: =J6+J7+J8+J9+J10+J11+J12+J13+J14+J15+K11+K10+K9+K7 -> 883371.63 | K19: =J18*60% -> 897000
C20: % d ealcance | E20: =E19/E18 -> #REF! | J20: =J19/J18 -> 0.59088403
K21: =K19-J19 -> 13628.37
D23: CUMPLIMIENTO | E23: CXO / LUA | F23: JUGUETES ARRIBA DE 1500 ANTES DE IVA | G23: DUSA | H23: PASTILLA SHUMATSU | I23: Lenceria
D24: 60% AL 74% | E24: 0.005 | F24: 0.0025 | G24: 0.005 | H24: 0.005 | I24: 0.005
D25: 75 % AL 79% | E25: 0.01 | F25: 0.005 | G25: 0.01 | H25: 0.01 | I25: 0.01
J26: =J18*60% -> 897000

Sheet ecommerce
B3: Número de pedido | C3: Estado del pedido | D3: Fecha del pedido | E3: Sucursal | F3: Importe total del pedido | G3: Sucursal | H3: Product Name
B4: 60291 | C4: Enviado | D4: 45866.437 | E4: 429 | F4: 671 | G4: 429 | H4: Aceites de Almendras para masaje con Feromonas - Diamante
B5: 60283 | C5: Enviado | D5: 45863.777 | E5: 306 | F5: 3430 | G5: sauces | H5: Vibrador multiorgásmico con succionador y textura suave Paty – CXO
B6: 60208 | C6: Enviado | D6: 45852.622 | E6: 306 | F6: 2560 | G6: sauces | H6: Vibrador tipo c con control remoto rosa Maia - CXO
B7: 60122 | C7: Enviado | D7: 45850.837 | E7: 306 | F7: 3087 | G7: sauces | H7: Vibrador e impulsor morado The Thruster
B8: 60102 | C8: Enviado | D8: 45845.771 | E8: 306 | F8: 2070 | G8: sauces | H8: Dildo flexible Oliver 18cm - CXO
B9: 60098 | C9: Enviado | D9: 45843.826 | E9: 312 | F9: 1100 | G9: zenter | H9: Kit de amarre para cama bondage - CXO
B10: 60090 | C10: Enviado | D10: 45842.547 | E10: 306 | F10: 1254 | G10: sauces | H10: Estimulador de clitoris Colette - CXO
B11: 60062 | C11: Enviado | D11: 45839.587 | E11: 312 | F11: 1130 | G11: zenter | H11: Dildo flexible Oliver 18cm - CXO
E14: sauces | F14: =F5+F6+F7+F8+F10 -> 12401
E15: zenter | F15: =F11+F9 -> 2230
